{
  "id": "632e6cca9e465e566c05802a",
  "datasetId": "632e6c9aff5edd8643bb923f",
  "url": "https://gate.dataloop.ai/api/v1/items/632e6cca9e465e566c05802a",
  "dataset": "https://gate.dataloop.ai/api/v1/datasets/632e6c9aff5edd8643bb923f",
  "createdAt": "2022-09-24T02:34:50.000Z",
  "dir": "/2020",
  "filename": "/2020/m_3712141_ne_10_060_20200525_325-small_2020.png",
  "type": "file",
  "hidden": false,
  "metadata": {
    "system": {
      "size": 2073448,
      "taskStatusLog": [
        {
          "status": {
            "taskId": "632e91ec7eb1331d49af333f",
            "assignmentId": "632e91ed7eb1334452af3341",
            "status": "completed",
            "creator": "lewis.kalata@es.cloudfactory.com",
            "timestamp": "2022-09-26T19:30:34.042Z"
          },
          "action": "created"
        },
        {
          "status": {
            "taskId": "6332d9662335fd3b124025ac",
            "assignmentId": "6332d9662335fd52304025ad",
            "status": "approved",
            "creator": "jackline.ogutu@es.cloudfactory.com",
            "timestamp": "2022-09-27T15:16:04.192Z"
          },
          "action": "created"
        }
      ],
      "mimetype": "image/png",
      "isBinary": true,
      "channels": 4,
      "exif": {},
      "height": 1175,
      "thumbnailId": "632e6ce36f165b77e1083c48",
      "width": 1174,
      "refs": [
        {
          "id": "632e91ec7eb1331d49af333f",
          "type": "task",
          "metadata": {
            "creator": "lewis.kalata@es.cloudfactory.com",
            "status": "completed",
            "timestamp": "2022-09-26T19:30:34.042Z"
          }
        },
        {
          "id": "632e91ed7eb1334452af3341",
          "type": "assignment",
          "metadata": {
            "creator": "lewis.kalata@es.cloudfactory.com",
            "status": "completed",
            "timestamp": "2022-09-26T19:30:34.042Z"
          }
        },
        {
          "id": "6332d9662335fd3b124025ac",
          "type": "task",
          "metadata": {
            "creator": "jackline.ogutu@es.cloudfactory.com",
            "status": "approved",
            "timestamp": "2022-09-27T15:16:04.192Z"
          }
        },
        {
          "id": "6332d9662335fd52304025ad",
          "type": "assignment",
          "metadata": {
            "creator": "jackline.ogutu@es.cloudfactory.com",
            "status": "approved",
            "timestamp": "2022-09-27T15:16:04.192Z"
          }
        },
        {
          "id": "6336a0a324e1aadd24e5f4ef",
          "type": "task"
        },
        {
          "id": "6336a0a324e1aa0830e5f4f1",
          "type": "assignment"
        }
      ]
    },
    "user": {
      "coordinates": "37.3315707299744, -121.92127778084",
      "image_year": 2020
    }
  },
  "name": "m_3712141_ne_10_060_20200525_325-small_2020.png",
  "creator": "rubiks@dataloop.ai",
  "stream": "https://gate.dataloop.ai/api/v1/items/632e6cca9e465e566c05802a/stream",
  "thumbnail": "https://gate.dataloop.ai/api/v1/items/632e6cca9e465e566c05802a/thumbnail",
  "annotations": [
    {
      "id": "6331fdd8526e5c0f79d27fda",
      "datasetId": "632e6c9aff5edd8643bb923f",
      "itemId": "632e6cca9e465e566c05802a",
      "url": "https://gate.dataloop.ai/api/v1/annotations/6331fdd8526e5c0f79d27fda",
      "item": "https://gate.dataloop.ai/api/v1/items/632e6cca9e465e566c05802a",
      "dataset": "https://gate.dataloop.ai/api/v1/datasets/632e6c9aff5edd8643bb923f",
      "type": "point",
      "label": "model_found_building",
      "attributes": [],
      "coordinates": {
        "x": 956.5805208477725,
        "y": 720.6835395629572,
        "z": 0
      },
      "metadata": {
        "system": {
          "startTime": 0,
          "endTime": 0,
          "frame": 0,
          "endFrame": 0,
          "snapshots_": [],
          "clientId": "e599fb5c-0f2b-48b0-a3a1-faec5935fe12",
          "automated": false,
          "objectId": "6",
          "isOpen": false,
          "isOnlyLocal": false,
          "attributes": {},
          "system": false,
          "itemLinks": [],
          "openAnnotationVersion": "1.47.1-prod.3",
          "recipeId": "632e6c9b433d0b508cde9dbc",
          "taskId": "632e91ec7eb1331d49af333f",
          "assignmentId": "632e91ed7eb1334452af3341",
          "coordinateVersion": "v1"
        },
        "user": {}
      },
      "creator": "lewis.kalata@es.cloudfactory.com",
      "createdAt": "2022-09-26T19:30:32.681Z",
      "updatedBy": "lewis.kalata@es.cloudfactory.com",
      "updatedAt": "2022-09-26T19:30:32.681Z",
      "hash": "74060db276898a24fed518aa7ca116d63a52b310",
      "source": "ui"
    },
    {
      "id": "6331fdd8526e5c3151d27fe1",
      "datasetId": "632e6c9aff5edd8643bb923f",
      "itemId": "632e6cca9e465e566c05802a",
      "url": "https://gate.dataloop.ai/api/v1/annotations/6331fdd8526e5c3151d27fe1",
      "item": "https://gate.dataloop.ai/api/v1/items/632e6cca9e465e566c05802a",
      "dataset": "https://gate.dataloop.ai/api/v1/datasets/632e6c9aff5edd8643bb923f",
      "type": "point",
      "label": "building_missed_by_model",
      "attributes": [],
      "coordinates": {
        "x": 773.4904331406337,
        "y": 542.4358691647083,
        "z": 0
      },
      "metadata": {
        "system": {
          "startTime": 0,
          "endTime": 0,
          "frame": 0,
          "endFrame": 0,
          "snapshots_": [],
          "clientId": "253622e9-48a1-420c-af83-dd18d2f1d0a1",
          "automated": false,
          "objectId": "10",
          "isOpen": false,
          "isOnlyLocal": false,
          "attributes": {},
          "system": false,
          "itemLinks": [],
          "openAnnotationVersion": "1.47.1-prod.3",
          "recipeId": "632e6c9b433d0b508cde9dbc",
          "taskId": "632e91ec7eb1331d49af333f",
          "assignmentId": "632e91ed7eb1334452af3341",
          "coordinateVersion": "v1"
        },
        "user": {}
      },
      "creator": "lewis.kalata@es.cloudfactory.com",
      "createdAt": "2022-09-26T19:30:32.692Z",
      "updatedBy": "lewis.kalata@es.cloudfactory.com",
      "updatedAt": "2022-09-26T19:30:32.692Z",
      "hash": "c9dbdca9ced4e88aeef9f935ad71483438c8d014",
      "source": "ui"
    },
    {
      "id": "6331fdd8526e5c21e7d27fd5",
      "datasetId": "632e6c9aff5edd8643bb923f",
      "itemId": "632e6cca9e465e566c05802a",
      "url": "https://gate.dataloop.ai/api/v1/annotations/6331fdd8526e5c21e7d27fd5",
      "item": "https://gate.dataloop.ai/api/v1/items/632e6cca9e465e566c05802a",
      "dataset": "https://gate.dataloop.ai/api/v1/datasets/632e6c9aff5edd8643bb923f",
      "type": "point",
      "label": "model_found_building",
      "attributes": [],
      "coordinates": {
        "x": 624.1524356110439,
        "y": 1153.9984540490289,
        "z": 0
      },
      "metadata": {
        "system": {
          "startTime": 0,
          "endTime": 0,
          "frame": 0,
          "endFrame": 0,
          "snapshots_": [],
          "clientId": "ce5268cd-b0e1-4f36-a554-348ef4bcbadb",
          "automated": false,
          "objectId": "1",
          "isOpen": false,
          "isOnlyLocal": false,
          "attributes": {},
          "system": false,
          "itemLinks": [],
          "openAnnotationVersion": "1.47.1-prod.3",
          "recipeId": "632e6c9b433d0b508cde9dbc",
          "taskId": "632e91ec7eb1331d49af333f",
          "assignmentId": "632e91ed7eb1334452af3341",
          "coordinateVersion": "v1"
        },
        "user": {}
      },
      "creator": "lewis.kalata@es.cloudfactory.com",
      "createdAt": "2022-09-26T19:30:32.672Z",
      "updatedBy": "lewis.kalata@es.cloudfactory.com",
      "updatedAt": "2022-09-26T19:30:32.672Z",
      "hash": "12ccb8540719529afd51f71d5a15d5c84517005d",
      "source": "ui"
    },
    {
      "id": "6331fdd8526e5c805cd27fe3",
      "datasetId": "632e6c9aff5edd8643bb923f",
      "itemId": "632e6cca9e465e566c05802a",
      "url": "https://gate.dataloop.ai/api/v1/annotations/6331fdd8526e5c805cd27fe3",
      "item": "https://gate.dataloop.ai/api/v1/items/632e6cca9e465e566c05802a",
      "dataset": "https://gate.dataloop.ai/api/v1/datasets/632e6c9aff5edd8643bb923f",
      "type": "point",
      "label": "model_found_building",
      "attributes": [],
      "coordinates": {
        "x": 1056.4478414153027,
        "y": 214.76357933242366,
        "z": 0
      },
      "metadata": {
        "system": {
          "startTime": 0,
          "endTime": 0,
          "frame": 0,
          "endFrame": 0,
          "snapshots_": [],
          "clientId": "84302eb8-bf40-4d28-a385-666d4669a92f",
          "automated": false,
          "objectId": "15",
          "isOpen": false,
          "isOnlyLocal": false,
          "attributes": {},
          "system": false,
          "itemLinks": [],
          "openAnnotationVersion": "1.47.1-prod.3",
          "recipeId": "632e6c9b433d0b508cde9dbc",
          "taskId": "632e91ec7eb1331d49af333f",
          "assignmentId": "632e91ed7eb1334452af3341",
          "coordinateVersion": "v1"
        },
        "user": {}
      },
      "creator": "lewis.kalata@es.cloudfactory.com",
      "createdAt": "2022-09-26T19:30:32.695Z",
      "updatedBy": "lewis.kalata@es.cloudfactory.com",
      "updatedAt": "2022-09-26T19:30:32.695Z",
      "hash": "d0ebb76e84dac9e95dc080f0258e8a729ed33d06",
      "source": "ui"
    },
    {
      "id": "6331fdd8526e5c57abd27fe5",
      "datasetId": "632e6c9aff5edd8643bb923f",
      "itemId": "632e6cca9e465e566c05802a",
      "url": "https://gate.dataloop.ai/api/v1/annotations/6331fdd8526e5c57abd27fe5",
      "item": "https://gate.dataloop.ai/api/v1/items/632e6cca9e465e566c05802a",
      "dataset": "https://gate.dataloop.ai/api/v1/datasets/632e6c9aff5edd8643bb923f",
      "type": "point",
      "label": "building_missed_by_model",
      "attributes": [],
      "coordinates": {
        "x": 1008.5947503100278,
        "y": 262.0687668827765,
        "z": 0
      },
      "metadata": {
        "system": {
          "startTime": 0,
          "endTime": 0,
          "frame": 0,
          "endFrame": 0,
          "snapshots_": [],
          "clientId": "8afbe75b-a5d0-44d6-b73a-93351bd177ba",
          "automated": false,
          "objectId": "17",
          "isOpen": false,
          "isOnlyLocal": false,
          "attributes": {},
          "system": false,
          "itemLinks": [],
          "openAnnotationVersion": "1.47.1-prod.3",
          "recipeId": "632e6c9b433d0b508cde9dbc",
          "taskId": "632e91ec7eb1331d49af333f",
          "assignmentId": "632e91ed7eb1334452af3341",
          "coordinateVersion": "v1"
        },
        "user": {}
      },
      "creator": "lewis.kalata@es.cloudfactory.com",
      "createdAt": "2022-09-26T19:30:32.698Z",
      "updatedBy": "lewis.kalata@es.cloudfactory.com",
      "updatedAt": "2022-09-26T19:30:32.698Z",
      "hash": "359d2c5e38938030e4d9774ed23d4f2d2ff44cd0",
      "source": "ui"
    },
    {
      "id": "6331fdd8526e5c35d9d27fd7",
      "datasetId": "632e6c9aff5edd8643bb923f",
      "itemId": "632e6cca9e465e566c05802a",
      "url": "https://gate.dataloop.ai/api/v1/annotations/6331fdd8526e5c35d9d27fd7",
      "item": "https://gate.dataloop.ai/api/v1/items/632e6cca9e465e566c05802a",
      "dataset": "https://gate.dataloop.ai/api/v1/datasets/632e6c9aff5edd8643bb923f",
      "type": "point",
      "label": "model_found_new_building",
      "attributes": [],
      "coordinates": {
        "x": 668.8846729485834,
        "y": 1094.2171730788027,
        "z": 0
      },
      "metadata": {
        "system": {
          "startTime": 0,
          "endTime": 0,
          "frame": 0,
          "endFrame": 0,
          "snapshots_": [],
          "clientId": "6b8c7dff-c8d4-4274-a697-3193029e5ce4",
          "automated": false,
          "objectId": "2",
          "isOpen": false,
          "isOnlyLocal": false,
          "attributes": {},
          "system": false,
          "itemLinks": [],
          "openAnnotationVersion": "1.47.1-prod.3",
          "recipeId": "632e6c9b433d0b508cde9dbc",
          "taskId": "632e91ec7eb1331d49af333f",
          "assignmentId": "632e91ed7eb1334452af3341",
          "coordinateVersion": "v1"
        },
        "user": {}
      },
      "creator": "lewis.kalata@es.cloudfactory.com",
      "createdAt": "2022-09-26T19:30:32.676Z",
      "updatedBy": "lewis.kalata@es.cloudfactory.com",
      "updatedAt": "2022-09-26T19:30:32.676Z",
      "hash": "3a45eeb1903aca0e37d5bc975d6a32ab38eb872d",
      "source": "ui"
    },
    {
      "id": "6331fdd8526e5c35d9d27fd8",
      "datasetId": "632e6c9aff5edd8643bb923f",
      "itemId": "632e6cca9e465e566c05802a",
      "url": "https://gate.dataloop.ai/api/v1/annotations/6331fdd8526e5c35d9d27fd8",
      "item": "https://gate.dataloop.ai/api/v1/items/632e6cca9e465e566c05802a",
      "dataset": "https://gate.dataloop.ai/api/v1/datasets/632e6c9aff5edd8643bb923f",
      "type": "point",
      "label": "building_missed_by_model",
      "attributes": [],
      "coordinates": {
        "x": 1045.5248532282292,
        "y": 650.50551407617,
        "z": 0
      },
      "metadata": {
        "system": {
          "startTime": 0,
          "endTime": 0,
          "frame": 0,
          "endFrame": 0,
          "snapshots_": [],
          "clientId": "3ac7e8b5-3d5d-4a5f-98f5-9093fc2d8d48",
          "automated": false,
          "objectId": "5",
          "isOpen": false,
          "isOnlyLocal": false,
          "attributes": {},
          "system": false,
          "itemLinks": [],
          "openAnnotationVersion": "1.47.1-prod.3",
          "recipeId": "632e6c9b433d0b508cde9dbc",
          "taskId": "632e91ec7eb1331d49af333f",
          "assignmentId": "632e91ed7eb1334452af3341",
          "coordinateVersion": "v1"
        },
        "user": {}
      },
      "creator": "lewis.kalata@es.cloudfactory.com",
      "createdAt": "2022-09-26T19:30:32.678Z",
      "updatedBy": "lewis.kalata@es.cloudfactory.com",
      "updatedAt": "2022-09-26T19:30:32.678Z",
      "hash": "b2ff7192fbacf4d2f7f173b3bcf86510e130265b",
      "source": "ui"
    },
    {
      "id": "6331fdd8526e5c091fd27fde",
      "datasetId": "632e6c9aff5edd8643bb923f",
      "itemId": "632e6cca9e465e566c05802a",
      "url": "https://gate.dataloop.ai/api/v1/annotations/6331fdd8526e5c091fd27fde",
      "item": "https://gate.dataloop.ai/api/v1/items/632e6cca9e465e566c05802a",
      "dataset": "https://gate.dataloop.ai/api/v1/datasets/632e6c9aff5edd8643bb923f",
      "type": "point",
      "label": "building_missed_by_model",
      "attributes": [],
      "coordinates": {
        "x": 859.3139117533551,
        "y": 452.504029096455,
        "z": 0
      },
      "metadata": {
        "system": {
          "startTime": 0,
          "endTime": 0,
          "frame": 0,
          "endFrame": 0,
          "snapshots_": [],
          "clientId": "26b313ee-accf-44eb-9a85-4ed564ed7a02",
          "automated": false,
          "objectId": "11",
          "isOpen": false,
          "isOnlyLocal": false,
          "attributes": {},
          "system": false,
          "itemLinks": [],
          "openAnnotationVersion": "1.47.1-prod.3",
          "recipeId": "632e6c9b433d0b508cde9dbc",
          "taskId": "632e91ec7eb1331d49af333f",
          "assignmentId": "632e91ed7eb1334452af3341",
          "coordinateVersion": "v1"
        },
        "user": {}
      },
      "creator": "lewis.kalata@es.cloudfactory.com",
      "createdAt": "2022-09-26T19:30:32.687Z",
      "updatedBy": "lewis.kalata@es.cloudfactory.com",
      "updatedAt": "2022-09-26T19:30:32.687Z",
      "hash": "9305f3f28fc1f595ee4b382d9b5b293b2922206f",
      "source": "ui"
    },
    {
      "id": "6331fdd8526e5c543dd27fef",
      "datasetId": "632e6c9aff5edd8643bb923f",
      "itemId": "632e6cca9e465e566c05802a",
      "url": "https://gate.dataloop.ai/api/v1/annotations/6331fdd8526e5c543dd27fef",
      "item": "https://gate.dataloop.ai/api/v1/items/632e6cca9e465e566c05802a",
      "dataset": "https://gate.dataloop.ai/api/v1/datasets/632e6c9aff5edd8643bb923f",
      "type": "point",
      "label": "building_missed_by_model",
      "attributes": [],
      "coordinates": {
        "x": 746.8187273152348,
        "y": 152.8321443934477,
        "z": 0
      },
      "metadata": {
        "system": {
          "startTime": 0,
          "endTime": 0,
          "frame": 0,
          "endFrame": 0,
          "snapshots_": [],
          "clientId": "91904807-c72e-49a2-975f-9eb4c6303b24",
          "automated": false,
          "objectId": "30",
          "isOpen": false,
          "isOnlyLocal": false,
          "attributes": {},
          "system": false,
          "itemLinks": [],
          "openAnnotationVersion": "1.47.1-prod.3",
          "recipeId": "632e6c9b433d0b508cde9dbc",
          "taskId": "632e91ec7eb1331d49af333f",
          "assignmentId": "632e91ed7eb1334452af3341",
          "coordinateVersion": "v1"
        },
        "user": {}
      },
      "creator": "lewis.kalata@es.cloudfactory.com",
      "createdAt": "2022-09-26T19:30:32.719Z",
      "updatedBy": "lewis.kalata@es.cloudfactory.com",
      "updatedAt": "2022-09-26T19:30:32.719Z",
      "hash": "b67491e3ad4ce61d283ed827be3e488bcd5ea81c",
      "source": "ui"
    },
    {
      "id": "6331fdd8526e5c1b2cd27feb",
      "datasetId": "632e6c9aff5edd8643bb923f",
      "itemId": "632e6cca9e465e566c05802a",
      "url": "https://gate.dataloop.ai/api/v1/annotations/6331fdd8526e5c1b2cd27feb",
      "item": "https://gate.dataloop.ai/api/v1/items/632e6cca9e465e566c05802a",
      "dataset": "https://gate.dataloop.ai/api/v1/datasets/632e6c9aff5edd8643bb923f",
      "type": "point",
      "label": "model_found_building",
      "attributes": [],
      "coordinates": {
        "x": 759.302142386176,
        "y": 116.96337581131202,
        "z": 0
      },
      "metadata": {
        "system": {
          "startTime": 0,
          "endTime": 0,
          "frame": 0,
          "endFrame": 0,
          "snapshots_": [],
          "clientId": "1b155aad-dc73-4955-9ddd-d5763ccf927c",
          "automated": false,
          "objectId": "24",
          "isOpen": false,
          "isOnlyLocal": false,
          "attributes": {},
          "system": false,
          "itemLinks": [],
          "openAnnotationVersion": "1.47.1-prod.3",
          "recipeId": "632e6c9b433d0b508cde9dbc",
          "taskId": "632e91ec7eb1331d49af333f",
          "assignmentId": "632e91ed7eb1334452af3341",
          "coordinateVersion": "v1"
        },
        "user": {}
      },
      "creator": "lewis.kalata@es.cloudfactory.com",
      "createdAt": "2022-09-26T19:30:32.713Z",
      "updatedBy": "lewis.kalata@es.cloudfactory.com",
      "updatedAt": "2022-09-26T19:30:32.713Z",
      "hash": "1b0083f45f7e97fc24b47e0839d23b89086d811e",
      "source": "ui"
    },
    {
      "id": "6331fdd8526e5c5f97d27ff0",
      "datasetId": "632e6c9aff5edd8643bb923f",
      "itemId": "632e6cca9e465e566c05802a",
      "url": "https://gate.dataloop.ai/api/v1/annotations/6331fdd8526e5c5f97d27ff0",
      "item": "https://gate.dataloop.ai/api/v1/items/632e6cca9e465e566c05802a",
      "dataset": "https://gate.dataloop.ai/api/v1/datasets/632e6c9aff5edd8643bb923f",
      "type": "point",
      "label": "model_found_building",
      "attributes": [],
      "coordinates": {
        "x": 668.2772408272292,
        "y": 187.6612385239273,
        "z": 0
      },
      "metadata": {
        "system": {
          "startTime": 0,
          "endTime": 0,
          "frame": 0,
          "endFrame": 0,
          "snapshots_": [],
          "clientId": "6b3dd2f1-1e98-4731-a8a6-73eb61ef1445",
          "automated": false,
          "objectId": "28",
          "isOpen": false,
          "isOnlyLocal": false,
          "attributes": {},
          "system": false,
          "itemLinks": [],
          "openAnnotationVersion": "1.47.1-prod.3",
          "recipeId": "632e6c9b433d0b508cde9dbc",
          "taskId": "632e91ec7eb1331d49af333f",
          "assignmentId": "632e91ed7eb1334452af3341",
          "coordinateVersion": "v1"
        },
        "user": {}
      },
      "creator": "lewis.kalata@es.cloudfactory.com",
      "createdAt": "2022-09-26T19:30:32.720Z",
      "updatedBy": "lewis.kalata@es.cloudfactory.com",
      "updatedAt": "2022-09-26T19:30:32.720Z",
      "hash": "9c87e00e23c82248824bd9af73ffff05abf1a16d",
      "source": "ui"
    },
    {
      "id": "6331fdd8526e5c3057d27fdd",
      "datasetId": "632e6c9aff5edd8643bb923f",
      "itemId": "632e6cca9e465e566c05802a",
      "url": "https://gate.dataloop.ai/api/v1/annotations/6331fdd8526e5c3057d27fdd",
      "item": "https://gate.dataloop.ai/api/v1/items/632e6cca9e465e566c05802a",
      "dataset": "https://gate.dataloop.ai/api/v1/datasets/632e6c9aff5edd8643bb923f",
      "type": "point",
      "label": "model_found_building",
      "attributes": [],
      "coordinates": {
        "x": 715.7546384375303,
        "y": 498.76954219515176,
        "z": 0
      },
      "metadata": {
        "system": {
          "startTime": 0,
          "endTime": 0,
          "frame": 0,
          "endFrame": 0,
          "snapshots_": [],
          "clientId": "9cd65702-2a0f-4ad3-89f2-ca0710854dff",
          "automated": false,
          "objectId": "8",
          "isOpen": false,
          "isOnlyLocal": false,
          "attributes": {},
          "system": false,
          "itemLinks": [],
          "openAnnotationVersion": "1.47.1-prod.3",
          "recipeId": "632e6c9b433d0b508cde9dbc",
          "taskId": "632e91ec7eb1331d49af333f",
          "assignmentId": "632e91ed7eb1334452af3341",
          "coordinateVersion": "v1"
        },
        "user": {}
      },
      "creator": "lewis.kalata@es.cloudfactory.com",
      "createdAt": "2022-09-26T19:30:32.686Z",
      "updatedBy": "lewis.kalata@es.cloudfactory.com",
      "updatedAt": "2022-09-26T19:30:32.686Z",
      "hash": "7e3399cdebef9e44dc6e7674c6032633b097afef",
      "source": "ui"
    },
    {
      "id": "6331fdd8526e5ca734d27fdb",
      "datasetId": "632e6c9aff5edd8643bb923f",
      "itemId": "632e6cca9e465e566c05802a",
      "url": "https://gate.dataloop.ai/api/v1/annotations/6331fdd8526e5ca734d27fdb",
      "item": "https://gate.dataloop.ai/api/v1/items/632e6cca9e465e566c05802a",
      "dataset": "https://gate.dataloop.ai/api/v1/datasets/632e6c9aff5edd8643bb923f",
      "type": "point",
      "label": "model_found_building",
      "attributes": [],
      "coordinates": {
        "x": 756.3257374180895,
        "y": 523.7217290348983,
        "z": 0
      },
      "metadata": {
        "system": {
          "startTime": 0,
          "endTime": 0,
          "frame": 0,
          "endFrame": 0,
          "snapshots_": [],
          "clientId": "82e94a5f-e1e9-48d6-97e0-2aa07adb939a",
          "automated": false,
          "objectId": "9",
          "isOpen": false,
          "isOnlyLocal": false,
          "attributes": {},
          "system": false,
          "itemLinks": [],
          "openAnnotationVersion": "1.47.1-prod.3",
          "recipeId": "632e6c9b433d0b508cde9dbc",
          "taskId": "632e91ec7eb1331d49af333f",
          "assignmentId": "632e91ed7eb1334452af3341",
          "coordinateVersion": "v1"
        },
        "user": {}
      },
      "creator": "lewis.kalata@es.cloudfactory.com",
      "createdAt": "2022-09-26T19:30:32.683Z",
      "updatedBy": "lewis.kalata@es.cloudfactory.com",
      "updatedAt": "2022-09-26T19:30:32.683Z",
      "hash": "f11c60c96b497422c46ebe14601aeff460aebbd9",
      "source": "ui"
    },
    {
      "id": "6331fdd8526e5c3911d27ff8",
      "datasetId": "632e6c9aff5edd8643bb923f",
      "itemId": "632e6cca9e465e566c05802a",
      "url": "https://gate.dataloop.ai/api/v1/annotations/6331fdd8526e5c3911d27ff8",
      "item": "https://gate.dataloop.ai/api/v1/items/632e6cca9e465e566c05802a",
      "dataset": "https://gate.dataloop.ai/api/v1/datasets/632e6c9aff5edd8643bb923f",
      "type": "point",
      "label": "model_found_building",
      "attributes": [],
      "coordinates": {
        "x": 311.04509218428694,
        "y": 18.714140129809923,
        "z": 0
      },
      "metadata": {
        "system": {
          "startTime": 0,
          "endTime": 0,
          "frame": 0,
          "endFrame": 0,
          "snapshots_": [],
          "clientId": "7dd7331f-12cb-47ff-a917-302fda42f7b9",
          "automated": false,
          "objectId": "37",
          "isOpen": false,
          "isOnlyLocal": false,
          "attributes": {},
          "system": false,
          "itemLinks": [],
          "openAnnotationVersion": "1.47.1-prod.3",
          "recipeId": "632e6c9b433d0b508cde9dbc",
          "taskId": "632e91ec7eb1331d49af333f",
          "assignmentId": "632e91ed7eb1334452af3341",
          "coordinateVersion": "v1"
        },
        "user": {}
      },
      "creator": "lewis.kalata@es.cloudfactory.com",
      "createdAt": "2022-09-26T19:30:32.733Z",
      "updatedBy": "lewis.kalata@es.cloudfactory.com",
      "updatedAt": "2022-09-26T19:30:32.733Z",
      "hash": "c2187cf58bee4b42678e2cb794149c0b1cf73a09",
      "source": "ui"
    },
    {
      "id": "6331fdd8526e5c5e41d27ff6",
      "datasetId": "632e6c9aff5edd8643bb923f",
      "itemId": "632e6cca9e465e566c05802a",
      "url": "https://gate.dataloop.ai/api/v1/annotations/6331fdd8526e5c5e41d27ff6",
      "item": "https://gate.dataloop.ai/api/v1/items/632e6cca9e465e566c05802a",
      "dataset": "https://gate.dataloop.ai/api/v1/datasets/632e6c9aff5edd8643bb923f",
      "type": "point",
      "label": "model_found_building",
      "attributes": [],
      "coordinates": {
        "x": 424.1438518336877,
        "y": 19.233977355637975,
        "z": 0
      },
      "metadata": {
        "system": {
          "startTime": 0,
          "endTime": 0,
          "frame": 0,
          "endFrame": 0,
          "snapshots_": [],
          "clientId": "5d31914b-5d43-4fd5-b582-131e5ecce140",
          "automated": false,
          "objectId": "35",
          "isOpen": false,
          "isOnlyLocal": false,
          "attributes": {},
          "system": false,
          "itemLinks": [],
          "openAnnotationVersion": "1.47.1-prod.3",
          "recipeId": "632e6c9b433d0b508cde9dbc",
          "taskId": "632e91ec7eb1331d49af333f",
          "assignmentId": "632e91ed7eb1334452af3341",
          "coordinateVersion": "v1"
        },
        "user": {}
      },
      "creator": "lewis.kalata@es.cloudfactory.com",
      "createdAt": "2022-09-26T19:30:32.729Z",
      "updatedBy": "lewis.kalata@es.cloudfactory.com",
      "updatedAt": "2022-09-26T19:30:32.729Z",
      "hash": "8e5f3df1e88dce94e836eebe7752a08730201617",
      "source": "ui"
    },
    {
      "id": "6331fdd8526e5c0cc2d27fee",
      "datasetId": "632e6c9aff5edd8643bb923f",
      "itemId": "632e6cca9e465e566c05802a",
      "url": "https://gate.dataloop.ai/api/v1/annotations/6331fdd8526e5c0cc2d27fee",
      "item": "https://gate.dataloop.ai/api/v1/items/632e6cca9e465e566c05802a",
      "dataset": "https://gate.dataloop.ai/api/v1/datasets/632e6c9aff5edd8643bb923f",
      "type": "point",
      "label": "model_found_building",
      "attributes": [],
      "coordinates": {
        "x": 644.3506952745918,
        "y": 212.61342536367385,
        "z": 0
      },
      "metadata": {
        "system": {
          "startTime": 0,
          "endTime": 0,
          "frame": 0,
          "endFrame": 0,
          "snapshots_": [],
          "clientId": "ec85ecc4-863a-419d-94d9-826400449b98",
          "automated": false,
          "objectId": "27",
          "isOpen": false,
          "isOnlyLocal": false,
          "attributes": {},
          "system": false,
          "itemLinks": [],
          "openAnnotationVersion": "1.47.1-prod.3",
          "recipeId": "632e6c9b433d0b508cde9dbc",
          "taskId": "632e91ec7eb1331d49af333f",
          "assignmentId": "632e91ed7eb1334452af3341",
          "coordinateVersion": "v1"
        },
        "user": {}
      },
      "creator": "lewis.kalata@es.cloudfactory.com",
      "createdAt": "2022-09-26T19:30:32.718Z",
      "updatedBy": "lewis.kalata@es.cloudfactory.com",
      "updatedAt": "2022-09-26T19:30:32.718Z",
      "hash": "7ea8f779bbc58d3c907c0f465df51ad436f1ee51",
      "source": "ui"
    },
    {
      "id": "6331fdd8526e5ccc1cd27fe7",
      "datasetId": "632e6c9aff5edd8643bb923f",
      "itemId": "632e6cca9e465e566c05802a",
      "url": "https://gate.dataloop.ai/api/v1/annotations/6331fdd8526e5ccc1cd27fe7",
      "item": "https://gate.dataloop.ai/api/v1/items/632e6cca9e465e566c05802a",
      "dataset": "https://gate.dataloop.ai/api/v1/datasets/632e6c9aff5edd8643bb923f",
      "type": "point",
      "label": "model_found_building",
      "attributes": [],
      "coordinates": {
        "x": 720.811612584107,
        "y": 29.110884646370987,
        "z": 0
      },
      "metadata": {
        "system": {
          "startTime": 0,
          "endTime": 0,
          "frame": 0,
          "endFrame": 0,
          "snapshots_": [],
          "clientId": "ed1963cc-7604-4741-bc94-139019020b02",
          "automated": false,
          "objectId": "23",
          "isOpen": false,
          "isOnlyLocal": false,
          "attributes": {},
          "system": false,
          "itemLinks": [],
          "openAnnotationVersion": "1.47.1-prod.3",
          "recipeId": "632e6c9b433d0b508cde9dbc",
          "taskId": "632e91ec7eb1331d49af333f",
          "assignmentId": "632e91ed7eb1334452af3341",
          "coordinateVersion": "v1"
        },
        "user": {}
      },
      "creator": "lewis.kalata@es.cloudfactory.com",
      "createdAt": "2022-09-26T19:30:32.705Z",
      "updatedBy": "lewis.kalata@es.cloudfactory.com",
      "updatedAt": "2022-09-26T19:30:32.705Z",
      "hash": "79f0cb630f185fe0afef7f0f13f88304c1bd45ae",
      "source": "ui"
    },
    {
      "id": "6331fdd8526e5c78fcd27fd6",
      "datasetId": "632e6c9aff5edd8643bb923f",
      "itemId": "632e6cca9e465e566c05802a",
      "url": "https://gate.dataloop.ai/api/v1/annotations/6331fdd8526e5c78fcd27fd6",
      "item": "https://gate.dataloop.ai/api/v1/items/632e6cca9e465e566c05802a",
      "dataset": "https://gate.dataloop.ai/api/v1/datasets/632e6c9aff5edd8643bb923f",
      "type": "point",
      "label": "model_found_building",
      "attributes": [],
      "coordinates": {
        "x": 1053.8471299421901,
        "y": 708.727283368912,
        "z": 0
      },
      "metadata": {
        "system": {
          "startTime": 0,
          "endTime": 0,
          "frame": 0,
          "endFrame": 0,
          "snapshots_": [],
          "clientId": "c9d2bf7f-6b01-4ab3-8d4e-6fb7b8f27081",
          "automated": false,
          "objectId": "3",
          "isOpen": false,
          "isOnlyLocal": false,
          "attributes": {},
          "system": false,
          "itemLinks": [],
          "openAnnotationVersion": "1.47.1-prod.3",
          "recipeId": "632e6c9b433d0b508cde9dbc",
          "taskId": "632e91ec7eb1331d49af333f",
          "assignmentId": "632e91ed7eb1334452af3341",
          "coordinateVersion": "v1"
        },
        "user": {}
      },
      "creator": "lewis.kalata@es.cloudfactory.com",
      "createdAt": "2022-09-26T19:30:32.674Z",
      "updatedBy": "lewis.kalata@es.cloudfactory.com",
      "updatedAt": "2022-09-26T19:30:32.674Z",
      "hash": "7a62d12c557a3b642dc22f70b81cf9033cb72516",
      "source": "ui"
    },
    {
      "id": "6331fdd8526e5cdc63d27fd9",
      "datasetId": "632e6c9aff5edd8643bb923f",
      "itemId": "632e6cca9e465e566c05802a",
      "url": "https://gate.dataloop.ai/api/v1/annotations/6331fdd8526e5cdc63d27fd9",
      "item": "https://gate.dataloop.ai/api/v1/items/632e6cca9e465e566c05802a",
      "dataset": "https://gate.dataloop.ai/api/v1/datasets/632e6c9aff5edd8643bb923f",
      "type": "point",
      "label": "model_found_building",
      "attributes": [],
      "coordinates": {
        "x": 1101.1800787528425,
        "y": 636.4699089788126,
        "z": 0
      },
      "metadata": {
        "system": {
          "startTime": 0,
          "endTime": 0,
          "frame": 0,
          "endFrame": 0,
          "snapshots_": [],
          "clientId": "3b9480b2-e10e-4070-8fbd-e3cc2c728fd7",
          "automated": false,
          "objectId": "4",
          "isOpen": false,
          "isOnlyLocal": false,
          "attributes": {},
          "system": false,
          "itemLinks": [],
          "openAnnotationVersion": "1.47.1-prod.3",
          "recipeId": "632e6c9b433d0b508cde9dbc",
          "taskId": "632e91ec7eb1331d49af333f",
          "assignmentId": "632e91ed7eb1334452af3341",
          "coordinateVersion": "v1"
        },
        "user": {}
      },
      "creator": "lewis.kalata@es.cloudfactory.com",
      "createdAt": "2022-09-26T19:30:32.679Z",
      "updatedBy": "lewis.kalata@es.cloudfactory.com",
      "updatedAt": "2022-09-26T19:30:32.679Z",
      "hash": "fd7f44036c46962244a0e24660a7e50a609a75d8",
      "source": "ui"
    },
    {
      "id": "6331fdd8526e5c2078d27ff9",
      "datasetId": "632e6c9aff5edd8643bb923f",
      "itemId": "632e6cca9e465e566c05802a",
      "url": "https://gate.dataloop.ai/api/v1/annotations/6331fdd8526e5c2078d27ff9",
      "item": "https://gate.dataloop.ai/api/v1/items/632e6cca9e465e566c05802a",
      "dataset": "https://gate.dataloop.ai/api/v1/datasets/632e6c9aff5edd8643bb923f",
      "type": "point",
      "label": "building_missed_by_model",
      "attributes": [],
      "coordinates": {
        "x": 314.68608824664483,
        "y": 100.32858458481432,
        "z": 0
      },
      "metadata": {
        "system": {
          "startTime": 0,
          "endTime": 0,
          "frame": 0,
          "endFrame": 0,
          "snapshots_": [],
          "clientId": "58b0046e-c16e-4c37-b1d6-83b36e718029",
          "automated": false,
          "objectId": "38",
          "isOpen": false,
          "isOnlyLocal": false,
          "attributes": {},
          "system": false,
          "itemLinks": [],
          "openAnnotationVersion": "1.47.1-prod.3",
          "recipeId": "632e6c9b433d0b508cde9dbc",
          "taskId": "632e91ec7eb1331d49af333f",
          "assignmentId": "632e91ed7eb1334452af3341",
          "coordinateVersion": "v1"
        },
        "user": {}
      },
      "creator": "lewis.kalata@es.cloudfactory.com",
      "createdAt": "2022-09-26T19:30:32.734Z",
      "updatedBy": "lewis.kalata@es.cloudfactory.com",
      "updatedAt": "2022-09-26T19:30:32.734Z",
      "hash": "2d14d53451d6f1272e6020998795baacf1d46f1a",
      "source": "ui"
    },
    {
      "id": "6331fdd8526e5c32d9d27fe2",
      "datasetId": "632e6c9aff5edd8643bb923f",
      "itemId": "632e6cca9e465e566c05802a",
      "url": "https://gate.dataloop.ai/api/v1/annotations/6331fdd8526e5c32d9d27fe2",
      "item": "https://gate.dataloop.ai/api/v1/items/632e6cca9e465e566c05802a",
      "dataset": "https://gate.dataloop.ai/api/v1/datasets/632e6c9aff5edd8643bb923f",
      "type": "point",
      "label": "model_found_building",
      "attributes": [],
      "coordinates": {
        "x": 975.3056434541845,
        "y": 305.735093852333,
        "z": 0
      },
      "metadata": {
        "system": {
          "startTime": 0,
          "endTime": 0,
          "frame": 0,
          "endFrame": 0,
          "snapshots_": [],
          "clientId": "71ce86a9-3d26-43bb-b427-dfb7e9c76927",
          "automated": false,
          "objectId": "13",
          "isOpen": false,
          "isOnlyLocal": false,
          "attributes": {},
          "system": false,
          "itemLinks": [],
          "openAnnotationVersion": "1.47.1-prod.3",
          "recipeId": "632e6c9b433d0b508cde9dbc",
          "taskId": "632e91ec7eb1331d49af333f",
          "assignmentId": "632e91ed7eb1334452af3341",
          "coordinateVersion": "v1"
        },
        "user": {}
      },
      "creator": "lewis.kalata@es.cloudfactory.com",
      "createdAt": "2022-09-26T19:30:32.693Z",
      "updatedBy": "lewis.kalata@es.cloudfactory.com",
      "updatedAt": "2022-09-26T19:30:32.693Z",
      "hash": "97590a4d9a6e9b8f95466567ef6663471516ccb1",
      "source": "ui"
    },
    {
      "id": "6331fdd8526e5c4bbad27fe6",
      "datasetId": "632e6c9aff5edd8643bb923f",
      "itemId": "632e6cca9e465e566c05802a",
      "url": "https://gate.dataloop.ai/api/v1/annotations/6331fdd8526e5c4bbad27fe6",
      "item": "https://gate.dataloop.ai/api/v1/items/632e6cca9e465e566c05802a",
      "dataset": "https://gate.dataloop.ai/api/v1/datasets/632e6c9aff5edd8643bb923f",
      "type": "point",
      "label": "building_missed_by_model",
      "attributes": [],
      "coordinates": {
        "x": 1040.3234302820038,
        "y": 287.0209537225231,
        "z": 0
      },
      "metadata": {
        "system": {
          "startTime": 0,
          "endTime": 0,
          "frame": 0,
          "endFrame": 0,
          "snapshots_": [],
          "clientId": "5cd1b876-3b19-401f-a6da-2b8bb9d8ba1b",
          "automated": false,
          "objectId": "16",
          "isOpen": false,
          "isOnlyLocal": false,
          "attributes": {},
          "system": false,
          "itemLinks": [],
          "openAnnotationVersion": "1.47.1-prod.3",
          "recipeId": "632e6c9b433d0b508cde9dbc",
          "taskId": "632e91ec7eb1331d49af333f",
          "assignmentId": "632e91ed7eb1334452af3341",
          "coordinateVersion": "v1"
        },
        "user": {}
      },
      "creator": "lewis.kalata@es.cloudfactory.com",
      "createdAt": "2022-09-26T19:30:32.702Z",
      "updatedBy": "lewis.kalata@es.cloudfactory.com",
      "updatedAt": "2022-09-26T19:30:32.702Z",
      "hash": "ae7ac8848d64309902022eb7c2b11f3335f95c90",
      "source": "ui"
    },
    {
      "id": "6331fdd8526e5c74d6d27fdf",
      "datasetId": "632e6c9aff5edd8643bb923f",
      "itemId": "632e6cca9e465e566c05802a",
      "url": "https://gate.dataloop.ai/api/v1/annotations/6331fdd8526e5c74d6d27fdf",
      "item": "https://gate.dataloop.ai/api/v1/items/632e6cca9e465e566c05802a",
      "dataset": "https://gate.dataloop.ai/api/v1/datasets/632e6c9aff5edd8643bb923f",
      "type": "point",
      "label": "model_found_building",
      "attributes": [],
      "coordinates": {
        "x": 906.6468605640075,
        "y": 411.4368882560388,
        "z": 0
      },
      "metadata": {
        "system": {
          "startTime": 0,
          "endTime": 0,
          "frame": 0,
          "endFrame": 0,
          "snapshots_": [],
          "clientId": "d1047232-6d85-43bd-8671-0bc37daeebba",
          "automated": false,
          "objectId": "12",
          "isOpen": false,
          "isOnlyLocal": false,
          "attributes": {},
          "system": false,
          "itemLinks": [],
          "openAnnotationVersion": "1.47.1-prod.3",
          "recipeId": "632e6c9b433d0b508cde9dbc",
          "taskId": "632e91ec7eb1331d49af333f",
          "assignmentId": "632e91ed7eb1334452af3341",
          "coordinateVersion": "v1"
        },
        "user": {}
      },
      "creator": "lewis.kalata@es.cloudfactory.com",
      "createdAt": "2022-09-26T19:30:32.689Z",
      "updatedBy": "lewis.kalata@es.cloudfactory.com",
      "updatedAt": "2022-09-26T19:30:32.689Z",
      "hash": "f9e7077c67507fac4c894b836c08e791b4818b25",
      "source": "ui"
    },
    {
      "id": "6331fdd8526e5cfb78d27fdc",
      "datasetId": "632e6c9aff5edd8643bb923f",
      "itemId": "632e6cca9e465e566c05802a",
      "url": "https://gate.dataloop.ai/api/v1/annotations/6331fdd8526e5cfb78d27fdc",
      "item": "https://gate.dataloop.ai/api/v1/items/632e6cca9e465e566c05802a",
      "dataset": "https://gate.dataloop.ai/api/v1/datasets/632e6c9aff5edd8643bb923f",
      "type": "point",
      "label": "model_found_building",
      "attributes": [],
      "coordinates": {
        "x": 1149.55331215274,
        "y": 670.663498072772,
        "z": 0
      },
      "metadata": {
        "system": {
          "startTime": 0,
          "endTime": 0,
          "frame": 0,
          "endFrame": 0,
          "snapshots_": [],
          "clientId": "e97c8b63-eba1-4f08-91ca-4f6aa50dd4f8",
          "automated": false,
          "objectId": "7",
          "isOpen": false,
          "isOnlyLocal": false,
          "attributes": {},
          "system": false,
          "itemLinks": [],
          "openAnnotationVersion": "1.47.1-prod.3",
          "recipeId": "632e6c9b433d0b508cde9dbc",
          "taskId": "632e91ec7eb1331d49af333f",
          "assignmentId": "632e91ed7eb1334452af3341",
          "coordinateVersion": "v1"
        },
        "user": {}
      },
      "creator": "lewis.kalata@es.cloudfactory.com",
      "createdAt": "2022-09-26T19:30:32.684Z",
      "updatedBy": "lewis.kalata@es.cloudfactory.com",
      "updatedAt": "2022-09-26T19:30:32.684Z",
      "hash": "e12c7a78ef3daa0b21fe60a13335c90ca0d0c7ca",
      "source": "ui"
    },
    {
      "id": "6331fdd8526e5c802cd27fed",
      "datasetId": "632e6c9aff5edd8643bb923f",
      "itemId": "632e6cca9e465e566c05802a",
      "url": "https://gate.dataloop.ai/api/v1/annotations/6331fdd8526e5c802cd27fed",
      "item": "https://gate.dataloop.ai/api/v1/items/632e6cca9e465e566c05802a",
      "dataset": "https://gate.dataloop.ai/api/v1/datasets/632e6c9aff5edd8643bb923f",
      "type": "point",
      "label": "model_found_building",
      "attributes": [],
      "coordinates": {
        "x": 776.4668381087204,
        "y": 55.62258316360171,
        "z": 0
      },
      "metadata": {
        "system": {
          "startTime": 0,
          "endTime": 0,
          "frame": 0,
          "endFrame": 0,
          "snapshots_": [],
          "clientId": "2843f0df-fc32-4e61-8aec-00057ff41ac2",
          "automated": false,
          "objectId": "25",
          "isOpen": false,
          "isOnlyLocal": false,
          "attributes": {},
          "system": false,
          "itemLinks": [],
          "openAnnotationVersion": "1.47.1-prod.3",
          "recipeId": "632e6c9b433d0b508cde9dbc",
          "taskId": "632e91ec7eb1331d49af333f",
          "assignmentId": "632e91ed7eb1334452af3341",
          "coordinateVersion": "v1"
        },
        "user": {}
      },
      "creator": "lewis.kalata@es.cloudfactory.com",
      "createdAt": "2022-09-26T19:30:32.716Z",
      "updatedBy": "lewis.kalata@es.cloudfactory.com",
      "updatedAt": "2022-09-26T19:30:32.716Z",
      "hash": "822433500baea0d4a31a63c85cafb9de89a7deae",
      "source": "ui"
    },
    {
      "id": "6331fdd8526e5c561dd27ff1",
      "datasetId": "632e6c9aff5edd8643bb923f",
      "itemId": "632e6cca9e465e566c05802a",
      "url": "https://gate.dataloop.ai/api/v1/annotations/6331fdd8526e5c561dd27ff1",
      "item": "https://gate.dataloop.ai/api/v1/items/632e6cca9e465e566c05802a",
      "dataset": "https://gate.dataloop.ai/api/v1/datasets/632e6c9aff5edd8643bb923f",
      "type": "point",
      "label": "model_found_building",
      "attributes": [],
      "coordinates": {
        "x": 703.6469168615629,
        "y": 137.75686484443418,
        "z": 0
      },
      "metadata": {
        "system": {
          "startTime": 0,
          "endTime": 0,
          "frame": 0,
          "endFrame": 0,
          "snapshots_": [],
          "clientId": "cc3afb99-5b8c-4461-8f97-113822dbd45c",
          "automated": false,
          "objectId": "29",
          "isOpen": false,
          "isOnlyLocal": false,
          "attributes": {},
          "system": false,
          "itemLinks": [],
          "openAnnotationVersion": "1.47.1-prod.3",
          "recipeId": "632e6c9b433d0b508cde9dbc",
          "taskId": "632e91ec7eb1331d49af333f",
          "assignmentId": "632e91ed7eb1334452af3341",
          "coordinateVersion": "v1"
        },
        "user": {}
      },
      "creator": "lewis.kalata@es.cloudfactory.com",
      "createdAt": "2022-09-26T19:30:32.722Z",
      "updatedBy": "lewis.kalata@es.cloudfactory.com",
      "updatedAt": "2022-09-26T19:30:32.722Z",
      "hash": "bd5a7f105a0fc65dd183c75b168302d99b21b48d",
      "source": "ui"
    },
    {
      "id": "6331fdd8526e5c102fd27ff4",
      "datasetId": "632e6c9aff5edd8643bb923f",
      "itemId": "632e6cca9e465e566c05802a",
      "url": "https://gate.dataloop.ai/api/v1/annotations/6331fdd8526e5c102fd27ff4",
      "item": "https://gate.dataloop.ai/api/v1/items/632e6cca9e465e566c05802a",
      "dataset": "https://gate.dataloop.ai/api/v1/datasets/632e6c9aff5edd8643bb923f",
      "type": "point",
      "label": "model_found_building",
      "attributes": [],
      "coordinates": {
        "x": 585.7458199097485,
        "y": 152.31230716761965,
        "z": 0
      },
      "metadata": {
        "system": {
          "startTime": 0,
          "endTime": 0,
          "frame": 0,
          "endFrame": 0,
          "snapshots_": [],
          "clientId": "ab0ee9a7-7316-4416-847c-7c6242e8bbdd",
          "automated": false,
          "objectId": "32",
          "isOpen": false,
          "isOnlyLocal": false,
          "attributes": {},
          "system": false,
          "itemLinks": [],
          "openAnnotationVersion": "1.47.1-prod.3",
          "recipeId": "632e6c9b433d0b508cde9dbc",
          "taskId": "632e91ec7eb1331d49af333f",
          "assignmentId": "632e91ed7eb1334452af3341",
          "coordinateVersion": "v1"
        },
        "user": {}
      },
      "creator": "lewis.kalata@es.cloudfactory.com",
      "createdAt": "2022-09-26T19:30:32.726Z",
      "updatedBy": "lewis.kalata@es.cloudfactory.com",
      "updatedAt": "2022-09-26T19:30:32.726Z",
      "hash": "88add1c0e87da93fbc180ffec552622d5bb1e2d2",
      "source": "ui"
    },
    {
      "id": "6331fdd8526e5c8692d27fe9",
      "datasetId": "632e6c9aff5edd8643bb923f",
      "itemId": "632e6cca9e465e566c05802a",
      "url": "https://gate.dataloop.ai/api/v1/annotations/6331fdd8526e5c8692d27fe9",
      "item": "https://gate.dataloop.ai/api/v1/items/632e6cca9e465e566c05802a",
      "dataset": "https://gate.dataloop.ai/api/v1/datasets/632e6c9aff5edd8643bb923f",
      "type": "point",
      "label": "building_missed_by_model",
      "attributes": [],
      "coordinates": {
        "x": 838.7216279118733,
        "y": 432.8067125757623,
        "z": 0
      },
      "metadata": {
        "system": {
          "startTime": 0,
          "endTime": 0,
          "frame": 0,
          "endFrame": 0,
          "snapshots_": [],
          "clientId": "26d80a14-7120-46ab-8914-a4094376d85e",
          "automated": false,
          "objectId": "20",
          "isOpen": false,
          "isOnlyLocal": false,
          "attributes": {},
          "system": false,
          "itemLinks": [],
          "openAnnotationVersion": "1.47.1-prod.3",
          "recipeId": "632e6c9b433d0b508cde9dbc",
          "taskId": "632e91ec7eb1331d49af333f",
          "assignmentId": "632e91ed7eb1334452af3341",
          "coordinateVersion": "v1"
        },
        "user": {}
      },
      "creator": "lewis.kalata@es.cloudfactory.com",
      "createdAt": "2022-09-26T19:30:32.708Z",
      "updatedBy": "lewis.kalata@es.cloudfactory.com",
      "updatedAt": "2022-09-26T19:30:32.708Z",
      "hash": "791c95634c364053880f8af7d59f443cb812bdf1",
      "source": "ui"
    },
    {
      "id": "6331fdd8526e5cb408d27fec",
      "datasetId": "632e6c9aff5edd8643bb923f",
      "itemId": "632e6cca9e465e566c05802a",
      "url": "https://gate.dataloop.ai/api/v1/annotations/6331fdd8526e5cb408d27fec",
      "item": "https://gate.dataloop.ai/api/v1/items/632e6cca9e465e566c05802a",
      "dataset": "https://gate.dataloop.ai/api/v1/datasets/632e6c9aff5edd8643bb923f",
      "type": "point",
      "label": "model_found_new_building",
      "attributes": [],
      "coordinates": {
        "x": 822.239360035505,
        "y": 93.05086342322156,
        "z": 0
      },
      "metadata": {
        "system": {
          "startTime": 0,
          "endTime": 0,
          "frame": 0,
          "endFrame": 0,
          "snapshots_": [],
          "clientId": "39291ba0-b3ef-4ce2-80bf-13bc2daa3e2c",
          "automated": false,
          "objectId": "26",
          "isOpen": false,
          "isOnlyLocal": false,
          "attributes": {},
          "system": false,
          "itemLinks": [],
          "openAnnotationVersion": "1.47.1-prod.3",
          "recipeId": "632e6c9b433d0b508cde9dbc",
          "taskId": "632e91ec7eb1331d49af333f",
          "assignmentId": "632e91ed7eb1334452af3341",
          "coordinateVersion": "v1"
        },
        "user": {}
      },
      "creator": "lewis.kalata@es.cloudfactory.com",
      "createdAt": "2022-09-26T19:30:32.715Z",
      "updatedBy": "lewis.kalata@es.cloudfactory.com",
      "updatedAt": "2022-09-26T19:30:32.715Z",
      "hash": "a64547ede0ee8eceb7a062be1d35d09eb3a19b32",
      "source": "ui"
    },
    {
      "id": "6331fdd8526e5c327bd27fe8",
      "datasetId": "632e6c9aff5edd8643bb923f",
      "itemId": "632e6cca9e465e566c05802a",
      "url": "https://gate.dataloop.ai/api/v1/annotations/6331fdd8526e5c327bd27fe8",
      "item": "https://gate.dataloop.ai/api/v1/items/632e6cca9e465e566c05802a",
      "dataset": "https://gate.dataloop.ai/api/v1/datasets/632e6c9aff5edd8643bb923f",
      "type": "point",
      "label": "model_found_building",
      "attributes": [],
      "coordinates": {
        "x": 1081.4146715571856,
        "y": 257.0432284182478,
        "z": 0
      },
      "metadata": {
        "system": {
          "startTime": 0,
          "endTime": 0,
          "frame": 0,
          "endFrame": 0,
          "snapshots_": [],
          "clientId": "6c983b25-cfac-48d6-933c-0d56eb949cfa",
          "automated": false,
          "objectId": "22",
          "isOpen": false,
          "isOnlyLocal": false,
          "attributes": {},
          "system": false,
          "itemLinks": [],
          "openAnnotationVersion": "1.47.1-prod.3",
          "recipeId": "632e6c9b433d0b508cde9dbc",
          "taskId": "632e91ec7eb1331d49af333f",
          "assignmentId": "632e91ed7eb1334452af3341",
          "coordinateVersion": "v1"
        },
        "user": {}
      },
      "creator": "lewis.kalata@es.cloudfactory.com",
      "createdAt": "2022-09-26T19:30:32.706Z",
      "updatedBy": "lewis.kalata@es.cloudfactory.com",
      "updatedAt": "2022-09-26T19:30:32.706Z",
      "hash": "8a63d9cbe07f436f9f29f4f83b150e3e0f469090",
      "source": "ui"
    },
    {
      "id": "6331fdd8526e5c3fa0d27ff2",
      "datasetId": "632e6c9aff5edd8643bb923f",
      "itemId": "632e6cca9e465e566c05802a",
      "url": "https://gate.dataloop.ai/api/v1/annotations/6331fdd8526e5c3fa0d27ff2",
      "item": "https://gate.dataloop.ai/api/v1/items/632e6cca9e465e566c05802a",
      "dataset": "https://gate.dataloop.ai/api/v1/datasets/632e6c9aff5edd8643bb923f",
      "type": "point",
      "label": "model_found_building",
      "attributes": [],
      "coordinates": {
        "x": 582.1048238473907,
        "y": 229.24821659017155,
        "z": 0
      },
      "metadata": {
        "system": {
          "startTime": 0,
          "endTime": 0,
          "frame": 0,
          "endFrame": 0,
          "snapshots_": [],
          "clientId": "b82b0420-1ba3-46d9-8fd2-d2b2e375545f",
          "automated": false,
          "objectId": "31",
          "isOpen": false,
          "isOnlyLocal": false,
          "attributes": {},
          "system": false,
          "itemLinks": [],
          "openAnnotationVersion": "1.47.1-prod.3",
          "recipeId": "632e6c9b433d0b508cde9dbc",
          "taskId": "632e91ec7eb1331d49af333f",
          "assignmentId": "632e91ed7eb1334452af3341",
          "coordinateVersion": "v1"
        },
        "user": {}
      },
      "creator": "lewis.kalata@es.cloudfactory.com",
      "createdAt": "2022-09-26T19:30:32.723Z",
      "updatedBy": "lewis.kalata@es.cloudfactory.com",
      "updatedAt": "2022-09-26T19:30:32.723Z",
      "hash": "a1699393b95c50d807df3aeb55c9db43b31efa22",
      "source": "ui"
    },
    {
      "id": "6331fdd8526e5caca9d27ff5",
      "datasetId": "632e6c9aff5edd8643bb923f",
      "itemId": "632e6cca9e465e566c05802a",
      "url": "https://gate.dataloop.ai/api/v1/annotations/6331fdd8526e5caca9d27ff5",
      "item": "https://gate.dataloop.ai/api/v1/items/632e6cca9e465e566c05802a",
      "dataset": "https://gate.dataloop.ai/api/v1/datasets/632e6c9aff5edd8643bb923f",
      "type": "point",
      "label": "model_found_building",
      "attributes": [],
      "coordinates": {
        "x": 351.3239305865302,
        "y": 48.86469922783703,
        "z": 0
      },
      "metadata": {
        "system": {
          "startTime": 0,
          "endTime": 0,
          "frame": 0,
          "endFrame": 0,
          "snapshots_": [],
          "clientId": "f6c5505f-378d-40ac-ac7b-35513b1c2e5c",
          "automated": false,
          "objectId": "34",
          "isOpen": false,
          "isOnlyLocal": false,
          "attributes": {},
          "system": false,
          "itemLinks": [],
          "openAnnotationVersion": "1.47.1-prod.3",
          "recipeId": "632e6c9b433d0b508cde9dbc",
          "taskId": "632e91ec7eb1331d49af333f",
          "assignmentId": "632e91ed7eb1334452af3341",
          "coordinateVersion": "v1"
        },
        "user": {}
      },
      "creator": "lewis.kalata@es.cloudfactory.com",
      "createdAt": "2022-09-26T19:30:32.727Z",
      "updatedBy": "lewis.kalata@es.cloudfactory.com",
      "updatedAt": "2022-09-26T19:30:32.727Z",
      "hash": "c44a341648efb76f81e3bb9af31d8f4935a69293",
      "source": "ui"
    },
    {
      "id": "6331fdd8526e5cb652d27ff7",
      "datasetId": "632e6c9aff5edd8643bb923f",
      "itemId": "632e6cca9e465e566c05802a",
      "url": "https://gate.dataloop.ai/api/v1/annotations/6331fdd8526e5cb652d27ff7",
      "item": "https://gate.dataloop.ai/api/v1/items/632e6cca9e465e566c05802a",
      "dataset": "https://gate.dataloop.ai/api/v1/datasets/632e6c9aff5edd8643bb923f",
      "type": "point",
      "label": "model_found_building",
      "attributes": [],
      "coordinates": {
        "x": 494.8832039023549,
        "y": 18.714140129809923,
        "z": 0
      },
      "metadata": {
        "system": {
          "startTime": 0,
          "endTime": 0,
          "frame": 0,
          "endFrame": 0,
          "snapshots_": [],
          "clientId": "bb120f4d-48e3-4181-8667-90aed1249279",
          "automated": false,
          "objectId": "36",
          "isOpen": false,
          "isOnlyLocal": false,
          "attributes": {},
          "system": false,
          "itemLinks": [],
          "openAnnotationVersion": "1.47.1-prod.3",
          "recipeId": "632e6c9b433d0b508cde9dbc",
          "taskId": "632e91ec7eb1331d49af333f",
          "assignmentId": "632e91ed7eb1334452af3341",
          "coordinateVersion": "v1"
        },
        "user": {}
      },
      "creator": "lewis.kalata@es.cloudfactory.com",
      "createdAt": "2022-09-26T19:30:32.730Z",
      "updatedBy": "lewis.kalata@es.cloudfactory.com",
      "updatedAt": "2022-09-26T19:30:32.730Z",
      "hash": "f1109a658cc4b4c9009e96f39e471e6c005e435f",
      "source": "ui"
    },
    {
      "id": "6331fdd8526e5c54aad27ffb",
      "datasetId": "632e6c9aff5edd8643bb923f",
      "itemId": "632e6cca9e465e566c05802a",
      "url": "https://gate.dataloop.ai/api/v1/annotations/6331fdd8526e5c54aad27ffb",
      "item": "https://gate.dataloop.ai/api/v1/items/632e6cca9e465e566c05802a",
      "dataset": "https://gate.dataloop.ai/api/v1/datasets/632e6c9aff5edd8643bb923f",
      "type": "point",
      "label": "model_found_new_building",
      "attributes": [],
      "coordinates": {
        "x": 908.0066651466499,
        "y": 772.5975301039041,
        "z": 0
      },
      "metadata": {
        "system": {
          "startTime": 0,
          "endTime": 0,
          "frame": 0,
          "endFrame": 0,
          "snapshots_": [],
          "clientId": "456d0f93-8113-4dc5-bd5a-901ddc69c708",
          "automated": false,
          "objectId": "39",
          "isOpen": false,
          "isOnlyLocal": false,
          "attributes": {},
          "system": false,
          "itemLinks": [],
          "openAnnotationVersion": "1.47.1-prod.3",
          "recipeId": "632e6c9b433d0b508cde9dbc",
          "taskId": "632e91ec7eb1331d49af333f",
          "assignmentId": "632e91ed7eb1334452af3341",
          "coordinateVersion": "v1"
        },
        "user": {}
      },
      "creator": "lewis.kalata@es.cloudfactory.com",
      "createdAt": "2022-09-26T19:30:32.737Z",
      "updatedBy": "lewis.kalata@es.cloudfactory.com",
      "updatedAt": "2022-09-26T19:30:32.737Z",
      "hash": "29f226902fa4523d64ed0f0f1b31477d7a65c133",
      "source": "ui"
    },
    {
      "id": "6331fdd8526e5ca5e7d27ffa",
      "datasetId": "632e6c9aff5edd8643bb923f",
      "itemId": "632e6cca9e465e566c05802a",
      "url": "https://gate.dataloop.ai/api/v1/annotations/6331fdd8526e5ca5e7d27ffa",
      "item": "https://gate.dataloop.ai/api/v1/items/632e6cca9e465e566c05802a",
      "dataset": "https://gate.dataloop.ai/api/v1/datasets/632e6c9aff5edd8643bb923f",
      "type": "point",
      "label": "model_found_building",
      "attributes": [],
      "coordinates": {
        "x": 957.7419022270856,
        "y": 356.23191720502064,
        "z": 0
      },
      "metadata": {
        "system": {
          "startTime": 0,
          "endTime": 0,
          "frame": 0,
          "endFrame": 0,
          "snapshots_": [],
          "clientId": "37274f69-d0d2-4d30-90f9-903eab7ccaa9",
          "automated": false,
          "objectId": "40",
          "isOpen": false,
          "isOnlyLocal": false,
          "attributes": {},
          "system": false,
          "itemLinks": [],
          "openAnnotationVersion": "1.47.1-prod.3",
          "recipeId": "632e6c9b433d0b508cde9dbc",
          "taskId": "632e91ec7eb1331d49af333f",
          "assignmentId": "632e91ed7eb1334452af3341",
          "coordinateVersion": "v1"
        },
        "user": {}
      },
      "creator": "lewis.kalata@es.cloudfactory.com",
      "createdAt": "2022-09-26T19:30:32.735Z",
      "updatedBy": "lewis.kalata@es.cloudfactory.com",
      "updatedAt": "2022-09-26T19:30:32.735Z",
      "hash": "88a6489ed78fe3242c8814b18ecc9704806c275a",
      "source": "ui"
    },
    {
      "id": "6331fdd8526e5c51ead27fe4",
      "datasetId": "632e6c9aff5edd8643bb923f",
      "itemId": "632e6cca9e465e566c05802a",
      "url": "https://gate.dataloop.ai/api/v1/annotations/6331fdd8526e5c51ead27fe4",
      "item": "https://gate.dataloop.ai/api/v1/items/632e6cca9e465e566c05802a",
      "dataset": "https://gate.dataloop.ai/api/v1/datasets/632e6c9aff5edd8643bb923f",
      "type": "point",
      "label": "model_found_building",
      "attributes": [],
      "coordinates": {
        "x": 918.0899910457036,
        "y": 331.2071179179076,
        "z": 0
      },
      "metadata": {
        "system": {
          "startTime": 0,
          "endTime": 0,
          "frame": 0,
          "endFrame": 0,
          "snapshots_": [],
          "clientId": "5d9156f6-fd0b-4198-b361-7b1c00dd7613",
          "automated": false,
          "objectId": "18",
          "isOpen": false,
          "isOnlyLocal": false,
          "attributes": {},
          "system": false,
          "itemLinks": [],
          "openAnnotationVersion": "1.47.1-prod.3",
          "recipeId": "632e6c9b433d0b508cde9dbc",
          "taskId": "632e91ec7eb1331d49af333f",
          "assignmentId": "632e91ed7eb1334452af3341",
          "coordinateVersion": "v1"
        },
        "user": {}
      },
      "creator": "lewis.kalata@es.cloudfactory.com",
      "createdAt": "2022-09-26T19:30:32.697Z",
      "updatedBy": "lewis.kalata@es.cloudfactory.com",
      "updatedAt": "2022-09-26T19:30:32.697Z",
      "hash": "7058aa8906f9f0c9edd10ae6931a1713bec67989",
      "source": "ui"
    },
    {
      "id": "6331fdd8526e5c11e4d27ff3",
      "datasetId": "632e6c9aff5edd8643bb923f",
      "itemId": "632e6cca9e465e566c05802a",
      "url": "https://gate.dataloop.ai/api/v1/annotations/6331fdd8526e5c11e4d27ff3",
      "item": "https://gate.dataloop.ai/api/v1/items/632e6cca9e465e566c05802a",
      "dataset": "https://gate.dataloop.ai/api/v1/datasets/632e6c9aff5edd8643bb923f",
      "type": "point",
      "label": "model_found_new_building",
      "attributes": [],
      "coordinates": {
        "x": 511.885614073346,
        "y": 194.93895968552002,
        "z": 0
      },
      "metadata": {
        "system": {
          "startTime": 0,
          "endTime": 0,
          "frame": 0,
          "endFrame": 0,
          "snapshots_": [],
          "clientId": "c66aec8e-5a4f-484a-9388-1f7d748c9d63",
          "automated": false,
          "objectId": "33",
          "isOpen": false,
          "isOnlyLocal": false,
          "attributes": {},
          "system": false,
          "itemLinks": [],
          "openAnnotationVersion": "1.47.1-prod.3",
          "recipeId": "632e6c9b433d0b508cde9dbc",
          "taskId": "632e91ec7eb1331d49af333f",
          "assignmentId": "632e91ed7eb1334452af3341",
          "coordinateVersion": "v1"
        },
        "user": {}
      },
      "creator": "lewis.kalata@es.cloudfactory.com",
      "createdAt": "2022-09-26T19:30:32.724Z",
      "updatedBy": "lewis.kalata@es.cloudfactory.com",
      "updatedAt": "2022-09-26T19:30:32.724Z",
      "hash": "a4b10e0688712a3e69160cf6ead0ddd6cface4e6",
      "source": "ui"
    },
    {
      "id": "6331fdd8526e5c2b7ed27fea",
      "datasetId": "632e6c9aff5edd8643bb923f",
      "itemId": "632e6cca9e465e566c05802a",
      "url": "https://gate.dataloop.ai/api/v1/annotations/6331fdd8526e5c2b7ed27fea",
      "item": "https://gate.dataloop.ai/api/v1/items/632e6cca9e465e566c05802a",
      "dataset": "https://gate.dataloop.ai/api/v1/datasets/632e6c9aff5edd8643bb923f",
      "type": "point",
      "label": "model_found_building",
      "attributes": [],
      "coordinates": {
        "x": 1109.5023554668032,
        "y": 208.17852919041079,
        "z": 0
      },
      "metadata": {
        "system": {
          "startTime": 0,
          "endTime": 0,
          "frame": 0,
          "endFrame": 0,
          "snapshots_": [],
          "clientId": "ee30f7b4-fb32-4272-acbf-0787e434c0f3",
          "automated": false,
          "objectId": "21",
          "isOpen": false,
          "isOnlyLocal": false,
          "attributes": {},
          "system": false,
          "itemLinks": [],
          "openAnnotationVersion": "1.47.1-prod.3",
          "recipeId": "632e6c9b433d0b508cde9dbc",
          "taskId": "632e91ec7eb1331d49af333f",
          "assignmentId": "632e91ed7eb1334452af3341",
          "coordinateVersion": "v1"
        },
        "user": {}
      },
      "creator": "lewis.kalata@es.cloudfactory.com",
      "createdAt": "2022-09-26T19:30:32.709Z",
      "updatedBy": "lewis.kalata@es.cloudfactory.com",
      "updatedAt": "2022-09-26T19:30:32.709Z",
      "hash": "f28670d8b369815a250fa2d3698ebda3b7bd67b8",
      "source": "ui"
    },
    {
      "id": "6331fdd8526e5cba88d27fe0",
      "datasetId": "632e6c9aff5edd8643bb923f",
      "itemId": "632e6cca9e465e566c05802a",
      "url": "https://gate.dataloop.ai/api/v1/annotations/6331fdd8526e5cba88d27fe0",
      "item": "https://gate.dataloop.ai/api/v1/items/632e6cca9e465e566c05802a",
      "dataset": "https://gate.dataloop.ai/api/v1/datasets/632e6c9aff5edd8643bb923f",
      "type": "point",
      "label": "building_missed_by_model",
      "attributes": [],
      "coordinates": {
        "x": 989.8696277036161,
        "y": 333.8063040470479,
        "z": 0
      },
      "metadata": {
        "system": {
          "startTime": 0,
          "endTime": 0,
          "frame": 0,
          "endFrame": 0,
          "snapshots_": [],
          "clientId": "cafc7cba-a0b6-47ad-9fc0-76463002cccb",
          "automated": false,
          "objectId": "14",
          "isOpen": false,
          "isOnlyLocal": false,
          "attributes": {},
          "system": false,
          "itemLinks": [],
          "openAnnotationVersion": "1.47.1-prod.3",
          "recipeId": "632e6c9b433d0b508cde9dbc",
          "taskId": "632e91ec7eb1331d49af333f",
          "assignmentId": "632e91ed7eb1334452af3341",
          "coordinateVersion": "v1"
        },
        "user": {}
      },
      "creator": "lewis.kalata@es.cloudfactory.com",
      "createdAt": "2022-09-26T19:30:32.690Z",
      "updatedBy": "lewis.kalata@es.cloudfactory.com",
      "updatedAt": "2022-09-26T19:30:32.690Z",
      "hash": "7a136a789a548a5fef192083451f6d5a19fd1486",
      "source": "ui"
    }
  ],
  "annotationsCount": 39,
  "annotated": true
}