{
  "id": "632e6cca9e465e945605801d",
  "datasetId": "632e6c9aff5edd8643bb923f",
  "url": "https://gate.dataloop.ai/api/v1/items/632e6cca9e465e945605801d",
  "dataset": "https://gate.dataloop.ai/api/v1/datasets/632e6c9aff5edd8643bb923f",
  "createdAt": "2022-09-24T02:34:50.000Z",
  "dir": "/2020",
  "filename": "/2020/m_3712141_ne_10_060_20200525_131-small_2020.png",
  "type": "file",
  "hidden": false,
  "metadata": {
    "system": {
      "size": 547005,
      "taskStatusLog": [
        {
          "status": {
            "taskId": "632e91ec7eb1331d49af333f",
            "assignmentId": "632e91ed7eb1335101af3343",
            "status": "completed",
            "creator": "jackline.ogutu@es.cloudfactory.com",
            "timestamp": "2022-09-26T15:23:36.099Z"
          },
          "action": "created"
        },
        {
          "status": {
            "taskId": "6332d8f97eb133c0c6af354a",
            "assignmentId": "6332d8f97eb133476aaf354b",
            "status": "approved",
            "creator": "lewis.kalata@es.cloudfactory.com",
            "timestamp": "2022-09-27T11:22:53.369Z"
          },
          "action": "created"
        },
        {
          "status": {
            "taskId": "6336a0a324e1aadd24e5f4ef",
            "assignmentId": "6336a0a424e1aa5616e5f4f3",
            "status": "completed",
            "creator": "nyambe.mwangelwa@es.cloudfactory.com",
            "timestamp": "2022-09-30T11:19:53.239Z"
          },
          "action": "created"
        },
        {
          "status": {
            "taskId": "6336fef9a7ca340792d9d39f",
            "assignmentId": "6336fefaa7ca3477a6d9d3a0",
            "status": "approved",
            "creator": "grace.odemba@es.cloudfactory.com",
            "timestamp": "2022-09-30T15:00:41.022Z"
          },
          "action": "created"
        }
      ],
      "mimetype": "image/png",
      "isBinary": true,
      "channels": 4,
      "exif": {},
      "height": 1175,
      "thumbnailId": "632e6cddb28a0c2952180c1a",
      "width": 1174,
      "refs": [
        {
          "id": "632e91ec7eb1331d49af333f",
          "type": "task",
          "metadata": {
            "creator": "jackline.ogutu@es.cloudfactory.com",
            "status": "completed",
            "timestamp": "2022-09-26T15:23:36.099Z"
          }
        },
        {
          "id": "632e91ed7eb1335101af3343",
          "type": "assignment",
          "metadata": {
            "creator": "jackline.ogutu@es.cloudfactory.com",
            "status": "completed",
            "timestamp": "2022-09-26T15:23:36.099Z"
          }
        },
        {
          "id": "6332d8f97eb133c0c6af354a",
          "type": "task",
          "metadata": {
            "creator": "lewis.kalata@es.cloudfactory.com",
            "status": "approved",
            "timestamp": "2022-09-27T11:22:53.369Z"
          }
        },
        {
          "id": "6332d8f97eb133476aaf354b",
          "type": "assignment",
          "metadata": {
            "creator": "lewis.kalata@es.cloudfactory.com",
            "status": "approved",
            "timestamp": "2022-09-27T11:22:53.369Z"
          }
        },
        {
          "id": "6336a0a324e1aadd24e5f4ef",
          "type": "task",
          "metadata": {
            "creator": "nyambe.mwangelwa@es.cloudfactory.com",
            "status": "completed",
            "timestamp": "2022-09-30T11:19:53.239Z"
          }
        },
        {
          "id": "6336a0a424e1aa5616e5f4f3",
          "type": "assignment",
          "metadata": {
            "creator": "nyambe.mwangelwa@es.cloudfactory.com",
            "status": "completed",
            "timestamp": "2022-09-30T11:19:53.239Z"
          }
        },
        {
          "id": "6336fef9a7ca340792d9d39f",
          "type": "task",
          "metadata": {
            "creator": "grace.odemba@es.cloudfactory.com",
            "status": "approved",
            "timestamp": "2022-09-30T15:00:41.022Z"
          }
        },
        {
          "id": "6336fefaa7ca3477a6d9d3a0",
          "type": "assignment",
          "metadata": {
            "creator": "grace.odemba@es.cloudfactory.com",
            "status": "approved",
            "timestamp": "2022-09-30T15:00:41.022Z"
          }
        }
      ]
    },
    "user": {
      "coordinates": "37.3590648163541, -121.9000713933357",
      "image_year": 2020
    }
  },
  "name": "m_3712141_ne_10_060_20200525_131-small_2020.png",
  "creator": "rubiks@dataloop.ai",
  "stream": "https://gate.dataloop.ai/api/v1/items/632e6cca9e465e945605801d/stream",
  "thumbnail": "https://gate.dataloop.ai/api/v1/items/632e6cca9e465e945605801d/thumbnail",
  "annotations": [
    {
      "id": "6331c26853404313ecaeaac4",
      "datasetId": "632e6c9aff5edd8643bb923f",
      "itemId": "632e6cca9e465e945605801d",
      "url": "https://gate.dataloop.ai/api/v1/annotations/6331c26853404313ecaeaac4",
      "item": "https://gate.dataloop.ai/api/v1/items/632e6cca9e465e945605801d",
      "dataset": "https://gate.dataloop.ai/api/v1/datasets/632e6c9aff5edd8643bb923f",
      "type": "point",
      "label": "model_found_building",
      "attributes": [],
      "coordinates": {
        "x": 551.9749014608719,
        "y": 1035.6453979416017,
        "z": 0
      },
      "metadata": {
        "system": {
          "startTime": 0,
          "endTime": 0,
          "frame": 0,
          "endFrame": 0,
          "snapshots_": [],
          "clientId": "ec305c5d-ba3a-447f-bdb3-ff42b9471a05",
          "automated": false,
          "objectId": "1",
          "isOpen": false,
          "isOnlyLocal": false,
          "attributes": {},
          "system": false,
          "itemLinks": [],
          "openAnnotationVersion": "1.47.1-prod.3",
          "recipeId": "632e6c9b433d0b508cde9dbc",
          "taskId": "632e91ec7eb1331d49af333f",
          "assignmentId": "632e91ed7eb1335101af3343",
          "coordinateVersion": "v1"
        },
        "user": {}
      },
      "creator": "jackline.ogutu@es.cloudfactory.com",
      "createdAt": "2022-09-26T15:16:56.629Z",
      "updatedBy": "lewis.kalata@es.cloudfactory.com",
      "updatedAt": "2022-09-27T11:22:44.885Z",
      "hash": "0b84b7cee00c149287059326b2305f62f8764d21",
      "source": "ui"
    },
    {
      "id": "6331c268534043f262aeaac6",
      "datasetId": "632e6c9aff5edd8643bb923f",
      "itemId": "632e6cca9e465e945605801d",
      "url": "https://gate.dataloop.ai/api/v1/annotations/6331c268534043f262aeaac6",
      "item": "https://gate.dataloop.ai/api/v1/items/632e6cca9e465e945605801d",
      "dataset": "https://gate.dataloop.ai/api/v1/datasets/632e6c9aff5edd8643bb923f",
      "type": "point",
      "label": "model_found_building",
      "attributes": [],
      "coordinates": {
        "x": 501.44858172470157,
        "y": 1073.0588165754784,
        "z": 0
      },
      "metadata": {
        "system": {
          "startTime": 0,
          "endTime": 0,
          "frame": 0,
          "endFrame": 0,
          "snapshots_": [],
          "clientId": "95164da3-b5ae-4101-b995-7d9863546898",
          "automated": false,
          "objectId": "4",
          "isOpen": false,
          "isOnlyLocal": false,
          "attributes": {},
          "system": false,
          "itemLinks": [],
          "openAnnotationVersion": "1.47.1-prod.3",
          "recipeId": "632e6c9b433d0b508cde9dbc",
          "taskId": "632e91ec7eb1331d49af333f",
          "assignmentId": "632e91ed7eb1335101af3343",
          "coordinateVersion": "v1"
        },
        "user": {}
      },
      "creator": "jackline.ogutu@es.cloudfactory.com",
      "createdAt": "2022-09-26T15:16:56.632Z",
      "updatedBy": "lewis.kalata@es.cloudfactory.com",
      "updatedAt": "2022-09-27T11:22:44.889Z",
      "hash": "fd4471f8e842ab456cf81a383408d122ae21c0ca",
      "source": "ui"
    },
    {
      "id": "6331c268534043aafbaeaac9",
      "datasetId": "632e6c9aff5edd8643bb923f",
      "itemId": "632e6cca9e465e945605801d",
      "url": "https://gate.dataloop.ai/api/v1/annotations/6331c268534043aafbaeaac9",
      "item": "https://gate.dataloop.ai/api/v1/items/632e6cca9e465e945605801d",
      "dataset": "https://gate.dataloop.ai/api/v1/datasets/632e6c9aff5edd8643bb923f",
      "type": "point",
      "label": "model_found_building",
      "attributes": [],
      "coordinates": {
        "x": 847.2346180240515,
        "y": 893.6072034846669,
        "z": 0
      },
      "metadata": {
        "system": {
          "startTime": 0,
          "endTime": 0,
          "frame": 0,
          "endFrame": 0,
          "snapshots_": [],
          "clientId": "f6c694d4-a9ba-4764-8b5d-1d45b58be6ac",
          "automated": false,
          "objectId": "6",
          "isOpen": false,
          "isOnlyLocal": false,
          "attributes": {},
          "system": false,
          "itemLinks": [],
          "openAnnotationVersion": "1.47.1-prod.3",
          "recipeId": "632e6c9b433d0b508cde9dbc",
          "taskId": "632e91ec7eb1331d49af333f",
          "assignmentId": "632e91ed7eb1335101af3343",
          "coordinateVersion": "v1"
        },
        "user": {}
      },
      "creator": "jackline.ogutu@es.cloudfactory.com",
      "createdAt": "2022-09-26T15:16:56.636Z",
      "updatedBy": "jackline.ogutu@es.cloudfactory.com",
      "updatedAt": "2022-09-26T15:16:56.636Z",
      "hash": "a395410691a394172c563fe149a60d67c804f950",
      "source": "ui"
    },
    {
      "id": "6331c26853404314baaeaac8",
      "datasetId": "632e6c9aff5edd8643bb923f",
      "itemId": "632e6cca9e465e945605801d",
      "url": "https://gate.dataloop.ai/api/v1/annotations/6331c26853404314baaeaac8",
      "item": "https://gate.dataloop.ai/api/v1/items/632e6cca9e465e945605801d",
      "dataset": "https://gate.dataloop.ai/api/v1/datasets/632e6c9aff5edd8643bb923f",
      "type": "point",
      "label": "model_found_new_building",
      "attributes": [],
      "coordinates": {
        "x": 996.0283499151917,
        "y": 1141.414496851651,
        "z": 0
      },
      "metadata": {
        "system": {
          "startTime": 0,
          "endTime": 0,
          "frame": 0,
          "endFrame": 0,
          "snapshots_": [],
          "clientId": "23369fc3-9a81-4076-b388-f154590bfb3f",
          "automated": false,
          "objectId": "5",
          "isOpen": false,
          "isOnlyLocal": false,
          "attributes": {},
          "system": false,
          "itemLinks": [],
          "openAnnotationVersion": "1.48.2-rc.82",
          "recipeId": "632e6c9b433d0b508cde9dbc",
          "taskId": "632e91ec7eb1331d49af333f",
          "assignmentId": "632e91ed7eb1335101af3343",
          "coordinateVersion": "v1"
        },
        "user": {}
      },
      "creator": "jackline.ogutu@es.cloudfactory.com",
      "createdAt": "2022-09-26T15:16:56.634Z",
      "updatedBy": "grace.odemba@es.cloudfactory.com",
      "updatedAt": "2022-09-30T15:00:40.510Z",
      "hash": "ee00309cb831aaaee96aec2918fde999b639ae1b",
      "source": "ui"
    },
    {
      "id": "6331c268534043588aaeaac5",
      "datasetId": "632e6c9aff5edd8643bb923f",
      "itemId": "632e6cca9e465e945605801d",
      "url": "https://gate.dataloop.ai/api/v1/annotations/6331c268534043588aaeaac5",
      "item": "https://gate.dataloop.ai/api/v1/items/632e6cca9e465e945605801d",
      "dataset": "https://gate.dataloop.ai/api/v1/datasets/632e6c9aff5edd8643bb923f",
      "type": "point",
      "label": "model_found_building",
      "attributes": [],
      "coordinates": {
        "x": 534.8630887693196,
        "y": 1123.8772573567792,
        "z": 0
      },
      "metadata": {
        "system": {
          "startTime": 0,
          "endTime": 0,
          "frame": 0,
          "endFrame": 0,
          "snapshots_": [],
          "clientId": "63951bac-ba5c-4cfb-881c-10b0d2fe40e6",
          "automated": false,
          "objectId": "2",
          "isOpen": false,
          "isOnlyLocal": false,
          "attributes": {},
          "system": false,
          "itemLinks": [],
          "openAnnotationVersion": "1.47.1-prod.3",
          "recipeId": "632e6c9b433d0b508cde9dbc",
          "taskId": "632e91ec7eb1331d49af333f",
          "assignmentId": "632e91ed7eb1335101af3343",
          "coordinateVersion": "v1"
        },
        "user": {}
      },
      "creator": "jackline.ogutu@es.cloudfactory.com",
      "createdAt": "2022-09-26T15:16:56.630Z",
      "updatedBy": "lewis.kalata@es.cloudfactory.com",
      "updatedAt": "2022-09-27T11:22:44.895Z",
      "hash": "1694239e3bfeacd8a8fb32b8a1e7b61822e07b44",
      "source": "ui"
    },
    {
      "id": "6331c268534043ec42aeaac7",
      "datasetId": "632e6c9aff5edd8643bb923f",
      "itemId": "632e6cca9e465e945605801d",
      "url": "https://gate.dataloop.ai/api/v1/annotations/6331c268534043ec42aeaac7",
      "item": "https://gate.dataloop.ai/api/v1/items/632e6cca9e465e945605801d",
      "dataset": "https://gate.dataloop.ai/api/v1/datasets/632e6c9aff5edd8643bb923f",
      "type": "point",
      "label": "model_found_building",
      "attributes": [],
      "coordinates": {
        "x": 99.91519216831004,
        "y": 1139.0586900896853,
        "z": 0
      },
      "metadata": {
        "system": {
          "startTime": 0,
          "endTime": 0,
          "frame": 0,
          "endFrame": 0,
          "snapshots_": [],
          "clientId": "2292bf68-5586-4cfa-aef2-80a277add3c6",
          "automated": false,
          "objectId": "3",
          "isOpen": false,
          "isOnlyLocal": false,
          "attributes": {},
          "system": false,
          "itemLinks": [],
          "openAnnotationVersion": "1.47.1-prod.3",
          "recipeId": "632e6c9b433d0b508cde9dbc",
          "taskId": "632e91ec7eb1331d49af333f",
          "assignmentId": "632e91ed7eb1335101af3343",
          "coordinateVersion": "v1"
        },
        "user": {}
      },
      "creator": "jackline.ogutu@es.cloudfactory.com",
      "createdAt": "2022-09-26T15:16:56.633Z",
      "updatedBy": "lewis.kalata@es.cloudfactory.com",
      "updatedAt": "2022-09-27T11:22:44.884Z",
      "hash": "d915a204c1051a6b9607998a49fb2c79ce9ac816",
      "source": "ui"
    },
    {
      "id": "6332dc3045f8cc01cde880e8",
      "datasetId": "632e6c9aff5edd8643bb923f",
      "itemId": "632e6cca9e465e945605801d",
      "url": "https://gate.dataloop.ai/api/v1/annotations/6332dc3045f8cc01cde880e8",
      "item": "https://gate.dataloop.ai/api/v1/items/632e6cca9e465e945605801d",
      "dataset": "https://gate.dataloop.ai/api/v1/datasets/632e6c9aff5edd8643bb923f",
      "type": "point",
      "label": "model_found_building",
      "attributes": [],
      "coordinates": {
        "x": 894.3921578210882,
        "y": 975.4506161391772,
        "z": 0
      },
      "metadata": {
        "system": {
          "startTime": 0,
          "endTime": 0,
          "frame": 0,
          "endFrame": 0,
          "snapshots_": [],
          "clientId": "2e767ab2-c123-4010-bd0d-7db14c9c5ebd",
          "automated": false,
          "objectId": "7",
          "isOpen": false,
          "isOnlyLocal": false,
          "attributes": {},
          "system": false,
          "itemLinks": [],
          "openAnnotationVersion": "1.47.1-prod.3",
          "recipeId": "632e6c9b433d0b508cde9dbc",
          "taskId": "6332d8f97eb133c0c6af354a",
          "assignmentId": "6332d8f97eb133476aaf354b",
          "coordinateVersion": "v1"
        },
        "user": {}
      },
      "creator": "lewis.kalata@es.cloudfactory.com",
      "createdAt": "2022-09-27T11:19:12.213Z",
      "updatedBy": "lewis.kalata@es.cloudfactory.com",
      "updatedAt": "2022-09-27T11:19:12.213Z",
      "hash": "79fb2930c0d9497d4657bac0b1883ebdc83ecaed",
      "source": "ui"
    },
    {
      "id": "6332dc7e9fff0517a39f4d8e",
      "datasetId": "632e6c9aff5edd8643bb923f",
      "itemId": "632e6cca9e465e945605801d",
      "url": "https://gate.dataloop.ai/api/v1/annotations/6332dc7e9fff0517a39f4d8e",
      "item": "https://gate.dataloop.ai/api/v1/items/632e6cca9e465e945605801d",
      "dataset": "https://gate.dataloop.ai/api/v1/datasets/632e6c9aff5edd8643bb923f",
      "type": "point",
      "label": "building_missed_by_model",
      "attributes": [],
      "coordinates": {
        "x": 866.4275206000661,
        "y": 833.3150907516554,
        "z": 0
      },
      "metadata": {
        "system": {
          "startTime": 0,
          "endTime": 0,
          "frame": 0,
          "endFrame": 0,
          "snapshots_": [],
          "clientId": "b947003b-1523-45a7-88f6-c51f891751eb",
          "automated": false,
          "objectId": "8",
          "isOpen": false,
          "isOnlyLocal": false,
          "attributes": {},
          "system": false,
          "itemLinks": [],
          "openAnnotationVersion": "1.47.1-prod.3",
          "recipeId": "632e6c9b433d0b508cde9dbc",
          "taskId": "6332d8f97eb133c0c6af354a",
          "assignmentId": "6332d8f97eb133476aaf354b",
          "coordinateVersion": "v1"
        },
        "user": {}
      },
      "creator": "lewis.kalata@es.cloudfactory.com",
      "createdAt": "2022-09-27T11:20:30.443Z",
      "updatedBy": "lewis.kalata@es.cloudfactory.com",
      "updatedAt": "2022-09-27T11:20:30.443Z",
      "hash": "51889d7e73ca556ebad3ae43263d7dba4d4fc849",
      "source": "ui"
    },
    {
      "id": "6332dc7e9fff0588d29f4d8d",
      "datasetId": "632e6c9aff5edd8643bb923f",
      "itemId": "632e6cca9e465e945605801d",
      "url": "https://gate.dataloop.ai/api/v1/annotations/6332dc7e9fff0588d29f4d8d",
      "item": "https://gate.dataloop.ai/api/v1/items/632e6cca9e465e945605801d",
      "dataset": "https://gate.dataloop.ai/api/v1/datasets/632e6c9aff5edd8643bb923f",
      "type": "point",
      "label": "building_missed_by_model",
      "attributes": [],
      "coordinates": {
        "x": 897.5976781892819,
        "y": 858.9400209865735,
        "z": 0
      },
      "metadata": {
        "system": {
          "startTime": 0,
          "endTime": 0,
          "frame": 0,
          "endFrame": 0,
          "snapshots_": [],
          "clientId": "901b6843-64df-4517-9a8e-72c9ed7bc90f",
          "automated": false,
          "objectId": "9",
          "isOpen": false,
          "isOnlyLocal": false,
          "attributes": {},
          "system": false,
          "itemLinks": [],
          "openAnnotationVersion": "1.47.1-prod.3",
          "recipeId": "632e6c9b433d0b508cde9dbc",
          "taskId": "6332d8f97eb133c0c6af354a",
          "assignmentId": "6332d8f97eb133476aaf354b",
          "coordinateVersion": "v1"
        },
        "user": {}
      },
      "creator": "lewis.kalata@es.cloudfactory.com",
      "createdAt": "2022-09-27T11:20:30.441Z",
      "updatedBy": "lewis.kalata@es.cloudfactory.com",
      "updatedAt": "2022-09-27T11:20:30.441Z",
      "hash": "1c804817d91c34ad7b362183c67a27901746b294",
      "source": "ui"
    },
    {
      "id": "6332dc8b45f8cc29f0e88175",
      "datasetId": "632e6c9aff5edd8643bb923f",
      "itemId": "632e6cca9e465e945605801d",
      "url": "https://gate.dataloop.ai/api/v1/annotations/6332dc8b45f8cc29f0e88175",
      "item": "https://gate.dataloop.ai/api/v1/items/632e6cca9e465e945605801d",
      "dataset": "https://gate.dataloop.ai/api/v1/datasets/632e6c9aff5edd8643bb923f",
      "type": "point",
      "label": "building_missed_by_model",
      "attributes": [],
      "coordinates": {
        "x": 860.8973313503666,
        "y": 922.7511217676442,
        "z": 0
      },
      "metadata": {
        "system": {
          "startTime": 0,
          "endTime": 0,
          "frame": 0,
          "endFrame": 0,
          "snapshots_": [],
          "clientId": "cc284e8e-358c-4194-b4e7-d57aacc2cd05",
          "automated": false,
          "objectId": "10",
          "isOpen": false,
          "isOnlyLocal": false,
          "attributes": {},
          "system": false,
          "itemLinks": [],
          "openAnnotationVersion": "1.47.1-prod.3",
          "recipeId": "632e6c9b433d0b508cde9dbc",
          "taskId": "6332d8f97eb133c0c6af354a",
          "assignmentId": "6332d8f97eb133476aaf354b",
          "coordinateVersion": "v1"
        },
        "user": {}
      },
      "creator": "lewis.kalata@es.cloudfactory.com",
      "createdAt": "2022-09-27T11:20:43.478Z",
      "updatedBy": "lewis.kalata@es.cloudfactory.com",
      "updatedAt": "2022-09-27T11:20:43.478Z",
      "hash": "431e1df5031db95cfbd46e5643276956b3486701",
      "source": "ui"
    },
    {
      "id": "6332dca39fff0544899f4de8",
      "datasetId": "632e6c9aff5edd8643bb923f",
      "itemId": "632e6cca9e465e945605801d",
      "url": "https://gate.dataloop.ai/api/v1/annotations/6332dca39fff0544899f4de8",
      "item": "https://gate.dataloop.ai/api/v1/items/632e6cca9e465e945605801d",
      "dataset": "https://gate.dataloop.ai/api/v1/datasets/632e6c9aff5edd8643bb923f",
      "type": "point",
      "label": "model_found_building",
      "attributes": [],
      "coordinates": {
        "x": 921.2266686198163,
        "y": 918.2290752555998,
        "z": 0
      },
      "metadata": {
        "system": {
          "startTime": 0,
          "endTime": 0,
          "frame": 0,
          "endFrame": 0,
          "snapshots_": [],
          "clientId": "13f9a52c-2742-4f7d-a741-783ce6938fa5",
          "automated": false,
          "objectId": "11",
          "isOpen": false,
          "isOnlyLocal": false,
          "attributes": {},
          "system": false,
          "itemLinks": [],
          "openAnnotationVersion": "1.47.1-prod.3",
          "recipeId": "632e6c9b433d0b508cde9dbc",
          "taskId": "6332d8f97eb133c0c6af354a",
          "assignmentId": "6332d8f97eb133476aaf354b",
          "coordinateVersion": "v1"
        },
        "user": {}
      },
      "creator": "lewis.kalata@es.cloudfactory.com",
      "createdAt": "2022-09-27T11:21:07.913Z",
      "updatedBy": "lewis.kalata@es.cloudfactory.com",
      "updatedAt": "2022-09-27T11:21:07.913Z",
      "hash": "b55f1b4d2882dd6f3b4742a7d45454e045a8af7a",
      "source": "ui"
    },
    {
      "id": "6332dca39fff05242d9f4de9",
      "datasetId": "632e6c9aff5edd8643bb923f",
      "itemId": "632e6cca9e465e945605801d",
      "url": "https://gate.dataloop.ai/api/v1/annotations/6332dca39fff05242d9f4de9",
      "item": "https://gate.dataloop.ai/api/v1/items/632e6cca9e465e945605801d",
      "dataset": "https://gate.dataloop.ai/api/v1/datasets/632e6c9aff5edd8643bb923f",
      "type": "point",
      "label": "model_found_building",
      "attributes": [],
      "coordinates": {
        "x": 947.7649852395639,
        "y": 970.1170495839704,
        "z": 0
      },
      "metadata": {
        "system": {
          "startTime": 0,
          "endTime": 0,
          "frame": 0,
          "endFrame": 0,
          "snapshots_": [],
          "clientId": "96b1d59f-13f8-4636-bc10-51cc3d7e81b5",
          "automated": false,
          "objectId": "12",
          "isOpen": false,
          "isOnlyLocal": false,
          "attributes": {},
          "system": false,
          "itemLinks": [],
          "openAnnotationVersion": "1.47.1-prod.3",
          "recipeId": "632e6c9b433d0b508cde9dbc",
          "taskId": "6332d8f97eb133c0c6af354a",
          "assignmentId": "6332d8f97eb133476aaf354b",
          "coordinateVersion": "v1"
        },
        "user": {}
      },
      "creator": "lewis.kalata@es.cloudfactory.com",
      "createdAt": "2022-09-27T11:21:07.915Z",
      "updatedBy": "lewis.kalata@es.cloudfactory.com",
      "updatedAt": "2022-09-27T11:21:07.915Z",
      "hash": "faa553a877c92e6545cb047c0f97c5e6260dd682",
      "source": "ui"
    },
    {
      "id": "6332dcae6fae302471237380",
      "datasetId": "632e6c9aff5edd8643bb923f",
      "itemId": "632e6cca9e465e945605801d",
      "url": "https://gate.dataloop.ai/api/v1/annotations/6332dcae6fae302471237380",
      "item": "https://gate.dataloop.ai/api/v1/items/632e6cca9e465e945605801d",
      "dataset": "https://gate.dataloop.ai/api/v1/datasets/632e6c9aff5edd8643bb923f",
      "type": "point",
      "label": "building_missed_by_model",
      "attributes": [],
      "coordinates": {
        "x": 1035.5629588474899,
        "y": 1105.4254151812056,
        "z": 0
      },
      "metadata": {
        "system": {
          "startTime": 0,
          "endTime": 0,
          "frame": 0,
          "endFrame": 0,
          "snapshots_": [],
          "clientId": "870d98af-dece-4383-a6ce-f2620b5ca00b",
          "automated": false,
          "objectId": "13",
          "isOpen": false,
          "isOnlyLocal": false,
          "attributes": {},
          "system": false,
          "itemLinks": [],
          "openAnnotationVersion": "1.48.2-rc.82",
          "recipeId": "632e6c9b433d0b508cde9dbc",
          "taskId": "6332d8f97eb133c0c6af354a",
          "assignmentId": "6332d8f97eb133476aaf354b",
          "coordinateVersion": "v1"
        },
        "user": {}
      },
      "creator": "lewis.kalata@es.cloudfactory.com",
      "createdAt": "2022-09-27T11:21:18.836Z",
      "updatedBy": "nyambe.mwangelwa@es.cloudfactory.com",
      "updatedAt": "2022-09-30T11:19:52.205Z",
      "hash": "7624aff5cb644467cf0f27a2b5d9760b91657f91",
      "source": "ui"
    },
    {
      "id": "6332dd05f18925871ce1071b",
      "datasetId": "632e6c9aff5edd8643bb923f",
      "itemId": "632e6cca9e465e945605801d",
      "url": "https://gate.dataloop.ai/api/v1/annotations/6332dd05f18925871ce1071b",
      "item": "https://gate.dataloop.ai/api/v1/items/632e6cca9e465e945605801d",
      "dataset": "https://gate.dataloop.ai/api/v1/datasets/632e6c9aff5edd8643bb923f",
      "type": "point",
      "label": "building_missed_by_model",
      "attributes": [],
      "coordinates": {
        "x": 1147.8572871832387,
        "y": 1094.7245534714157,
        "z": 0
      },
      "metadata": {
        "system": {
          "startTime": 0,
          "endTime": 0,
          "frame": 0,
          "endFrame": 0,
          "snapshots_": [],
          "clientId": "a9528b3f-8f0b-4a32-9115-5c9d1ef74f36",
          "automated": false,
          "objectId": "14",
          "isOpen": false,
          "isOnlyLocal": false,
          "attributes": {},
          "system": false,
          "itemLinks": [],
          "openAnnotationVersion": "1.47.1-prod.3",
          "recipeId": "632e6c9b433d0b508cde9dbc",
          "taskId": "6332d8f97eb133c0c6af354a",
          "assignmentId": "6332d8f97eb133476aaf354b",
          "coordinateVersion": "v1"
        },
        "user": {}
      },
      "creator": "lewis.kalata@es.cloudfactory.com",
      "createdAt": "2022-09-27T11:22:45.273Z",
      "updatedBy": "lewis.kalata@es.cloudfactory.com",
      "updatedAt": "2022-09-27T11:22:45.273Z",
      "hash": "7698478734dc9ea9d94bda3695e6d47d75fa74ff",
      "source": "ui"
    },
    {
      "id": "6332dd05f18925749ce10721",
      "datasetId": "632e6c9aff5edd8643bb923f",
      "itemId": "632e6cca9e465e945605801d",
      "url": "https://gate.dataloop.ai/api/v1/annotations/6332dd05f18925749ce10721",
      "item": "https://gate.dataloop.ai/api/v1/items/632e6cca9e465e945605801d",
      "dataset": "https://gate.dataloop.ai/api/v1/datasets/632e6c9aff5edd8643bb923f",
      "type": "point",
      "label": "model_found_new_building",
      "attributes": [],
      "coordinates": {
        "x": 701.6488669684678,
        "y": 1138.280507269149,
        "z": 0
      },
      "metadata": {
        "system": {
          "startTime": 0,
          "endTime": 0,
          "frame": 0,
          "endFrame": 0,
          "snapshots_": [],
          "clientId": "70cdcf39-e29b-46f7-9c48-9bd043991acd",
          "automated": false,
          "objectId": "20",
          "isOpen": false,
          "isOnlyLocal": false,
          "attributes": {},
          "system": false,
          "itemLinks": [],
          "openAnnotationVersion": "1.48.2-rc.82",
          "recipeId": "632e6c9b433d0b508cde9dbc",
          "taskId": "6332d8f97eb133c0c6af354a",
          "assignmentId": "6332d8f97eb133476aaf354b",
          "coordinateVersion": "v1"
        },
        "user": {}
      },
      "creator": "lewis.kalata@es.cloudfactory.com",
      "createdAt": "2022-09-27T11:22:45.285Z",
      "updatedBy": "grace.odemba@es.cloudfactory.com",
      "updatedAt": "2022-09-30T15:00:40.501Z",
      "hash": "d19d1c83e301911ff7117c1b0209b2d0b908a1da",
      "source": "ui"
    },
    {
      "id": "6332dd05f1892530f6e10723",
      "datasetId": "632e6c9aff5edd8643bb923f",
      "itemId": "632e6cca9e465e945605801d",
      "url": "https://gate.dataloop.ai/api/v1/annotations/6332dd05f1892530f6e10723",
      "item": "https://gate.dataloop.ai/api/v1/items/632e6cca9e465e945605801d",
      "dataset": "https://gate.dataloop.ai/api/v1/datasets/632e6c9aff5edd8643bb923f",
      "type": "point",
      "label": "model_found_new_building",
      "attributes": [],
      "coordinates": {
        "x": 1154.3630909267451,
        "y": 1153.6122340749087,
        "z": 0
      },
      "metadata": {
        "system": {
          "startTime": 0,
          "endTime": 0,
          "frame": 0,
          "endFrame": 0,
          "snapshots_": [],
          "clientId": "7fcb7422-d280-40bc-b479-89e0cdf1e287",
          "automated": false,
          "objectId": "22",
          "isOpen": false,
          "isOnlyLocal": false,
          "attributes": {},
          "system": false,
          "itemLinks": [],
          "openAnnotationVersion": "1.48.2-rc.82",
          "recipeId": "632e6c9b433d0b508cde9dbc",
          "taskId": "6332d8f97eb133c0c6af354a",
          "assignmentId": "6332d8f97eb133476aaf354b",
          "coordinateVersion": "v1"
        },
        "user": {}
      },
      "creator": "lewis.kalata@es.cloudfactory.com",
      "createdAt": "2022-09-27T11:22:45.288Z",
      "updatedBy": "grace.odemba@es.cloudfactory.com",
      "updatedAt": "2022-09-30T15:00:40.505Z",
      "hash": "75470dbc3fabad8b3f62e3d0519478eb3dd634b4",
      "source": "ui"
    },
    {
      "id": "6332dd05f18925b2c5e1071e",
      "datasetId": "632e6c9aff5edd8643bb923f",
      "itemId": "632e6cca9e465e945605801d",
      "url": "https://gate.dataloop.ai/api/v1/annotations/6332dd05f18925b2c5e1071e",
      "item": "https://gate.dataloop.ai/api/v1/items/632e6cca9e465e945605801d",
      "dataset": "https://gate.dataloop.ai/api/v1/datasets/632e6c9aff5edd8643bb923f",
      "type": "point",
      "label": "model_found_building",
      "attributes": [],
      "coordinates": {
        "x": 596.1113370573905,
        "y": 1087.2901510835425,
        "z": 0
      },
      "metadata": {
        "system": {
          "startTime": 0,
          "endTime": 0,
          "frame": 0,
          "endFrame": 0,
          "snapshots_": [],
          "clientId": "effa2486-eb5a-4d25-a095-becf004f1efc",
          "automated": false,
          "objectId": "16",
          "isOpen": false,
          "isOnlyLocal": false,
          "attributes": {},
          "system": false,
          "itemLinks": [],
          "openAnnotationVersion": "1.47.1-prod.3",
          "recipeId": "632e6c9b433d0b508cde9dbc",
          "taskId": "6332d8f97eb133c0c6af354a",
          "assignmentId": "6332d8f97eb133476aaf354b",
          "coordinateVersion": "v1"
        },
        "user": {}
      },
      "creator": "lewis.kalata@es.cloudfactory.com",
      "createdAt": "2022-09-27T11:22:45.279Z",
      "updatedBy": "lewis.kalata@es.cloudfactory.com",
      "updatedAt": "2022-09-27T11:22:45.279Z",
      "hash": "eed233a319549e969b13c3515ceb146c8d8b02c7",
      "source": "ui"
    },
    {
      "id": "6332dd05f189254802e10720",
      "datasetId": "632e6c9aff5edd8643bb923f",
      "itemId": "632e6cca9e465e945605801d",
      "url": "https://gate.dataloop.ai/api/v1/annotations/6332dd05f189254802e10720",
      "item": "https://gate.dataloop.ai/api/v1/items/632e6cca9e465e945605801d",
      "dataset": "https://gate.dataloop.ai/api/v1/datasets/632e6c9aff5edd8643bb923f",
      "type": "point",
      "label": "model_found_new_building",
      "attributes": [],
      "coordinates": {
        "x": 956.0599302942426,
        "y": 1156.1804772407152,
        "z": 0
      },
      "metadata": {
        "system": {
          "startTime": 0,
          "endTime": 0,
          "frame": 0,
          "endFrame": 0,
          "snapshots_": [],
          "clientId": "967fb9c5-d3c9-4427-a8cc-ea8633fb4f4f",
          "automated": false,
          "objectId": "21",
          "isOpen": false,
          "isOnlyLocal": false,
          "attributes": {},
          "system": false,
          "itemLinks": [],
          "openAnnotationVersion": "1.48.2-rc.82",
          "recipeId": "632e6c9b433d0b508cde9dbc",
          "taskId": "6332d8f97eb133c0c6af354a",
          "assignmentId": "6332d8f97eb133476aaf354b",
          "coordinateVersion": "v1"
        },
        "user": {}
      },
      "creator": "lewis.kalata@es.cloudfactory.com",
      "createdAt": "2022-09-27T11:22:45.283Z",
      "updatedBy": "grace.odemba@es.cloudfactory.com",
      "updatedAt": "2022-09-30T15:00:40.500Z",
      "hash": "3ee871746fe678c5608ab387e1e77e6b4c52bf8c",
      "source": "ui"
    },
    {
      "id": "6332dd05f189254ee3e1071d",
      "datasetId": "632e6c9aff5edd8643bb923f",
      "itemId": "632e6cca9e465e945605801d",
      "url": "https://gate.dataloop.ai/api/v1/annotations/6332dd05f189254ee3e1071d",
      "item": "https://gate.dataloop.ai/api/v1/items/632e6cca9e465e945605801d",
      "dataset": "https://gate.dataloop.ai/api/v1/datasets/632e6c9aff5edd8643bb923f",
      "type": "point",
      "label": "building_missed_by_model",
      "attributes": [],
      "coordinates": {
        "x": 67.0829093651034,
        "y": 1085.8152116187473,
        "z": 0
      },
      "metadata": {
        "system": {
          "startTime": 0,
          "endTime": 0,
          "frame": 0,
          "endFrame": 0,
          "snapshots_": [],
          "clientId": "e128c389-6263-4089-a699-fe2e958ceea2",
          "automated": false,
          "objectId": "17",
          "isOpen": false,
          "isOnlyLocal": false,
          "attributes": {},
          "system": false,
          "itemLinks": [],
          "openAnnotationVersion": "1.47.1-prod.3",
          "recipeId": "632e6c9b433d0b508cde9dbc",
          "taskId": "6332d8f97eb133c0c6af354a",
          "assignmentId": "6332d8f97eb133476aaf354b",
          "coordinateVersion": "v1"
        },
        "user": {}
      },
      "creator": "lewis.kalata@es.cloudfactory.com",
      "createdAt": "2022-09-27T11:22:45.277Z",
      "updatedBy": "lewis.kalata@es.cloudfactory.com",
      "updatedAt": "2022-09-27T11:22:45.277Z",
      "hash": "ff27185336651680574193f373f023dbb1461b3b",
      "source": "ui"
    },
    {
      "id": "6332dd05f189251972e1071c",
      "datasetId": "632e6c9aff5edd8643bb923f",
      "itemId": "632e6cca9e465e945605801d",
      "url": "https://gate.dataloop.ai/api/v1/annotations/6332dd05f189251972e1071c",
      "item": "https://gate.dataloop.ai/api/v1/items/632e6cca9e465e945605801d",
      "dataset": "https://gate.dataloop.ai/api/v1/datasets/632e6c9aff5edd8643bb923f",
      "type": "point",
      "label": "model_found_new_building",
      "attributes": [],
      "coordinates": {
        "x": 625.6555660804702,
        "y": 1140.1158751185483,
        "z": 0
      },
      "metadata": {
        "system": {
          "startTime": 0,
          "endTime": 0,
          "frame": 0,
          "endFrame": 0,
          "snapshots_": [],
          "clientId": "744cd859-a7d3-4e22-b526-49b6d240e50a",
          "automated": false,
          "objectId": "15",
          "isOpen": false,
          "isOnlyLocal": false,
          "attributes": {},
          "system": false,
          "itemLinks": [],
          "openAnnotationVersion": "1.48.2-rc.82",
          "recipeId": "632e6c9b433d0b508cde9dbc",
          "taskId": "6332d8f97eb133c0c6af354a",
          "assignmentId": "6332d8f97eb133476aaf354b",
          "coordinateVersion": "v1"
        },
        "user": {}
      },
      "creator": "lewis.kalata@es.cloudfactory.com",
      "createdAt": "2022-09-27T11:22:45.275Z",
      "updatedBy": "nyambe.mwangelwa@es.cloudfactory.com",
      "updatedAt": "2022-09-30T11:19:52.196Z",
      "hash": "fee80653d9cf122663cbe111d8b7a1a0bf4cd2bb",
      "source": "ui"
    },
    {
      "id": "6332dd0c45f8cc197ae8825c",
      "datasetId": "632e6c9aff5edd8643bb923f",
      "itemId": "632e6cca9e465e945605801d",
      "url": "https://gate.dataloop.ai/api/v1/annotations/6332dd0c45f8cc197ae8825c",
      "item": "https://gate.dataloop.ai/api/v1/items/632e6cca9e465e945605801d",
      "dataset": "https://gate.dataloop.ai/api/v1/datasets/632e6c9aff5edd8643bb923f",
      "type": "point",
      "label": "building_missed_by_model",
      "attributes": [],
      "coordinates": {
        "x": 1064.1936104883298,
        "y": 1150.007570270403,
        "z": 0
      },
      "metadata": {
        "system": {
          "startTime": 0,
          "endTime": 0,
          "frame": 0,
          "endFrame": 0,
          "snapshots_": [],
          "clientId": "1fab7a1e-0001-4296-b1d5-2df5901f50b6",
          "automated": false,
          "objectId": "23",
          "isOpen": false,
          "isOnlyLocal": false,
          "attributes": {},
          "system": false,
          "itemLinks": [],
          "openAnnotationVersion": "1.47.1-prod.3",
          "recipeId": "632e6c9b433d0b508cde9dbc",
          "taskId": "6332d8f97eb133c0c6af354a",
          "assignmentId": "6332d8f97eb133476aaf354b",
          "coordinateVersion": "v1"
        },
        "user": {}
      },
      "creator": "lewis.kalata@es.cloudfactory.com",
      "createdAt": "2022-09-27T11:22:52.563Z",
      "updatedBy": "lewis.kalata@es.cloudfactory.com",
      "updatedAt": "2022-09-27T11:22:52.563Z",
      "hash": "543f7eab0a4cbada4480b67b0c7a9a948d668811",
      "source": "ui"
    },
    {
      "id": "6336d0d837c277daee4a3f27",
      "datasetId": "632e6c9aff5edd8643bb923f",
      "itemId": "632e6cca9e465e945605801d",
      "url": "https://gate.dataloop.ai/api/v1/annotations/6336d0d837c277daee4a3f27",
      "item": "https://gate.dataloop.ai/api/v1/items/632e6cca9e465e945605801d",
      "dataset": "https://gate.dataloop.ai/api/v1/datasets/632e6c9aff5edd8643bb923f",
      "type": "point",
      "label": "model_found_new_building",
      "attributes": [],
      "coordinates": {
        "x": 538.238303155956,
        "y": 1154.5856801676357,
        "z": 0
      },
      "metadata": {
        "system": {
          "startTime": 0,
          "endTime": 0,
          "frame": 0,
          "endFrame": 0,
          "snapshots_": [],
          "clientId": "3370266e-f46a-474d-9012-c87e0f78d6d7",
          "automated": false,
          "objectId": "24",
          "isOpen": false,
          "isOnlyLocal": false,
          "attributes": {},
          "system": false,
          "itemLinks": [],
          "openAnnotationVersion": "1.48.2-rc.82",
          "recipeId": "632e6c9b433d0b508cde9dbc",
          "taskId": "6336a0a324e1aadd24e5f4ef",
          "assignmentId": "6336a0a424e1aa5616e5f4f3",
          "coordinateVersion": "v1"
        },
        "user": {}
      },
      "creator": "nyambe.mwangelwa@es.cloudfactory.com",
      "createdAt": "2022-09-30T11:19:52.586Z",
      "updatedBy": "nyambe.mwangelwa@es.cloudfactory.com",
      "updatedAt": "2022-09-30T11:19:52.586Z",
      "hash": "8cc9c0b461d6eeacba483f08673e5e1df19e5887",
      "source": "ui"
    },
    {
      "id": "6336d0d837c277664b4a3f28",
      "datasetId": "632e6c9aff5edd8643bb923f",
      "itemId": "632e6cca9e465e945605801d",
      "url": "https://gate.dataloop.ai/api/v1/annotations/6336d0d837c277664b4a3f28",
      "item": "https://gate.dataloop.ai/api/v1/items/632e6cca9e465e945605801d",
      "dataset": "https://gate.dataloop.ai/api/v1/datasets/632e6c9aff5edd8643bb923f",
      "type": "point",
      "label": "model_found_new_building",
      "attributes": [],
      "coordinates": {
        "x": 24.759556217559442,
        "y": 820.8225048179579,
        "z": 0
      },
      "metadata": {
        "system": {
          "startTime": 0,
          "endTime": 0,
          "frame": 0,
          "endFrame": 0,
          "snapshots_": [],
          "clientId": "f3cf2692-3c0f-4d00-8c87-96d755beb174",
          "automated": false,
          "objectId": "25",
          "isOpen": false,
          "isOnlyLocal": false,
          "attributes": {},
          "system": false,
          "itemLinks": [],
          "openAnnotationVersion": "1.48.2-rc.82",
          "recipeId": "632e6c9b433d0b508cde9dbc",
          "taskId": "6336a0a324e1aadd24e5f4ef",
          "assignmentId": "6336a0a424e1aa5616e5f4f3",
          "coordinateVersion": "v1"
        },
        "user": {}
      },
      "creator": "nyambe.mwangelwa@es.cloudfactory.com",
      "createdAt": "2022-09-30T11:19:52.588Z",
      "updatedBy": "nyambe.mwangelwa@es.cloudfactory.com",
      "updatedAt": "2022-09-30T11:19:52.588Z",
      "hash": "77c979c3a3fb3c3dacb6267cab13066237cee450",
      "source": "ui"
    }
  ],
  "annotationsCount": 23,
  "annotated": true
}