{
  "id": "632e6cca9e465e357405807c",
  "datasetId": "632e6c9aff5edd8643bb923f",
  "url": "https://gate.dataloop.ai/api/v1/items/632e6cca9e465e357405807c",
  "dataset": "https://gate.dataloop.ai/api/v1/datasets/632e6c9aff5edd8643bb923f",
  "createdAt": "2022-09-24T02:34:50.000Z",
  "dir": "/2020",
  "filename": "/2020/m_3712142_sw_10_060_20200525_311-small_2020.png",
  "type": "file",
  "hidden": false,
  "metadata": {
    "system": {
      "size": 2014139,
      "taskStatusLog": [
        {
          "status": {
            "taskId": "632e91ec7eb1331d49af333f",
            "assignmentId": "632e91ed7eb1334452af3341",
            "status": "completed",
            "creator": "lewis.kalata@es.cloudfactory.com",
            "timestamp": "2022-09-26T18:31:59.749Z"
          },
          "action": "created"
        },
        {
          "status": {
            "taskId": "6332d9662335fd3b124025ac",
            "assignmentId": "6332d9662335fd52304025ad",
            "status": "approved",
            "creator": "jackline.ogutu@es.cloudfactory.com",
            "timestamp": "2022-09-27T16:34:40.541Z"
          },
          "action": "created"
        }
      ],
      "mimetype": "image/png",
      "isBinary": true,
      "channels": 4,
      "exif": {},
      "height": 1175,
      "thumbnailId": "632e6d5d48a80a4fadcbe690",
      "width": 1174,
      "refs": [
        {
          "id": "632e91ec7eb1331d49af333f",
          "type": "task",
          "metadata": {
            "creator": "lewis.kalata@es.cloudfactory.com",
            "status": "completed",
            "timestamp": "2022-09-26T18:31:59.749Z"
          }
        },
        {
          "id": "632e91ed7eb1334452af3341",
          "type": "assignment",
          "metadata": {
            "creator": "lewis.kalata@es.cloudfactory.com",
            "status": "completed",
            "timestamp": "2022-09-26T18:31:59.749Z"
          }
        },
        {
          "id": "6332d9662335fd3b124025ac",
          "type": "task",
          "metadata": {
            "creator": "jackline.ogutu@es.cloudfactory.com",
            "status": "approved",
            "timestamp": "2022-09-27T16:34:40.541Z"
          }
        },
        {
          "id": "6332d9662335fd52304025ad",
          "type": "assignment",
          "metadata": {
            "creator": "jackline.ogutu@es.cloudfactory.com",
            "status": "approved",
            "timestamp": "2022-09-27T16:34:40.541Z"
          }
        },
        {
          "id": "6336a0a324e1aadd24e5f4ef",
          "type": "task"
        },
        {
          "id": "6336a0a324e1aa0830e5f4f1",
          "type": "assignment"
        }
      ]
    },
    "user": {
      "coordinates": "37.2716284905297, -121.8380039871115",
      "image_year": 2020
    }
  },
  "name": "m_3712142_sw_10_060_20200525_311-small_2020.png",
  "creator": "rubiks@dataloop.ai",
  "stream": "https://gate.dataloop.ai/api/v1/items/632e6cca9e465e357405807c/stream",
  "thumbnail": "https://gate.dataloop.ai/api/v1/items/632e6cca9e465e357405807c/thumbnail",
  "annotations": [
    {
      "id": "6331f01f53404302c7aec952",
      "datasetId": "632e6c9aff5edd8643bb923f",
      "itemId": "632e6cca9e465e357405807c",
      "url": "https://gate.dataloop.ai/api/v1/annotations/6331f01f53404302c7aec952",
      "item": "https://gate.dataloop.ai/api/v1/items/632e6cca9e465e357405807c",
      "dataset": "https://gate.dataloop.ai/api/v1/datasets/632e6c9aff5edd8643bb923f",
      "type": "point",
      "label": "model_found_building",
      "attributes": [],
      "coordinates": {
        "x": 1150.5240771684641,
        "y": 477.30609768429565,
        "z": 0
      },
      "metadata": {
        "system": {
          "startTime": 0,
          "endTime": 0,
          "frame": 0,
          "endFrame": 0,
          "snapshots_": [],
          "clientId": "7c7cc912-f317-4797-a11a-cafd8f69586c",
          "automated": false,
          "objectId": "1",
          "isOpen": false,
          "isOnlyLocal": false,
          "attributes": {},
          "system": false,
          "itemLinks": [],
          "openAnnotationVersion": "1.47.1-prod.3",
          "recipeId": "632e6c9b433d0b508cde9dbc",
          "taskId": "632e91ec7eb1331d49af333f",
          "assignmentId": "632e91ed7eb1334452af3341",
          "coordinateVersion": "v1"
        },
        "user": {}
      },
      "creator": "lewis.kalata@es.cloudfactory.com",
      "createdAt": "2022-09-26T18:31:59.198Z",
      "updatedBy": "lewis.kalata@es.cloudfactory.com",
      "updatedAt": "2022-09-26T18:31:59.198Z",
      "hash": "302540258029d27f9415f01b97d8989bda6a5a50",
      "source": "ui"
    },
    {
      "id": "6331f01f5340437004aec959",
      "datasetId": "632e6c9aff5edd8643bb923f",
      "itemId": "632e6cca9e465e357405807c",
      "url": "https://gate.dataloop.ai/api/v1/annotations/6331f01f5340437004aec959",
      "item": "https://gate.dataloop.ai/api/v1/items/632e6cca9e465e357405807c",
      "dataset": "https://gate.dataloop.ai/api/v1/datasets/632e6c9aff5edd8643bb923f",
      "type": "point",
      "label": "model_found_new_building",
      "attributes": [],
      "coordinates": {
        "x": 550.720890243285,
        "y": 165.15531766973902,
        "z": 0
      },
      "metadata": {
        "system": {
          "startTime": 0,
          "endTime": 0,
          "frame": 0,
          "endFrame": 0,
          "snapshots_": [],
          "clientId": "ebc7a1ee-0979-42fe-bc06-04e8f6da490b",
          "automated": false,
          "objectId": "7",
          "isOpen": false,
          "isOnlyLocal": false,
          "attributes": {},
          "system": false,
          "itemLinks": [],
          "openAnnotationVersion": "1.47.1-prod.3",
          "recipeId": "632e6c9b433d0b508cde9dbc",
          "taskId": "632e91ec7eb1331d49af333f",
          "assignmentId": "632e91ed7eb1334452af3341",
          "coordinateVersion": "v1"
        },
        "user": {}
      },
      "creator": "lewis.kalata@es.cloudfactory.com",
      "createdAt": "2022-09-26T18:31:59.211Z",
      "updatedBy": "lewis.kalata@es.cloudfactory.com",
      "updatedAt": "2022-09-26T18:31:59.211Z",
      "hash": "c03a9eb800bd7b4234b0e86cb253d3f2fb1d0121",
      "source": "ui"
    },
    {
      "id": "6331f01f5340438063aec954",
      "datasetId": "632e6c9aff5edd8643bb923f",
      "itemId": "632e6cca9e465e357405807c",
      "url": "https://gate.dataloop.ai/api/v1/annotations/6331f01f5340438063aec954",
      "item": "https://gate.dataloop.ai/api/v1/items/632e6cca9e465e357405807c",
      "dataset": "https://gate.dataloop.ai/api/v1/datasets/632e6c9aff5edd8643bb923f",
      "type": "point",
      "label": "model_found_building",
      "attributes": [],
      "coordinates": {
        "x": 783.3905514203252,
        "y": 1159.66427343513,
        "z": 0
      },
      "metadata": {
        "system": {
          "startTime": 0,
          "endTime": 0,
          "frame": 0,
          "endFrame": 0,
          "snapshots_": [],
          "clientId": "5c98846d-6d2e-4c85-8cb1-67e02aeb3a7d",
          "automated": false,
          "objectId": "3",
          "isOpen": false,
          "isOnlyLocal": false,
          "attributes": {},
          "system": false,
          "itemLinks": [],
          "openAnnotationVersion": "1.47.1-prod.3",
          "recipeId": "632e6c9b433d0b508cde9dbc",
          "taskId": "632e91ec7eb1331d49af333f",
          "assignmentId": "632e91ed7eb1334452af3341",
          "coordinateVersion": "v1"
        },
        "user": {}
      },
      "creator": "lewis.kalata@es.cloudfactory.com",
      "createdAt": "2022-09-26T18:31:59.202Z",
      "updatedBy": "lewis.kalata@es.cloudfactory.com",
      "updatedAt": "2022-09-26T18:31:59.202Z",
      "hash": "32ab0ba459238cb3da10609d08a21e41a4c17ded",
      "source": "ui"
    },
    {
      "id": "6331f01f534043402baec956",
      "datasetId": "632e6c9aff5edd8643bb923f",
      "itemId": "632e6cca9e465e357405807c",
      "url": "https://gate.dataloop.ai/api/v1/annotations/6331f01f534043402baec956",
      "item": "https://gate.dataloop.ai/api/v1/items/632e6cca9e465e357405807c",
      "dataset": "https://gate.dataloop.ai/api/v1/datasets/632e6c9aff5edd8643bb923f",
      "type": "point",
      "label": "model_found_building",
      "attributes": [],
      "coordinates": {
        "x": 577.295557341054,
        "y": 497.25610060062365,
        "z": 0
      },
      "metadata": {
        "system": {
          "startTime": 0,
          "endTime": 0,
          "frame": 0,
          "endFrame": 0,
          "snapshots_": [],
          "clientId": "e22599cf-725b-4de7-8e50-81226f915f68",
          "automated": false,
          "objectId": "5",
          "isOpen": false,
          "isOnlyLocal": false,
          "attributes": {},
          "system": false,
          "itemLinks": [],
          "openAnnotationVersion": "1.47.1-prod.3",
          "recipeId": "632e6c9b433d0b508cde9dbc",
          "taskId": "632e91ec7eb1331d49af333f",
          "assignmentId": "632e91ed7eb1334452af3341",
          "coordinateVersion": "v1"
        },
        "user": {}
      },
      "creator": "lewis.kalata@es.cloudfactory.com",
      "createdAt": "2022-09-26T18:31:59.206Z",
      "updatedBy": "lewis.kalata@es.cloudfactory.com",
      "updatedAt": "2022-09-26T18:31:59.206Z",
      "hash": "b837b8a2e913cf740ec17e5435486df67f4415b0",
      "source": "ui"
    },
    {
      "id": "6331f01f534043de18aec958",
      "datasetId": "632e6c9aff5edd8643bb923f",
      "itemId": "632e6cca9e465e357405807c",
      "url": "https://gate.dataloop.ai/api/v1/annotations/6331f01f534043de18aec958",
      "item": "https://gate.dataloop.ai/api/v1/items/632e6cca9e465e357405807c",
      "dataset": "https://gate.dataloop.ai/api/v1/datasets/632e6c9aff5edd8643bb923f",
      "type": "point",
      "label": "model_found_new_building",
      "attributes": [],
      "coordinates": {
        "x": 817.2899452189754,
        "y": 414.73513568641454,
        "z": 0
      },
      "metadata": {
        "system": {
          "startTime": 0,
          "endTime": 0,
          "frame": 0,
          "endFrame": 0,
          "snapshots_": [],
          "clientId": "b5fa712d-dbf5-460f-9379-4fdcda199801",
          "automated": false,
          "objectId": "6",
          "isOpen": false,
          "isOnlyLocal": false,
          "attributes": {},
          "system": false,
          "itemLinks": [],
          "openAnnotationVersion": "1.47.1-prod.3",
          "recipeId": "632e6c9b433d0b508cde9dbc",
          "taskId": "632e91ec7eb1331d49af333f",
          "assignmentId": "632e91ed7eb1334452af3341",
          "coordinateVersion": "v1"
        },
        "user": {}
      },
      "creator": "lewis.kalata@es.cloudfactory.com",
      "createdAt": "2022-09-26T18:31:59.210Z",
      "updatedBy": "lewis.kalata@es.cloudfactory.com",
      "updatedAt": "2022-09-26T18:31:59.210Z",
      "hash": "896dc66d77b34f3fea899c1cbcd6871ff14152df",
      "source": "ui"
    },
    {
      "id": "6331f01f5340431a2caec957",
      "datasetId": "632e6c9aff5edd8643bb923f",
      "itemId": "632e6cca9e465e357405807c",
      "url": "https://gate.dataloop.ai/api/v1/annotations/6331f01f5340431a2caec957",
      "item": "https://gate.dataloop.ai/api/v1/items/632e6cca9e465e357405807c",
      "dataset": "https://gate.dataloop.ai/api/v1/datasets/632e6c9aff5edd8643bb923f",
      "type": "point",
      "label": "model_found_new_building",
      "attributes": [],
      "coordinates": {
        "x": 198.27566544329162,
        "y": 697.8488505879874,
        "z": 0
      },
      "metadata": {
        "system": {
          "startTime": 0,
          "endTime": 0,
          "frame": 0,
          "endFrame": 0,
          "snapshots_": [],
          "clientId": "d2fb4ad9-f874-4bd0-9dca-1d61de06bcbb",
          "automated": false,
          "objectId": "8",
          "isOpen": false,
          "isOnlyLocal": false,
          "attributes": {},
          "system": false,
          "itemLinks": [],
          "openAnnotationVersion": "1.47.1-prod.3",
          "recipeId": "632e6c9b433d0b508cde9dbc",
          "taskId": "632e91ec7eb1331d49af333f",
          "assignmentId": "632e91ed7eb1334452af3341",
          "coordinateVersion": "v1"
        },
        "user": {}
      },
      "creator": "lewis.kalata@es.cloudfactory.com",
      "createdAt": "2022-09-26T18:31:59.208Z",
      "updatedBy": "lewis.kalata@es.cloudfactory.com",
      "updatedAt": "2022-09-26T18:31:59.208Z",
      "hash": "31052c20a4bae131a660d1b24cfed5ba20a8e90e",
      "source": "ui"
    },
    {
      "id": "6331f01f534043deb1aec955",
      "datasetId": "632e6c9aff5edd8643bb923f",
      "itemId": "632e6cca9e465e357405807c",
      "url": "https://gate.dataloop.ai/api/v1/annotations/6331f01f534043deb1aec955",
      "item": "https://gate.dataloop.ai/api/v1/items/632e6cca9e465e357405807c",
      "dataset": "https://gate.dataloop.ai/api/v1/datasets/632e6c9aff5edd8643bb923f",
      "type": "point",
      "label": "model_found_building",
      "attributes": [],
      "coordinates": {
        "x": 478.30776241835025,
        "y": 1151.0486399029226,
        "z": 0
      },
      "metadata": {
        "system": {
          "startTime": 0,
          "endTime": 0,
          "frame": 0,
          "endFrame": 0,
          "snapshots_": [],
          "clientId": "abb13059-b72d-4976-99d6-9fa21e72d255",
          "automated": false,
          "objectId": "4",
          "isOpen": false,
          "isOnlyLocal": false,
          "attributes": {},
          "system": false,
          "itemLinks": [],
          "openAnnotationVersion": "1.47.1-prod.3",
          "recipeId": "632e6c9b433d0b508cde9dbc",
          "taskId": "632e91ec7eb1331d49af333f",
          "assignmentId": "632e91ed7eb1334452af3341",
          "coordinateVersion": "v1"
        },
        "user": {}
      },
      "creator": "lewis.kalata@es.cloudfactory.com",
      "createdAt": "2022-09-26T18:31:59.204Z",
      "updatedBy": "lewis.kalata@es.cloudfactory.com",
      "updatedAt": "2022-09-26T18:31:59.204Z",
      "hash": "5648698c64b4df5f6eea54ceb009ea108f94afae",
      "source": "ui"
    },
    {
      "id": "6331f01f5340434ffdaec953",
      "datasetId": "632e6c9aff5edd8643bb923f",
      "itemId": "632e6cca9e465e357405807c",
      "url": "https://gate.dataloop.ai/api/v1/annotations/6331f01f5340434ffdaec953",
      "item": "https://gate.dataloop.ai/api/v1/items/632e6cca9e465e357405807c",
      "dataset": "https://gate.dataloop.ai/api/v1/datasets/632e6c9aff5edd8643bb923f",
      "type": "point",
      "label": "model_found_building",
      "attributes": [],
      "coordinates": {
        "x": 912.6629196415009,
        "y": 1157.9411467286886,
        "z": 0
      },
      "metadata": {
        "system": {
          "startTime": 0,
          "endTime": 0,
          "frame": 0,
          "endFrame": 0,
          "snapshots_": [],
          "clientId": "5c83722a-ae50-4207-af52-9e17e54507fa",
          "automated": false,
          "objectId": "2",
          "isOpen": false,
          "isOnlyLocal": false,
          "attributes": {},
          "system": false,
          "itemLinks": [],
          "openAnnotationVersion": "1.47.1-prod.3",
          "recipeId": "632e6c9b433d0b508cde9dbc",
          "taskId": "632e91ec7eb1331d49af333f",
          "assignmentId": "632e91ed7eb1334452af3341",
          "coordinateVersion": "v1"
        },
        "user": {}
      },
      "creator": "lewis.kalata@es.cloudfactory.com",
      "createdAt": "2022-09-26T18:31:59.199Z",
      "updatedBy": "lewis.kalata@es.cloudfactory.com",
      "updatedAt": "2022-09-26T18:31:59.199Z",
      "hash": "0c6985059d0b931f0a419dac3a5750237dd95a45",
      "source": "ui"
    }
  ],
  "annotationsCount": 8,
  "annotated": true
}