{
  "id": "632e6cca9e465e03a0058092",
  "datasetId": "632e6c9aff5edd8643bb923f",
  "url": "https://gate.dataloop.ai/api/v1/items/632e6cca9e465e03a0058092",
  "dataset": "https://gate.dataloop.ai/api/v1/datasets/632e6c9aff5edd8643bb923f",
  "createdAt": "2022-09-24T02:34:50.000Z",
  "dir": "/2020",
  "filename": "/2020/m_3712150_ne_10_060_20200525_28-small_2020.png",
  "type": "file",
  "hidden": false,
  "metadata": {
    "system": {
      "size": 2253294,
      "taskStatusLog": [
        {
          "status": {
            "taskId": "632e91ec7eb1331d49af333f",
            "assignmentId": "632e91ec7eb133e32aaf3340",
            "status": "completed",
            "creator": "nyambe.mwangelwa@es.cloudfactory.com",
            "timestamp": "2022-09-26T13:56:04.989Z"
          },
          "action": "created"
        },
        {
          "status": {
            "taskId": "6333105e7eb13353eaaf3571",
            "assignmentId": "6333105f7eb133fe2aaf3572",
            "status": "approved",
            "creator": "grace.odemba@es.cloudfactory.com",
            "timestamp": "2022-09-27T15:48:11.978Z"
          },
          "action": "created"
        },
        {
          "status": {
            "taskId": "6336a0a324e1aadd24e5f4ef",
            "assignmentId": "6336a0a324e1aa715ce5f4f0",
            "status": "completed",
            "creator": "lewis.kalata@es.cloudfactory.com",
            "timestamp": "2022-09-30T15:26:11.253Z"
          },
          "action": "created"
        }
      ],
      "mimetype": "image/png",
      "isBinary": true,
      "channels": 4,
      "exif": {},
      "height": 1175,
      "thumbnailId": "632e6d5848a80a5b67cbe68d",
      "width": 1174,
      "refs": [
        {
          "id": "632e91ec7eb1331d49af333f",
          "type": "task",
          "metadata": {
            "creator": "nyambe.mwangelwa@es.cloudfactory.com",
            "status": "completed",
            "timestamp": "2022-09-26T13:56:04.989Z"
          }
        },
        {
          "id": "632e91ec7eb133e32aaf3340",
          "type": "assignment",
          "metadata": {
            "creator": "nyambe.mwangelwa@es.cloudfactory.com",
            "status": "completed",
            "timestamp": "2022-09-26T13:56:04.989Z"
          }
        },
        {
          "id": "6333105e7eb13353eaaf3571",
          "type": "task",
          "metadata": {
            "creator": "grace.odemba@es.cloudfactory.com",
            "status": "approved",
            "timestamp": "2022-09-27T15:48:11.978Z"
          }
        },
        {
          "id": "6333105f7eb133fe2aaf3572",
          "type": "assignment",
          "metadata": {
            "creator": "grace.odemba@es.cloudfactory.com",
            "status": "approved",
            "timestamp": "2022-09-27T15:48:11.978Z"
          }
        },
        {
          "id": "6336a0a324e1aadd24e5f4ef",
          "type": "task",
          "metadata": {
            "creator": "lewis.kalata@es.cloudfactory.com",
            "status": "completed",
            "timestamp": "2022-09-30T15:26:11.253Z"
          }
        },
        {
          "id": "6336a0a324e1aa715ce5f4f0",
          "type": "assignment",
          "metadata": {
            "creator": "lewis.kalata@es.cloudfactory.com",
            "status": "completed",
            "timestamp": "2022-09-30T15:26:11.253Z"
          }
        }
      ]
    },
    "user": {
      "coordinates": "37.2480507943124, -121.7853688971908",
      "image_year": 2020
    }
  },
  "name": "m_3712150_ne_10_060_20200525_28-small_2020.png",
  "creator": "rubiks@dataloop.ai",
  "stream": "https://gate.dataloop.ai/api/v1/items/632e6cca9e465e03a0058092/stream",
  "thumbnail": "https://gate.dataloop.ai/api/v1/items/632e6cca9e465e03a0058092/thumbnail",
  "annotations": [
    {
      "id": "6331ad919d0400b0182114e7",
      "datasetId": "632e6c9aff5edd8643bb923f",
      "itemId": "632e6cca9e465e03a0058092",
      "url": "https://gate.dataloop.ai/api/v1/annotations/6331ad919d0400b0182114e7",
      "item": "https://gate.dataloop.ai/api/v1/items/632e6cca9e465e03a0058092",
      "dataset": "https://gate.dataloop.ai/api/v1/datasets/632e6c9aff5edd8643bb923f",
      "type": "point",
      "label": "model_found_building",
      "attributes": [],
      "coordinates": {
        "x": 359.7171891549913,
        "y": 633.1641418103651,
        "z": 0
      },
      "metadata": {
        "system": {
          "startTime": 0,
          "endTime": 0,
          "frame": 0,
          "endFrame": 0,
          "snapshots_": [],
          "clientId": "1e4f2799-2b54-4f49-aa44-549291be03ad",
          "automated": false,
          "objectId": "1",
          "isOpen": false,
          "isOnlyLocal": false,
          "attributes": {},
          "system": false,
          "itemLinks": [],
          "openAnnotationVersion": "1.48.2-rc.82",
          "recipeId": "632e6c9b433d0b508cde9dbc",
          "taskId": "632e91ec7eb1331d49af333f",
          "assignmentId": "632e91ec7eb133e32aaf3340",
          "coordinateVersion": "v1"
        },
        "user": {}
      },
      "creator": "nyambe.mwangelwa@es.cloudfactory.com",
      "createdAt": "2022-09-26T13:48:01.846Z",
      "updatedBy": "lewis.kalata@es.cloudfactory.com",
      "updatedAt": "2022-09-30T15:24:24.728Z",
      "hash": "cbb921443eaf4afbf3be32303f494584b67dbc3b",
      "source": "ui"
    },
    {
      "id": "6331ae16526e5ca795d24069",
      "datasetId": "632e6c9aff5edd8643bb923f",
      "itemId": "632e6cca9e465e03a0058092",
      "url": "https://gate.dataloop.ai/api/v1/annotations/6331ae16526e5ca795d24069",
      "item": "https://gate.dataloop.ai/api/v1/items/632e6cca9e465e03a0058092",
      "dataset": "https://gate.dataloop.ai/api/v1/datasets/632e6c9aff5edd8643bb923f",
      "type": "point",
      "label": "model_found_new_building",
      "attributes": [],
      "coordinates": {
        "x": 818.5759547650678,
        "y": 621.4391524226324,
        "z": 0
      },
      "metadata": {
        "system": {
          "startTime": 0,
          "endTime": 0,
          "frame": 0,
          "endFrame": 0,
          "snapshots_": [],
          "clientId": "43684721-03cf-4275-9ce5-3fc45d93e8d5",
          "automated": false,
          "objectId": "2",
          "isOpen": false,
          "isOnlyLocal": false,
          "attributes": {},
          "system": false,
          "itemLinks": [],
          "openAnnotationVersion": "1.47.1-prod.3",
          "recipeId": "632e6c9b433d0b508cde9dbc",
          "taskId": "632e91ec7eb1331d49af333f",
          "assignmentId": "632e91ec7eb133e32aaf3340",
          "coordinateVersion": "v1"
        },
        "user": {}
      },
      "creator": "nyambe.mwangelwa@es.cloudfactory.com",
      "createdAt": "2022-09-26T13:50:14.382Z",
      "updatedBy": "nyambe.mwangelwa@es.cloudfactory.com",
      "updatedAt": "2022-09-26T13:50:14.382Z",
      "hash": "a31679c9a25c28e4c74cf9681499aa44e67d52af",
      "source": "ui"
    },
    {
      "id": "6331af1d526e5c42ead2423a",
      "datasetId": "632e6c9aff5edd8643bb923f",
      "itemId": "632e6cca9e465e03a0058092",
      "url": "https://gate.dataloop.ai/api/v1/annotations/6331af1d526e5c42ead2423a",
      "item": "https://gate.dataloop.ai/api/v1/items/632e6cca9e465e03a0058092",
      "dataset": "https://gate.dataloop.ai/api/v1/datasets/632e6c9aff5edd8643bb923f",
      "type": "point",
      "label": "model_found_new_building",
      "attributes": [],
      "coordinates": {
        "x": 257.4731980086904,
        "y": 874.793036157193,
        "z": 0
      },
      "metadata": {
        "system": {
          "startTime": 0,
          "endTime": 0,
          "frame": 0,
          "endFrame": 0,
          "snapshots_": [],
          "clientId": "fb777eb0-85fc-4923-bf1b-258b524159d4",
          "automated": false,
          "objectId": "3",
          "isOpen": false,
          "isOnlyLocal": false,
          "attributes": {},
          "system": false,
          "itemLinks": [],
          "openAnnotationVersion": "1.47.1-prod.3",
          "recipeId": "632e6c9b433d0b508cde9dbc",
          "taskId": "632e91ec7eb1331d49af333f",
          "assignmentId": "632e91ec7eb133e32aaf3340",
          "coordinateVersion": "v1"
        },
        "user": {}
      },
      "creator": "nyambe.mwangelwa@es.cloudfactory.com",
      "createdAt": "2022-09-26T13:54:37.000Z",
      "updatedBy": "nyambe.mwangelwa@es.cloudfactory.com",
      "updatedAt": "2022-09-26T13:54:37.000Z",
      "hash": "f22b37578a25acc10fa6d5110dbe12a88b82549b",
      "source": "ui"
    },
    {
      "id": "6331c85d526e5ca570d26256",
      "datasetId": "632e6c9aff5edd8643bb923f",
      "itemId": "632e6cca9e465e03a0058092",
      "url": "https://gate.dataloop.ai/api/v1/annotations/6331c85d526e5ca570d26256",
      "item": "https://gate.dataloop.ai/api/v1/items/632e6cca9e465e03a0058092",
      "dataset": "https://gate.dataloop.ai/api/v1/datasets/632e6c9aff5edd8643bb923f",
      "type": "point",
      "label": "model_found_building",
      "attributes": [],
      "coordinates": {
        "x": 1088.6067145610623,
        "y": 1157.4549628850566,
        "z": 0
      },
      "metadata": {
        "system": {
          "startTime": 0,
          "endTime": 0,
          "frame": 0,
          "endFrame": 0,
          "snapshots_": [],
          "clientId": "b1be56ce-c7c5-43d3-be8c-9f9ae4f50961",
          "automated": false,
          "objectId": "7",
          "isOpen": false,
          "isOnlyLocal": false,
          "attributes": {},
          "system": false,
          "itemLinks": [],
          "openAnnotationVersion": "1.48.2-rc.82",
          "recipeId": "632e6c9b433d0b508cde9dbc",
          "taskId": "632e91ec7eb1331d49af333f",
          "assignmentId": "632e91ec7eb133e32aaf3340",
          "coordinateVersion": "v1"
        },
        "user": {}
      },
      "creator": "nyambe.mwangelwa@es.cloudfactory.com",
      "createdAt": "2022-09-26T15:42:21.236Z",
      "updatedBy": "lewis.kalata@es.cloudfactory.com",
      "updatedAt": "2022-09-30T15:26:09.986Z",
      "hash": "dffbf13c4077389d82e80f93acac7735204143e1",
      "source": "ui"
    },
    {
      "id": "6331c85d526e5c5512d26257",
      "datasetId": "632e6c9aff5edd8643bb923f",
      "itemId": "632e6cca9e465e03a0058092",
      "url": "https://gate.dataloop.ai/api/v1/annotations/6331c85d526e5c5512d26257",
      "item": "https://gate.dataloop.ai/api/v1/items/632e6cca9e465e03a0058092",
      "dataset": "https://gate.dataloop.ai/api/v1/datasets/632e6c9aff5edd8643bb923f",
      "type": "point",
      "label": "model_found_building",
      "attributes": [],
      "coordinates": {
        "x": 704.945138175586,
        "y": 1154.6753938151476,
        "z": 0
      },
      "metadata": {
        "system": {
          "startTime": 0,
          "endTime": 0,
          "frame": 0,
          "endFrame": 0,
          "snapshots_": [],
          "clientId": "651a3ad3-ba3c-48a7-ba5d-3a49cf273a29",
          "automated": false,
          "objectId": "5",
          "isOpen": false,
          "isOnlyLocal": false,
          "attributes": {},
          "system": false,
          "itemLinks": [],
          "openAnnotationVersion": "1.48.2-rc.82",
          "recipeId": "632e6c9b433d0b508cde9dbc",
          "taskId": "632e91ec7eb1331d49af333f",
          "assignmentId": "632e91ec7eb133e32aaf3340",
          "coordinateVersion": "v1"
        },
        "user": {}
      },
      "creator": "nyambe.mwangelwa@es.cloudfactory.com",
      "createdAt": "2022-09-26T15:42:21.237Z",
      "updatedBy": "lewis.kalata@es.cloudfactory.com",
      "updatedAt": "2022-09-30T15:26:09.975Z",
      "hash": "8d31b07a4efe62f2878634164166d9db07c2140f",
      "source": "ui"
    },
    {
      "id": "6331c85d526e5c10b3d26258",
      "datasetId": "632e6c9aff5edd8643bb923f",
      "itemId": "632e6cca9e465e03a0058092",
      "url": "https://gate.dataloop.ai/api/v1/annotations/6331c85d526e5c10b3d26258",
      "item": "https://gate.dataloop.ai/api/v1/items/632e6cca9e465e03a0058092",
      "dataset": "https://gate.dataloop.ai/api/v1/datasets/632e6c9aff5edd8643bb923f",
      "type": "point",
      "label": "model_found_building",
      "attributes": [],
      "coordinates": {
        "x": 813.9934918791794,
        "y": 1155.8336318503846,
        "z": 0
      },
      "metadata": {
        "system": {
          "startTime": 0,
          "endTime": 0,
          "frame": 0,
          "endFrame": 0,
          "snapshots_": [],
          "clientId": "344e9b40-df9b-4672-8e78-db940861da36",
          "automated": false,
          "objectId": "6",
          "isOpen": false,
          "isOnlyLocal": false,
          "attributes": {},
          "system": false,
          "itemLinks": [],
          "openAnnotationVersion": "1.48.2-rc.82",
          "recipeId": "632e6c9b433d0b508cde9dbc",
          "taskId": "632e91ec7eb1331d49af333f",
          "assignmentId": "632e91ec7eb133e32aaf3340",
          "coordinateVersion": "v1"
        },
        "user": {}
      },
      "creator": "nyambe.mwangelwa@es.cloudfactory.com",
      "createdAt": "2022-09-26T15:42:21.239Z",
      "updatedBy": "lewis.kalata@es.cloudfactory.com",
      "updatedAt": "2022-09-30T15:26:10.263Z",
      "hash": "189868d7427e3ad3bef2a0e7cf619d99777954f0",
      "source": "ui"
    },
    {
      "id": "63370a290840da3e0facf57f",
      "datasetId": "632e6c9aff5edd8643bb923f",
      "itemId": "632e6cca9e465e03a0058092",
      "url": "https://gate.dataloop.ai/api/v1/annotations/63370a290840da3e0facf57f",
      "item": "https://gate.dataloop.ai/api/v1/items/632e6cca9e465e03a0058092",
      "dataset": "https://gate.dataloop.ai/api/v1/datasets/632e6c9aff5edd8643bb923f",
      "type": "point",
      "label": "model_found_new_building",
      "attributes": [],
      "coordinates": {
        "x": 1125.2816894421737,
        "y": 99.33331803059825,
        "z": 0
      },
      "metadata": {
        "system": {
          "startTime": 0,
          "endTime": 0,
          "frame": 0,
          "endFrame": 0,
          "snapshots_": [],
          "clientId": "d197050b-e333-4e25-a5b6-11d76c5468e0",
          "automated": false,
          "objectId": "8",
          "isOpen": false,
          "isOnlyLocal": false,
          "attributes": {},
          "system": false,
          "itemLinks": [],
          "openAnnotationVersion": "1.48.2-rc.82",
          "recipeId": "632e6c9b433d0b508cde9dbc",
          "taskId": "6336a0a324e1aadd24e5f4ef",
          "assignmentId": "6336a0a324e1aa715ce5f4f0",
          "coordinateVersion": "v1"
        },
        "user": {}
      },
      "creator": "lewis.kalata@es.cloudfactory.com",
      "createdAt": "2022-09-30T15:24:25.251Z",
      "updatedBy": "lewis.kalata@es.cloudfactory.com",
      "updatedAt": "2022-09-30T15:24:25.251Z",
      "hash": "f6abe3290916844c0710262663bebf8e466a3931",
      "source": "ui"
    },
    {
      "id": "63370a92c57ba4080a34ec21",
      "datasetId": "632e6c9aff5edd8643bb923f",
      "itemId": "632e6cca9e465e03a0058092",
      "url": "https://gate.dataloop.ai/api/v1/annotations/63370a92c57ba4080a34ec21",
      "item": "https://gate.dataloop.ai/api/v1/items/632e6cca9e465e03a0058092",
      "dataset": "https://gate.dataloop.ai/api/v1/datasets/632e6c9aff5edd8643bb923f",
      "type": "point",
      "label": "model_found_building",
      "attributes": [],
      "coordinates": {
        "x": 479.3667587982476,
        "y": 1158.9367622065474,
        "z": 0
      },
      "metadata": {
        "system": {
          "startTime": 0,
          "endTime": 0,
          "frame": 0,
          "endFrame": 0,
          "snapshots_": [],
          "clientId": "4f1ac1a4-bc8c-481c-ad79-2dc7375ae48b",
          "automated": false,
          "objectId": "10",
          "isOpen": false,
          "isOnlyLocal": false,
          "attributes": {},
          "system": false,
          "itemLinks": [],
          "openAnnotationVersion": "1.48.2-rc.82",
          "recipeId": "632e6c9b433d0b508cde9dbc",
          "taskId": "6336a0a324e1aadd24e5f4ef",
          "assignmentId": "6336a0a324e1aa715ce5f4f0",
          "coordinateVersion": "v1"
        },
        "user": {}
      },
      "creator": "lewis.kalata@es.cloudfactory.com",
      "createdAt": "2022-09-30T15:26:10.672Z",
      "updatedBy": "lewis.kalata@es.cloudfactory.com",
      "updatedAt": "2022-09-30T15:26:10.672Z",
      "hash": "382492167321676ef6df65439b593bcc1106a114",
      "source": "ui"
    },
    {
      "id": "63370a92c57ba4a7db34ec22",
      "datasetId": "632e6c9aff5edd8643bb923f",
      "itemId": "632e6cca9e465e03a0058092",
      "url": "https://gate.dataloop.ai/api/v1/annotations/63370a92c57ba4a7db34ec22",
      "item": "https://gate.dataloop.ai/api/v1/items/632e6cca9e465e03a0058092",
      "dataset": "https://gate.dataloop.ai/api/v1/datasets/632e6c9aff5edd8643bb923f",
      "type": "point",
      "label": "model_found_building",
      "attributes": [],
      "coordinates": {
        "x": 314.82735780533557,
        "y": 76.42847490783404,
        "z": 0
      },
      "metadata": {
        "system": {
          "startTime": 0,
          "endTime": 0,
          "frame": 0,
          "endFrame": 0,
          "snapshots_": [],
          "clientId": "4fb44acd-4d1c-4dd6-9280-46a84bd83418",
          "automated": false,
          "objectId": "9",
          "isOpen": false,
          "isOnlyLocal": false,
          "attributes": {},
          "system": false,
          "itemLinks": [],
          "openAnnotationVersion": "1.48.2-rc.82",
          "recipeId": "632e6c9b433d0b508cde9dbc",
          "taskId": "6336a0a324e1aadd24e5f4ef",
          "assignmentId": "6336a0a324e1aa715ce5f4f0",
          "coordinateVersion": "v1"
        },
        "user": {}
      },
      "creator": "lewis.kalata@es.cloudfactory.com",
      "createdAt": "2022-09-30T15:26:10.674Z",
      "updatedBy": "lewis.kalata@es.cloudfactory.com",
      "updatedAt": "2022-09-30T15:26:10.674Z",
      "hash": "f150910c74553f37861b57c1da2542438335b315",
      "source": "ui"
    }
  ],
  "annotationsCount": 9,
  "annotated": true
}