{
  "id": "632e6cca9e465e2da9058028",
  "datasetId": "632e6c9aff5edd8643bb923f",
  "url": "https://gate.dataloop.ai/api/v1/items/632e6cca9e465e2da9058028",
  "dataset": "https://gate.dataloop.ai/api/v1/datasets/632e6c9aff5edd8643bb923f",
  "createdAt": "2022-09-24T02:34:50.000Z",
  "dir": "/2020",
  "filename": "/2020/m_3712141_ne_10_060_20200525_288-small_2020.png",
  "type": "file",
  "hidden": false,
  "metadata": {
    "system": {
      "size": 1508377,
      "taskStatusLog": [
        {
          "status": {
            "taskId": "632e91ec7eb1331d49af333f",
            "assignmentId": "632e91ed7eb1334452af3341",
            "status": "completed",
            "creator": "lewis.kalata@es.cloudfactory.com",
            "timestamp": "2022-09-26T18:12:54.656Z"
          },
          "action": "created"
        },
        {
          "status": {
            "taskId": "6332d9662335fd3b124025ac",
            "assignmentId": "6332d9662335fd52304025ad",
            "status": "approved",
            "creator": "jackline.ogutu@es.cloudfactory.com",
            "timestamp": "2022-09-27T15:13:57.438Z"
          },
          "action": "created"
        }
      ],
      "mimetype": "image/png",
      "isBinary": true,
      "channels": 4,
      "exif": {},
      "height": 1175,
      "thumbnailId": "632e6cd88493479d8e0e54e4",
      "width": 1174,
      "refs": [
        {
          "id": "632e91ec7eb1331d49af333f",
          "type": "task",
          "metadata": {
            "creator": "lewis.kalata@es.cloudfactory.com",
            "status": "completed",
            "timestamp": "2022-09-26T18:12:54.656Z"
          }
        },
        {
          "id": "632e91ed7eb1334452af3341",
          "type": "assignment",
          "metadata": {
            "creator": "lewis.kalata@es.cloudfactory.com",
            "status": "completed",
            "timestamp": "2022-09-26T18:12:54.656Z"
          }
        },
        {
          "id": "6332d9662335fd3b124025ac",
          "type": "task",
          "metadata": {
            "creator": "jackline.ogutu@es.cloudfactory.com",
            "status": "approved",
            "timestamp": "2022-09-27T15:13:57.438Z"
          }
        },
        {
          "id": "6332d9662335fd52304025ad",
          "type": "assignment",
          "metadata": {
            "creator": "jackline.ogutu@es.cloudfactory.com",
            "status": "approved",
            "timestamp": "2022-09-27T15:13:57.438Z"
          }
        },
        {
          "id": "6336a0a324e1aadd24e5f4ef",
          "type": "task"
        },
        {
          "id": "6336a0a324e1aa0830e5f4f1",
          "type": "assignment"
        }
      ]
    },
    "user": {
      "coordinates": "37.3370125810823, -121.9107965118261",
      "image_year": 2020
    }
  },
  "name": "m_3712141_ne_10_060_20200525_288-small_2020.png",
  "creator": "rubiks@dataloop.ai",
  "stream": "https://gate.dataloop.ai/api/v1/items/632e6cca9e465e2da9058028/stream",
  "thumbnail": "https://gate.dataloop.ai/api/v1/items/632e6cca9e465e2da9058028/thumbnail",
  "annotations": [
    {
      "id": "6331ea489635398e679f5676",
      "datasetId": "632e6c9aff5edd8643bb923f",
      "itemId": "632e6cca9e465e2da9058028",
      "url": "https://gate.dataloop.ai/api/v1/annotations/6331ea489635398e679f5676",
      "item": "https://gate.dataloop.ai/api/v1/items/632e6cca9e465e2da9058028",
      "dataset": "https://gate.dataloop.ai/api/v1/datasets/632e6c9aff5edd8643bb923f",
      "type": "point",
      "label": "model_found_new_building",
      "attributes": [],
      "coordinates": {
        "x": 118.59244317394219,
        "y": 1084.404523345976,
        "z": 0
      },
      "metadata": {
        "system": {
          "startTime": 0,
          "endTime": 0,
          "frame": 0,
          "endFrame": 0,
          "snapshots_": [],
          "clientId": "1e599d79-32ba-44ba-9a23-e7be9401334e",
          "automated": false,
          "objectId": "1",
          "isOpen": false,
          "isOnlyLocal": false,
          "attributes": {},
          "system": false,
          "itemLinks": [],
          "openAnnotationVersion": "1.47.1-prod.3",
          "recipeId": "632e6c9b433d0b508cde9dbc",
          "taskId": "632e91ec7eb1331d49af333f",
          "assignmentId": "632e91ed7eb1334452af3341",
          "coordinateVersion": "v1"
        },
        "user": {}
      },
      "creator": "lewis.kalata@es.cloudfactory.com",
      "createdAt": "2022-09-26T18:07:04.031Z",
      "updatedBy": "lewis.kalata@es.cloudfactory.com",
      "updatedAt": "2022-09-26T18:07:04.031Z",
      "hash": "71e8e16a5eb435fcf737387cc2ea02b18c815008",
      "source": "ui"
    },
    {
      "id": "6331ea489635393f429f5677",
      "datasetId": "632e6c9aff5edd8643bb923f",
      "itemId": "632e6cca9e465e2da9058028",
      "url": "https://gate.dataloop.ai/api/v1/annotations/6331ea489635393f429f5677",
      "item": "https://gate.dataloop.ai/api/v1/items/632e6cca9e465e2da9058028",
      "dataset": "https://gate.dataloop.ai/api/v1/datasets/632e6c9aff5edd8643bb923f",
      "type": "point",
      "label": "model_found_building",
      "attributes": [],
      "coordinates": {
        "x": 239.78559782099714,
        "y": 971.5998453412885,
        "z": 0
      },
      "metadata": {
        "system": {
          "startTime": 0,
          "endTime": 0,
          "frame": 0,
          "endFrame": 0,
          "snapshots_": [],
          "clientId": "26e63f6c-0ca4-4561-86e5-b736260e927c",
          "automated": false,
          "objectId": "3",
          "isOpen": false,
          "isOnlyLocal": false,
          "attributes": {},
          "system": false,
          "itemLinks": [],
          "openAnnotationVersion": "1.47.1-prod.3",
          "recipeId": "632e6c9b433d0b508cde9dbc",
          "taskId": "632e91ec7eb1331d49af333f",
          "assignmentId": "632e91ed7eb1334452af3341",
          "coordinateVersion": "v1"
        },
        "user": {}
      },
      "creator": "lewis.kalata@es.cloudfactory.com",
      "createdAt": "2022-09-26T18:07:04.030Z",
      "updatedBy": "lewis.kalata@es.cloudfactory.com",
      "updatedAt": "2022-09-26T18:07:04.030Z",
      "hash": "c0ea947c9240eae374315e91f04c8b958d9cc51b",
      "source": "ui"
    },
    {
      "id": "6331ea489635396cf49f5675",
      "datasetId": "632e6c9aff5edd8643bb923f",
      "itemId": "632e6cca9e465e2da9058028",
      "url": "https://gate.dataloop.ai/api/v1/annotations/6331ea489635396cf49f5675",
      "item": "https://gate.dataloop.ai/api/v1/items/632e6cca9e465e2da9058028",
      "dataset": "https://gate.dataloop.ai/api/v1/datasets/632e6c9aff5edd8643bb923f",
      "type": "point",
      "label": "model_found_building",
      "attributes": [],
      "coordinates": {
        "x": 153.96211920827582,
        "y": 1044.3770569572162,
        "z": 0
      },
      "metadata": {
        "system": {
          "startTime": 0,
          "endTime": 0,
          "frame": 0,
          "endFrame": 0,
          "snapshots_": [],
          "clientId": "6c40d867-36aa-49a2-9fac-cff882257842",
          "automated": false,
          "objectId": "2",
          "isOpen": false,
          "isOnlyLocal": false,
          "attributes": {},
          "system": false,
          "itemLinks": [],
          "openAnnotationVersion": "1.47.1-prod.3",
          "recipeId": "632e6c9b433d0b508cde9dbc",
          "taskId": "632e91ec7eb1331d49af333f",
          "assignmentId": "632e91ed7eb1334452af3341",
          "coordinateVersion": "v1"
        },
        "user": {}
      },
      "creator": "lewis.kalata@es.cloudfactory.com",
      "createdAt": "2022-09-26T18:07:04.032Z",
      "updatedBy": "lewis.kalata@es.cloudfactory.com",
      "updatedAt": "2022-09-26T18:07:04.032Z",
      "hash": "3696f7562a4f78913930855ff6bcec8a6b2cd252",
      "source": "ui"
    },
    {
      "id": "6331ea4896353944c39f5678",
      "datasetId": "632e6c9aff5edd8643bb923f",
      "itemId": "632e6cca9e465e2da9058028",
      "url": "https://gate.dataloop.ai/api/v1/annotations/6331ea4896353944c39f5678",
      "item": "https://gate.dataloop.ai/api/v1/items/632e6cca9e465e2da9058028",
      "dataset": "https://gate.dataloop.ai/api/v1/datasets/632e6c9aff5edd8643bb923f",
      "type": "point",
      "label": "model_found_building",
      "attributes": [],
      "coordinates": {
        "x": 321.447938076738,
        "y": 897.2631220478769,
        "z": 0
      },
      "metadata": {
        "system": {
          "startTime": 0,
          "endTime": 0,
          "frame": 0,
          "endFrame": 0,
          "snapshots_": [],
          "clientId": "4d8c218e-cf64-4f35-9d0b-cecfd61f971a",
          "automated": false,
          "objectId": "4",
          "isOpen": false,
          "isOnlyLocal": false,
          "attributes": {},
          "system": false,
          "itemLinks": [],
          "openAnnotationVersion": "1.47.1-prod.3",
          "recipeId": "632e6c9b433d0b508cde9dbc",
          "taskId": "632e91ec7eb1331d49af333f",
          "assignmentId": "632e91ed7eb1334452af3341",
          "coordinateVersion": "v1"
        },
        "user": {}
      },
      "creator": "lewis.kalata@es.cloudfactory.com",
      "createdAt": "2022-09-26T18:07:04.063Z",
      "updatedBy": "lewis.kalata@es.cloudfactory.com",
      "updatedAt": "2022-09-26T18:07:04.063Z",
      "hash": "ddfa30245594c022494d496c90342565da94917b",
      "source": "ui"
    },
    {
      "id": "6331ea64336817c29278fd2f",
      "datasetId": "632e6c9aff5edd8643bb923f",
      "itemId": "632e6cca9e465e2da9058028",
      "url": "https://gate.dataloop.ai/api/v1/annotations/6331ea64336817c29278fd2f",
      "item": "https://gate.dataloop.ai/api/v1/items/632e6cca9e465e2da9058028",
      "dataset": "https://gate.dataloop.ai/api/v1/datasets/632e6c9aff5edd8643bb923f",
      "type": "point",
      "label": "model_found_building",
      "attributes": [],
      "coordinates": {
        "x": 572.1476057088566,
        "y": 674.6557857382052,
        "z": 0
      },
      "metadata": {
        "system": {
          "startTime": 0,
          "endTime": 0,
          "frame": 0,
          "endFrame": 0,
          "snapshots_": [],
          "clientId": "70decd77-f272-4bae-8ca3-68467cfe0b50",
          "automated": false,
          "objectId": "5",
          "isOpen": false,
          "isOnlyLocal": false,
          "attributes": {},
          "system": false,
          "itemLinks": [],
          "openAnnotationVersion": "1.47.1-prod.3",
          "recipeId": "632e6c9b433d0b508cde9dbc",
          "taskId": "632e91ec7eb1331d49af333f",
          "assignmentId": "632e91ed7eb1334452af3341",
          "coordinateVersion": "v1"
        },
        "user": {}
      },
      "creator": "lewis.kalata@es.cloudfactory.com",
      "createdAt": "2022-09-26T18:07:32.819Z",
      "updatedBy": "lewis.kalata@es.cloudfactory.com",
      "updatedAt": "2022-09-26T18:07:32.819Z",
      "hash": "7057cf0a56b6dc0713ada36bbd4f9aff8d354e66",
      "source": "ui"
    },
    {
      "id": "6331ea8b544a8ef5fa8eacdb",
      "datasetId": "632e6c9aff5edd8643bb923f",
      "itemId": "632e6cca9e465e2da9058028",
      "url": "https://gate.dataloop.ai/api/v1/annotations/6331ea8b544a8ef5fa8eacdb",
      "item": "https://gate.dataloop.ai/api/v1/items/632e6cca9e465e2da9058028",
      "dataset": "https://gate.dataloop.ai/api/v1/datasets/632e6c9aff5edd8643bb923f",
      "type": "point",
      "label": "building_missed_by_model",
      "attributes": [],
      "coordinates": {
        "x": 768.9480458917458,
        "y": 404.3390924630448,
        "z": 0
      },
      "metadata": {
        "system": {
          "startTime": 0,
          "endTime": 0,
          "frame": 0,
          "endFrame": 0,
          "snapshots_": [],
          "clientId": "060ab8c3-70fa-4a62-ab22-17b0475b0a11",
          "automated": false,
          "objectId": "8",
          "isOpen": false,
          "isOnlyLocal": false,
          "attributes": {},
          "system": false,
          "itemLinks": [],
          "openAnnotationVersion": "1.47.1-prod.3",
          "recipeId": "632e6c9b433d0b508cde9dbc",
          "taskId": "632e91ec7eb1331d49af333f",
          "assignmentId": "632e91ed7eb1334452af3341",
          "coordinateVersion": "v1"
        },
        "user": {}
      },
      "creator": "lewis.kalata@es.cloudfactory.com",
      "createdAt": "2022-09-26T18:08:11.711Z",
      "updatedBy": "lewis.kalata@es.cloudfactory.com",
      "updatedAt": "2022-09-26T18:08:11.711Z",
      "hash": "e20dcc6368b7b4fc3027563f9f9ff3d313839fc8",
      "source": "ui"
    },
    {
      "id": "6331ea8b544a8ef8b58eacdc",
      "datasetId": "632e6c9aff5edd8643bb923f",
      "itemId": "632e6cca9e465e2da9058028",
      "url": "https://gate.dataloop.ai/api/v1/annotations/6331ea8b544a8ef8b58eacdc",
      "item": "https://gate.dataloop.ai/api/v1/items/632e6cca9e465e2da9058028",
      "dataset": "https://gate.dataloop.ai/api/v1/datasets/632e6c9aff5edd8643bb923f",
      "type": "point",
      "label": "model_found_building",
      "attributes": [],
      "coordinates": {
        "x": 657.4509420269553,
        "y": 595.120690186513,
        "z": 0
      },
      "metadata": {
        "system": {
          "startTime": 0,
          "endTime": 0,
          "frame": 0,
          "endFrame": 0,
          "snapshots_": [],
          "clientId": "5744f548-2fb4-4a16-bf1f-290b7efaed42",
          "automated": false,
          "objectId": "7",
          "isOpen": false,
          "isOnlyLocal": false,
          "attributes": {},
          "system": false,
          "itemLinks": [],
          "openAnnotationVersion": "1.47.1-prod.3",
          "recipeId": "632e6c9b433d0b508cde9dbc",
          "taskId": "632e91ec7eb1331d49af333f",
          "assignmentId": "632e91ed7eb1334452af3341",
          "coordinateVersion": "v1"
        },
        "user": {}
      },
      "creator": "lewis.kalata@es.cloudfactory.com",
      "createdAt": "2022-09-26T18:08:11.738Z",
      "updatedBy": "lewis.kalata@es.cloudfactory.com",
      "updatedAt": "2022-09-26T18:08:11.738Z",
      "hash": "5899b182aff9ee5862f39c7c681e38d1542961da",
      "source": "ui"
    },
    {
      "id": "6331ea8b544a8e3c6a8eacdd",
      "datasetId": "632e6c9aff5edd8643bb923f",
      "itemId": "632e6cca9e465e2da9058028",
      "url": "https://gate.dataloop.ai/api/v1/annotations/6331ea8b544a8e3c6a8eacdd",
      "item": "https://gate.dataloop.ai/api/v1/items/632e6cca9e465e2da9058028",
      "dataset": "https://gate.dataloop.ai/api/v1/datasets/632e6c9aff5edd8643bb923f",
      "type": "point",
      "label": "model_found_building",
      "attributes": [],
      "coordinates": {
        "x": 612.7187046894157,
        "y": 629.9497843169926,
        "z": 0
      },
      "metadata": {
        "system": {
          "startTime": 0,
          "endTime": 0,
          "frame": 0,
          "endFrame": 0,
          "snapshots_": [],
          "clientId": "4c1a3d08-5fd0-488f-bb8a-995467d7def0",
          "automated": false,
          "objectId": "6",
          "isOpen": false,
          "isOnlyLocal": false,
          "attributes": {},
          "system": false,
          "itemLinks": [],
          "openAnnotationVersion": "1.47.1-prod.3",
          "recipeId": "632e6c9b433d0b508cde9dbc",
          "taskId": "632e91ec7eb1331d49af333f",
          "assignmentId": "632e91ed7eb1334452af3341",
          "coordinateVersion": "v1"
        },
        "user": {}
      },
      "creator": "lewis.kalata@es.cloudfactory.com",
      "createdAt": "2022-09-26T18:08:11.746Z",
      "updatedBy": "lewis.kalata@es.cloudfactory.com",
      "updatedAt": "2022-09-26T18:08:11.746Z",
      "hash": "5ef49993facd6e168f880e09c5c19bda76cb12c5",
      "source": "ui"
    },
    {
      "id": "6331ea8b544a8e42fd8eacde",
      "datasetId": "632e6c9aff5edd8643bb923f",
      "itemId": "632e6cca9e465e2da9058028",
      "url": "https://gate.dataloop.ai/api/v1/annotations/6331ea8b544a8e42fd8eacde",
      "item": "https://gate.dataloop.ai/api/v1/items/632e6cca9e465e2da9058028",
      "dataset": "https://gate.dataloop.ai/api/v1/datasets/632e6c9aff5edd8643bb923f",
      "type": "point",
      "label": "model_found_building",
      "attributes": [],
      "coordinates": {
        "x": 782.4717455519321,
        "y": 475.03695517566007,
        "z": 0
      },
      "metadata": {
        "system": {
          "startTime": 0,
          "endTime": 0,
          "frame": 0,
          "endFrame": 0,
          "snapshots_": [],
          "clientId": "7075adf8-87f5-4332-b9aa-54cb105c6fa8",
          "automated": false,
          "objectId": "9",
          "isOpen": false,
          "isOnlyLocal": false,
          "attributes": {},
          "system": false,
          "itemLinks": [],
          "openAnnotationVersion": "1.47.1-prod.3",
          "recipeId": "632e6c9b433d0b508cde9dbc",
          "taskId": "632e91ec7eb1331d49af333f",
          "assignmentId": "632e91ed7eb1334452af3341",
          "coordinateVersion": "v1"
        },
        "user": {}
      },
      "creator": "lewis.kalata@es.cloudfactory.com",
      "createdAt": "2022-09-26T18:08:11.750Z",
      "updatedBy": "lewis.kalata@es.cloudfactory.com",
      "updatedAt": "2022-09-26T18:08:11.750Z",
      "hash": "e7244a7bba6bf1e4f76b6adafd5042cbb2eb2e6b",
      "source": "ui"
    },
    {
      "id": "6331eac65575821e0addebb2",
      "datasetId": "632e6c9aff5edd8643bb923f",
      "itemId": "632e6cca9e465e2da9058028",
      "url": "https://gate.dataloop.ai/api/v1/annotations/6331eac65575821e0addebb2",
      "item": "https://gate.dataloop.ai/api/v1/items/632e6cca9e465e2da9058028",
      "dataset": "https://gate.dataloop.ai/api/v1/datasets/632e6c9aff5edd8643bb923f",
      "type": "point",
      "label": "building_missed_by_model",
      "attributes": [],
      "coordinates": {
        "x": 739.2999350982601,
        "y": 526.5008405326373,
        "z": 0
      },
      "metadata": {
        "system": {
          "startTime": 0,
          "endTime": 0,
          "frame": 0,
          "endFrame": 0,
          "snapshots_": [],
          "clientId": "db317481-cf90-4e5c-b208-4e04cff08d87",
          "automated": false,
          "objectId": "10",
          "isOpen": false,
          "isOnlyLocal": false,
          "attributes": {},
          "system": false,
          "itemLinks": [],
          "openAnnotationVersion": "1.47.1-prod.3",
          "recipeId": "632e6c9b433d0b508cde9dbc",
          "taskId": "632e91ec7eb1331d49af333f",
          "assignmentId": "632e91ed7eb1334452af3341",
          "coordinateVersion": "v1"
        },
        "user": {}
      },
      "creator": "lewis.kalata@es.cloudfactory.com",
      "createdAt": "2022-09-26T18:09:10.683Z",
      "updatedBy": "lewis.kalata@es.cloudfactory.com",
      "updatedAt": "2022-09-26T18:09:10.683Z",
      "hash": "7fcdfc03124bf9437cc8ca6bc8a5c3a865c5ff41",
      "source": "ui"
    },
    {
      "id": "6331eac655758215ddddebb3",
      "datasetId": "632e6c9aff5edd8643bb923f",
      "itemId": "632e6cca9e465e2da9058028",
      "url": "https://gate.dataloop.ai/api/v1/annotations/6331eac655758215ddddebb3",
      "item": "https://gate.dataloop.ai/api/v1/items/632e6cca9e465e2da9058028",
      "dataset": "https://gate.dataloop.ai/api/v1/datasets/632e6c9aff5edd8643bb923f",
      "type": "point",
      "label": "building_missed_by_model",
      "attributes": [],
      "coordinates": {
        "x": 700.8094052961912,
        "y": 564.4489580180852,
        "z": 0
      },
      "metadata": {
        "system": {
          "startTime": 0,
          "endTime": 0,
          "frame": 0,
          "endFrame": 0,
          "snapshots_": [],
          "clientId": "703a7fec-c036-44ab-a9a9-0fa5703cc28d",
          "automated": false,
          "objectId": "11",
          "isOpen": false,
          "isOnlyLocal": false,
          "attributes": {},
          "system": false,
          "itemLinks": [],
          "openAnnotationVersion": "1.47.1-prod.3",
          "recipeId": "632e6c9b433d0b508cde9dbc",
          "taskId": "632e91ec7eb1331d49af333f",
          "assignmentId": "632e91ed7eb1334452af3341",
          "coordinateVersion": "v1"
        },
        "user": {}
      },
      "creator": "lewis.kalata@es.cloudfactory.com",
      "createdAt": "2022-09-26T18:09:10.715Z",
      "updatedBy": "lewis.kalata@es.cloudfactory.com",
      "updatedAt": "2022-09-26T18:09:10.715Z",
      "hash": "a89d9a9a18cfc150122ec01bee591096507fa275",
      "source": "ui"
    },
    {
      "id": "6331eae1c39d16f6de7e9e83",
      "datasetId": "632e6c9aff5edd8643bb923f",
      "itemId": "632e6cca9e465e2da9058028",
      "url": "https://gate.dataloop.ai/api/v1/annotations/6331eae1c39d16f6de7e9e83",
      "item": "https://gate.dataloop.ai/api/v1/items/632e6cca9e465e2da9058028",
      "dataset": "https://gate.dataloop.ai/api/v1/datasets/632e6c9aff5edd8643bb923f",
      "type": "point",
      "label": "model_found_building",
      "attributes": [],
      "coordinates": {
        "x": 526.7840629170081,
        "y": 332.3688838328165,
        "z": 0
      },
      "metadata": {
        "system": {
          "startTime": 0,
          "endTime": 0,
          "frame": 0,
          "endFrame": 0,
          "snapshots_": [],
          "clientId": "648190d0-6521-41b5-9296-346ba9e493ce",
          "automated": false,
          "objectId": "13",
          "isOpen": false,
          "isOnlyLocal": false,
          "attributes": {},
          "system": false,
          "itemLinks": [],
          "openAnnotationVersion": "1.47.1-prod.3",
          "recipeId": "632e6c9b433d0b508cde9dbc",
          "taskId": "632e91ec7eb1331d49af333f",
          "assignmentId": "632e91ed7eb1334452af3341",
          "coordinateVersion": "v1"
        },
        "user": {}
      },
      "creator": "lewis.kalata@es.cloudfactory.com",
      "createdAt": "2022-09-26T18:09:37.644Z",
      "updatedBy": "lewis.kalata@es.cloudfactory.com",
      "updatedAt": "2022-09-26T18:09:37.644Z",
      "hash": "e118ea3c9bd60d3b32a531b7d5fc1a9ebaa42cb2",
      "source": "ui"
    },
    {
      "id": "6331eae1c39d1663a27e9e85",
      "datasetId": "632e6c9aff5edd8643bb923f",
      "itemId": "632e6cca9e465e2da9058028",
      "url": "https://gate.dataloop.ai/api/v1/annotations/6331eae1c39d1663a27e9e85",
      "item": "https://gate.dataloop.ai/api/v1/items/632e6cca9e465e2da9058028",
      "dataset": "https://gate.dataloop.ai/api/v1/datasets/632e6c9aff5edd8643bb923f",
      "type": "point",
      "label": "model_found_building",
      "attributes": [],
      "coordinates": {
        "x": 485.1726793472038,
        "y": 367.71781518912417,
        "z": 0
      },
      "metadata": {
        "system": {
          "startTime": 0,
          "endTime": 0,
          "frame": 0,
          "endFrame": 0,
          "snapshots_": [],
          "clientId": "8e6de151-e9d3-4fcf-86b3-4020294b6f36",
          "automated": false,
          "objectId": "12",
          "isOpen": false,
          "isOnlyLocal": false,
          "attributes": {},
          "system": false,
          "itemLinks": [],
          "openAnnotationVersion": "1.47.1-prod.3",
          "recipeId": "632e6c9b433d0b508cde9dbc",
          "taskId": "632e91ec7eb1331d49af333f",
          "assignmentId": "632e91ed7eb1334452af3341",
          "coordinateVersion": "v1"
        },
        "user": {}
      },
      "creator": "lewis.kalata@es.cloudfactory.com",
      "createdAt": "2022-09-26T18:09:37.676Z",
      "updatedBy": "lewis.kalata@es.cloudfactory.com",
      "updatedAt": "2022-09-26T18:09:37.676Z",
      "hash": "b4af853437f72148adfc322b2860a556b3fd8b82",
      "source": "ui"
    },
    {
      "id": "6331eb2aab9d91803ced8086",
      "datasetId": "632e6c9aff5edd8643bb923f",
      "itemId": "632e6cca9e465e2da9058028",
      "url": "https://gate.dataloop.ai/api/v1/annotations/6331eb2aab9d91803ced8086",
      "item": "https://gate.dataloop.ai/api/v1/items/632e6cca9e465e2da9058028",
      "dataset": "https://gate.dataloop.ai/api/v1/datasets/632e6c9aff5edd8643bb923f",
      "type": "point",
      "label": "model_found_building",
      "attributes": [],
      "coordinates": {
        "x": 421.71531940325235,
        "y": 344.8449772526898,
        "z": 0
      },
      "metadata": {
        "system": {
          "startTime": 0,
          "endTime": 0,
          "frame": 0,
          "endFrame": 0,
          "snapshots_": [],
          "clientId": "56516380-b7c8-4617-b394-23128fc11431",
          "automated": false,
          "objectId": "14",
          "isOpen": false,
          "isOnlyLocal": false,
          "attributes": {},
          "system": false,
          "itemLinks": [],
          "openAnnotationVersion": "1.47.1-prod.3",
          "recipeId": "632e6c9b433d0b508cde9dbc",
          "taskId": "632e91ec7eb1331d49af333f",
          "assignmentId": "632e91ed7eb1334452af3341",
          "coordinateVersion": "v1"
        },
        "user": {}
      },
      "creator": "lewis.kalata@es.cloudfactory.com",
      "createdAt": "2022-09-26T18:10:50.644Z",
      "updatedBy": "lewis.kalata@es.cloudfactory.com",
      "updatedAt": "2022-09-26T18:10:50.644Z",
      "hash": "e71596872470801661a30d5c98de06586f63954c",
      "source": "ui"
    },
    {
      "id": "6331eb2aab9d9132fded8087",
      "datasetId": "632e6c9aff5edd8643bb923f",
      "itemId": "632e6cca9e465e2da9058028",
      "url": "https://gate.dataloop.ai/api/v1/annotations/6331eb2aab9d9132fded8087",
      "item": "https://gate.dataloop.ai/api/v1/items/632e6cca9e465e2da9058028",
      "dataset": "https://gate.dataloop.ai/api/v1/datasets/632e6c9aff5edd8643bb923f",
      "type": "point",
      "label": "model_found_building",
      "attributes": [],
      "coordinates": {
        "x": 418.1854865005807,
        "y": 374.76553657390537,
        "z": 0
      },
      "metadata": {
        "system": {
          "startTime": 0,
          "endTime": 0,
          "frame": 0,
          "endFrame": 0,
          "snapshots_": [],
          "clientId": "e2b10b20-cacb-4a77-bb5d-3748eea12a13",
          "automated": false,
          "objectId": "17",
          "isOpen": false,
          "isOnlyLocal": false,
          "attributes": {},
          "system": false,
          "itemLinks": [],
          "openAnnotationVersion": "1.47.1-prod.3",
          "recipeId": "632e6c9b433d0b508cde9dbc",
          "taskId": "632e91ec7eb1331d49af333f",
          "assignmentId": "632e91ed7eb1334452af3341",
          "coordinateVersion": "v1"
        },
        "user": {}
      },
      "creator": "lewis.kalata@es.cloudfactory.com",
      "createdAt": "2022-09-26T18:10:50.646Z",
      "updatedBy": "lewis.kalata@es.cloudfactory.com",
      "updatedAt": "2022-09-26T18:10:50.646Z",
      "hash": "24ad9d111bea7d894c1c26341624be175b0fdb63",
      "source": "ui"
    },
    {
      "id": "6331eb2aab9d915de2ed8088",
      "datasetId": "632e6c9aff5edd8643bb923f",
      "itemId": "632e6cca9e465e2da9058028",
      "url": "https://gate.dataloop.ai/api/v1/annotations/6331eb2aab9d915de2ed8088",
      "item": "https://gate.dataloop.ai/api/v1/items/632e6cca9e465e2da9058028",
      "dataset": "https://gate.dataloop.ai/api/v1/datasets/632e6c9aff5edd8643bb923f",
      "type": "point",
      "label": "model_found_building",
      "attributes": [],
      "coordinates": {
        "x": 399.9805061887913,
        "y": 443.38405038320843,
        "z": 0
      },
      "metadata": {
        "system": {
          "startTime": 0,
          "endTime": 0,
          "frame": 0,
          "endFrame": 0,
          "snapshots_": [],
          "clientId": "8de61453-ce7c-4e48-8d00-df9571639144",
          "automated": false,
          "objectId": "19",
          "isOpen": false,
          "isOnlyLocal": false,
          "attributes": {},
          "system": false,
          "itemLinks": [],
          "openAnnotationVersion": "1.47.1-prod.3",
          "recipeId": "632e6c9b433d0b508cde9dbc",
          "taskId": "632e91ec7eb1331d49af333f",
          "assignmentId": "632e91ed7eb1334452af3341",
          "coordinateVersion": "v1"
        },
        "user": {}
      },
      "creator": "lewis.kalata@es.cloudfactory.com",
      "createdAt": "2022-09-26T18:10:50.647Z",
      "updatedBy": "lewis.kalata@es.cloudfactory.com",
      "updatedAt": "2022-09-26T18:10:50.647Z",
      "hash": "f62002b408f4c52ca39b1cafc861d54870a7d1c8",
      "source": "ui"
    },
    {
      "id": "6331eb2aab9d911bb3ed8084",
      "datasetId": "632e6c9aff5edd8643bb923f",
      "itemId": "632e6cca9e465e2da9058028",
      "url": "https://gate.dataloop.ai/api/v1/annotations/6331eb2aab9d911bb3ed8084",
      "item": "https://gate.dataloop.ai/api/v1/items/632e6cca9e465e2da9058028",
      "dataset": "https://gate.dataloop.ai/api/v1/datasets/632e6c9aff5edd8643bb923f",
      "type": "point",
      "label": "model_found_building",
      "attributes": [],
      "coordinates": {
        "x": 444.71274352633094,
        "y": 405.95577012358865,
        "z": 0
      },
      "metadata": {
        "system": {
          "startTime": 0,
          "endTime": 0,
          "frame": 0,
          "endFrame": 0,
          "snapshots_": [],
          "clientId": "0efab5b2-af7c-48a2-9f8c-e3c2606beff8",
          "automated": false,
          "objectId": "15",
          "isOpen": false,
          "isOnlyLocal": false,
          "attributes": {},
          "system": false,
          "itemLinks": [],
          "openAnnotationVersion": "1.47.1-prod.3",
          "recipeId": "632e6c9b433d0b508cde9dbc",
          "taskId": "632e91ec7eb1331d49af333f",
          "assignmentId": "632e91ed7eb1334452af3341",
          "coordinateVersion": "v1"
        },
        "user": {}
      },
      "creator": "lewis.kalata@es.cloudfactory.com",
      "createdAt": "2022-09-26T18:10:50.641Z",
      "updatedBy": "lewis.kalata@es.cloudfactory.com",
      "updatedAt": "2022-09-26T18:10:50.641Z",
      "hash": "544ea2fe2630f0e3b5c5deb5b99783e3bb31acb8",
      "source": "ui"
    },
    {
      "id": "6331eb2aab9d91b577ed8090",
      "datasetId": "632e6c9aff5edd8643bb923f",
      "itemId": "632e6cca9e465e2da9058028",
      "url": "https://gate.dataloop.ai/api/v1/annotations/6331eb2aab9d91b577ed8090",
      "item": "https://gate.dataloop.ai/api/v1/items/632e6cca9e465e2da9058028",
      "dataset": "https://gate.dataloop.ai/api/v1/datasets/632e6c9aff5edd8643bb923f",
      "type": "point",
      "label": "model_found_building",
      "attributes": [],
      "coordinates": {
        "x": 44.732237337539594,
        "y": 680.9503305089152,
        "z": 0
      },
      "metadata": {
        "system": {
          "startTime": 0,
          "endTime": 0,
          "frame": 0,
          "endFrame": 0,
          "snapshots_": [],
          "clientId": "c22047fa-41c9-474f-a5e6-a8752be020bf",
          "automated": false,
          "objectId": "27",
          "isOpen": false,
          "isOnlyLocal": false,
          "attributes": {},
          "system": false,
          "itemLinks": [],
          "openAnnotationVersion": "1.47.1-prod.3",
          "recipeId": "632e6c9b433d0b508cde9dbc",
          "taskId": "632e91ec7eb1331d49af333f",
          "assignmentId": "632e91ed7eb1334452af3341",
          "coordinateVersion": "v1"
        },
        "user": {}
      },
      "creator": "lewis.kalata@es.cloudfactory.com",
      "createdAt": "2022-09-26T18:10:50.659Z",
      "updatedBy": "lewis.kalata@es.cloudfactory.com",
      "updatedAt": "2022-09-26T18:10:50.659Z",
      "hash": "5bb6bcf136fd6789588c135935048c6cfe7176a3",
      "source": "ui"
    },
    {
      "id": "6331eb2aab9d91a586ed8089",
      "datasetId": "632e6c9aff5edd8643bb923f",
      "itemId": "632e6cca9e465e2da9058028",
      "url": "https://gate.dataloop.ai/api/v1/annotations/6331eb2aab9d91a586ed8089",
      "item": "https://gate.dataloop.ai/api/v1/items/632e6cca9e465e2da9058028",
      "dataset": "https://gate.dataloop.ai/api/v1/datasets/632e6c9aff5edd8643bb923f",
      "type": "point",
      "label": "model_found_building",
      "attributes": [],
      "coordinates": {
        "x": 350.0468459050262,
        "y": 476.6536328362039,
        "z": 0
      },
      "metadata": {
        "system": {
          "startTime": 0,
          "endTime": 0,
          "frame": 0,
          "endFrame": 0,
          "snapshots_": [],
          "clientId": "f06a97f2-618b-4942-87d7-95ead5e9ccae",
          "automated": false,
          "objectId": "20",
          "isOpen": false,
          "isOnlyLocal": false,
          "attributes": {},
          "system": false,
          "itemLinks": [],
          "openAnnotationVersion": "1.47.1-prod.3",
          "recipeId": "632e6c9b433d0b508cde9dbc",
          "taskId": "632e91ec7eb1331d49af333f",
          "assignmentId": "632e91ed7eb1334452af3341",
          "coordinateVersion": "v1"
        },
        "user": {}
      },
      "creator": "lewis.kalata@es.cloudfactory.com",
      "createdAt": "2022-09-26T18:10:50.649Z",
      "updatedBy": "lewis.kalata@es.cloudfactory.com",
      "updatedAt": "2022-09-26T18:10:50.649Z",
      "hash": "050e57a1831678ff13056491113ba6df861d54b2",
      "source": "ui"
    },
    {
      "id": "6331eb2aab9d911dcfed808a",
      "datasetId": "632e6c9aff5edd8643bb923f",
      "itemId": "632e6cca9e465e2da9058028",
      "url": "https://gate.dataloop.ai/api/v1/annotations/6331eb2aab9d911dcfed808a",
      "item": "https://gate.dataloop.ai/api/v1/items/632e6cca9e465e2da9058028",
      "dataset": "https://gate.dataloop.ai/api/v1/datasets/632e6c9aff5edd8643bb923f",
      "type": "point",
      "label": "model_found_building",
      "attributes": [],
      "coordinates": {
        "x": 255.90109057834403,
        "y": 489.1297262560771,
        "z": 0
      },
      "metadata": {
        "system": {
          "startTime": 0,
          "endTime": 0,
          "frame": 0,
          "endFrame": 0,
          "snapshots_": [],
          "clientId": "694de964-61de-4cc2-bfc3-58ad8adb64ee",
          "automated": false,
          "objectId": "21",
          "isOpen": false,
          "isOnlyLocal": false,
          "attributes": {},
          "system": false,
          "itemLinks": [],
          "openAnnotationVersion": "1.47.1-prod.3",
          "recipeId": "632e6c9b433d0b508cde9dbc",
          "taskId": "632e91ec7eb1331d49af333f",
          "assignmentId": "632e91ed7eb1334452af3341",
          "coordinateVersion": "v1"
        },
        "user": {}
      },
      "creator": "lewis.kalata@es.cloudfactory.com",
      "createdAt": "2022-09-26T18:10:50.650Z",
      "updatedBy": "lewis.kalata@es.cloudfactory.com",
      "updatedAt": "2022-09-26T18:10:50.650Z",
      "hash": "92af8561f47b1c5de553e0c3efca948282113d23",
      "source": "ui"
    },
    {
      "id": "6331eb2aab9d916e4ced808f",
      "datasetId": "632e6c9aff5edd8643bb923f",
      "itemId": "632e6cca9e465e2da9058028",
      "url": "https://gate.dataloop.ai/api/v1/annotations/6331eb2aab9d916e4ced808f",
      "item": "https://gate.dataloop.ai/api/v1/items/632e6cca9e465e2da9058028",
      "dataset": "https://gate.dataloop.ai/api/v1/datasets/632e6c9aff5edd8643bb923f",
      "type": "point",
      "label": "model_found_building",
      "attributes": [],
      "coordinates": {
        "x": 150.32112314591794,
        "y": 615.4508400545803,
        "z": 0
      },
      "metadata": {
        "system": {
          "startTime": 0,
          "endTime": 0,
          "frame": 0,
          "endFrame": 0,
          "snapshots_": [],
          "clientId": "2b2f5ec9-8cef-4341-a43a-628050710ae5",
          "automated": false,
          "objectId": "26",
          "isOpen": false,
          "isOnlyLocal": false,
          "attributes": {},
          "system": false,
          "itemLinks": [],
          "openAnnotationVersion": "1.47.1-prod.3",
          "recipeId": "632e6c9b433d0b508cde9dbc",
          "taskId": "632e91ec7eb1331d49af333f",
          "assignmentId": "632e91ed7eb1334452af3341",
          "coordinateVersion": "v1"
        },
        "user": {}
      },
      "creator": "lewis.kalata@es.cloudfactory.com",
      "createdAt": "2022-09-26T18:10:50.658Z",
      "updatedBy": "lewis.kalata@es.cloudfactory.com",
      "updatedAt": "2022-09-26T18:10:50.658Z",
      "hash": "8f55c550f20b6e5990080f3a53251480336c3692",
      "source": "ui"
    },
    {
      "id": "6331eb2aab9d911e94ed8092",
      "datasetId": "632e6c9aff5edd8643bb923f",
      "itemId": "632e6cca9e465e2da9058028",
      "url": "https://gate.dataloop.ai/api/v1/annotations/6331eb2aab9d911e94ed8092",
      "item": "https://gate.dataloop.ai/api/v1/items/632e6cca9e465e2da9058028",
      "dataset": "https://gate.dataloop.ai/api/v1/datasets/632e6c9aff5edd8643bb923f",
      "type": "point",
      "label": "model_found_building",
      "attributes": [],
      "coordinates": {
        "x": 222.09184142787805,
        "y": 582.7004269051267,
        "z": 0
      },
      "metadata": {
        "system": {
          "startTime": 0,
          "endTime": 0,
          "frame": 0,
          "endFrame": 0,
          "snapshots_": [],
          "clientId": "2bc80808-786a-4135-bee3-2b948da7e4a9",
          "automated": false,
          "objectId": "24",
          "isOpen": false,
          "isOnlyLocal": false,
          "attributes": {},
          "system": false,
          "itemLinks": [],
          "openAnnotationVersion": "1.47.1-prod.3",
          "recipeId": "632e6c9b433d0b508cde9dbc",
          "taskId": "632e91ec7eb1331d49af333f",
          "assignmentId": "632e91ed7eb1334452af3341",
          "coordinateVersion": "v1"
        },
        "user": {}
      },
      "creator": "lewis.kalata@es.cloudfactory.com",
      "createdAt": "2022-09-26T18:10:50.655Z",
      "updatedBy": "lewis.kalata@es.cloudfactory.com",
      "updatedAt": "2022-09-26T18:10:50.655Z",
      "hash": "cef1c45b9a58b3543142bf21a0f23be839039ff3",
      "source": "ui"
    },
    {
      "id": "6331eb2aab9d917e6fed808e",
      "datasetId": "632e6c9aff5edd8643bb923f",
      "itemId": "632e6cca9e465e2da9058028",
      "url": "https://gate.dataloop.ai/api/v1/annotations/6331eb2aab9d917e6fed808e",
      "item": "https://gate.dataloop.ai/api/v1/items/632e6cca9e465e2da9058028",
      "dataset": "https://gate.dataloop.ai/api/v1/datasets/632e6c9aff5edd8643bb923f",
      "type": "point",
      "label": "model_found_building",
      "attributes": [],
      "coordinates": {
        "x": 197.13392966194775,
        "y": 633.6451429585622,
        "z": 0
      },
      "metadata": {
        "system": {
          "startTime": 0,
          "endTime": 0,
          "frame": 0,
          "endFrame": 0,
          "snapshots_": [],
          "clientId": "f582edc6-1ad1-46b5-ac32-25c6252fa371",
          "automated": false,
          "objectId": "25",
          "isOpen": false,
          "isOnlyLocal": false,
          "attributes": {},
          "system": false,
          "itemLinks": [],
          "openAnnotationVersion": "1.47.1-prod.3",
          "recipeId": "632e6c9b433d0b508cde9dbc",
          "taskId": "632e91ec7eb1331d49af333f",
          "assignmentId": "632e91ed7eb1334452af3341",
          "coordinateVersion": "v1"
        },
        "user": {}
      },
      "creator": "lewis.kalata@es.cloudfactory.com",
      "createdAt": "2022-09-26T18:10:50.656Z",
      "updatedBy": "lewis.kalata@es.cloudfactory.com",
      "updatedAt": "2022-09-26T18:10:50.656Z",
      "hash": "70044969c0567bbe661202ce7f2939161d6b5f31",
      "source": "ui"
    },
    {
      "id": "6331eb2aab9d912d5aed8085",
      "datasetId": "632e6c9aff5edd8643bb923f",
      "itemId": "632e6cca9e465e2da9058028",
      "url": "https://gate.dataloop.ai/api/v1/annotations/6331eb2aab9d912d5aed8085",
      "item": "https://gate.dataloop.ai/api/v1/items/632e6cca9e465e2da9058028",
      "dataset": "https://gate.dataloop.ai/api/v1/datasets/632e6c9aff5edd8643bb923f",
      "type": "point",
      "label": "model_found_building",
      "attributes": [],
      "coordinates": {
        "x": 380.7352412877569,
        "y": 379.96390883218595,
        "z": 0
      },
      "metadata": {
        "system": {
          "startTime": 0,
          "endTime": 0,
          "frame": 0,
          "endFrame": 0,
          "snapshots_": [],
          "clientId": "3cfc6db8-6cf2-499e-8e36-24a4bb74c074",
          "automated": false,
          "objectId": "16",
          "isOpen": false,
          "isOnlyLocal": false,
          "attributes": {},
          "system": false,
          "itemLinks": [],
          "openAnnotationVersion": "1.47.1-prod.3",
          "recipeId": "632e6c9b433d0b508cde9dbc",
          "taskId": "632e91ec7eb1331d49af333f",
          "assignmentId": "632e91ed7eb1334452af3341",
          "coordinateVersion": "v1"
        },
        "user": {}
      },
      "creator": "lewis.kalata@es.cloudfactory.com",
      "createdAt": "2022-09-26T18:10:50.643Z",
      "updatedBy": "lewis.kalata@es.cloudfactory.com",
      "updatedAt": "2022-09-26T18:10:50.643Z",
      "hash": "3eab615e5a1b7c6bd5d2d9517849ad3ee8812a61",
      "source": "ui"
    },
    {
      "id": "6331eb2aab9d91abc9ed8091",
      "datasetId": "632e6c9aff5edd8643bb923f",
      "itemId": "632e6cca9e465e2da9058028",
      "url": "https://gate.dataloop.ai/api/v1/annotations/6331eb2aab9d91abc9ed8091",
      "item": "https://gate.dataloop.ai/api/v1/items/632e6cca9e465e2da9058028",
      "dataset": "https://gate.dataloop.ai/api/v1/datasets/632e6c9aff5edd8643bb923f",
      "type": "point",
      "label": "model_found_new_building",
      "attributes": [],
      "coordinates": {
        "x": 98.30689368366261,
        "y": 609.7326305704718,
        "z": 0
      },
      "metadata": {
        "system": {
          "startTime": 0,
          "endTime": 0,
          "frame": 0,
          "endFrame": 0,
          "snapshots_": [],
          "clientId": "e3659429-99cb-41ce-ab0b-b3e90ea812b5",
          "automated": false,
          "objectId": "28",
          "isOpen": false,
          "isOnlyLocal": false,
          "attributes": {},
          "system": false,
          "itemLinks": [],
          "openAnnotationVersion": "1.47.1-prod.3",
          "recipeId": "632e6c9b433d0b508cde9dbc",
          "taskId": "632e91ec7eb1331d49af333f",
          "assignmentId": "632e91ed7eb1334452af3341",
          "coordinateVersion": "v1"
        },
        "user": {}
      },
      "creator": "lewis.kalata@es.cloudfactory.com",
      "createdAt": "2022-09-26T18:10:50.663Z",
      "updatedBy": "lewis.kalata@es.cloudfactory.com",
      "updatedAt": "2022-09-26T18:10:50.663Z",
      "hash": "1c0cddb8465534300ebfd3d3e9b5a77b7a8780ff",
      "source": "ui"
    },
    {
      "id": "6331eb2aab9d9172b6ed808c",
      "datasetId": "632e6c9aff5edd8643bb923f",
      "itemId": "632e6cca9e465e2da9058028",
      "url": "https://gate.dataloop.ai/api/v1/annotations/6331eb2aab9d9172b6ed808c",
      "item": "https://gate.dataloop.ai/api/v1/items/632e6cca9e465e2da9058028",
      "dataset": "https://gate.dataloop.ai/api/v1/datasets/632e6c9aff5edd8643bb923f",
      "type": "point",
      "label": "model_found_building",
      "attributes": [],
      "coordinates": {
        "x": 317.27788134380535,
        "y": 515.1215875474799,
        "z": 0
      },
      "metadata": {
        "system": {
          "startTime": 0,
          "endTime": 0,
          "frame": 0,
          "endFrame": 0,
          "snapshots_": [],
          "clientId": "faab3c2c-59d3-4465-bc05-de6d21341a61",
          "automated": false,
          "objectId": "22",
          "isOpen": false,
          "isOnlyLocal": false,
          "attributes": {},
          "system": false,
          "itemLinks": [],
          "openAnnotationVersion": "1.47.1-prod.3",
          "recipeId": "632e6c9b433d0b508cde9dbc",
          "taskId": "632e91ec7eb1331d49af333f",
          "assignmentId": "632e91ed7eb1334452af3341",
          "coordinateVersion": "v1"
        },
        "user": {}
      },
      "creator": "lewis.kalata@es.cloudfactory.com",
      "createdAt": "2022-09-26T18:10:50.666Z",
      "updatedBy": "lewis.kalata@es.cloudfactory.com",
      "updatedAt": "2022-09-26T18:10:50.666Z",
      "hash": "28ac1becda1892ef6fb4ee591e1b8551eec5e67b",
      "source": "ui"
    },
    {
      "id": "6331eb2aab9d911415ed808b",
      "datasetId": "632e6c9aff5edd8643bb923f",
      "itemId": "632e6cca9e465e2da9058028",
      "url": "https://gate.dataloop.ai/api/v1/annotations/6331eb2aab9d911415ed808b",
      "item": "https://gate.dataloop.ai/api/v1/items/632e6cca9e465e2da9058028",
      "dataset": "https://gate.dataloop.ai/api/v1/datasets/632e6c9aff5edd8643bb923f",
      "type": "point",
      "label": "building_missed_by_model",
      "attributes": [],
      "coordinates": {
        "x": 271.5053594170206,
        "y": 542.6729605163666,
        "z": 0
      },
      "metadata": {
        "system": {
          "startTime": 0,
          "endTime": 0,
          "frame": 0,
          "endFrame": 0,
          "snapshots_": [],
          "clientId": "b6fbbecd-4ce3-4a5a-83d9-cc79a22b081b",
          "automated": false,
          "objectId": "23",
          "isOpen": false,
          "isOnlyLocal": false,
          "attributes": {},
          "system": false,
          "itemLinks": [],
          "openAnnotationVersion": "1.47.1-prod.3",
          "recipeId": "632e6c9b433d0b508cde9dbc",
          "taskId": "632e91ec7eb1331d49af333f",
          "assignmentId": "632e91ed7eb1334452af3341",
          "coordinateVersion": "v1"
        },
        "user": {}
      },
      "creator": "lewis.kalata@es.cloudfactory.com",
      "createdAt": "2022-09-26T18:10:50.664Z",
      "updatedBy": "lewis.kalata@es.cloudfactory.com",
      "updatedAt": "2022-09-26T18:10:50.664Z",
      "hash": "7bd9d45937c12f6d173b02824dc822833f3e3873",
      "source": "ui"
    },
    {
      "id": "6331eb2aab9d91ed97ed808d",
      "datasetId": "632e6c9aff5edd8643bb923f",
      "itemId": "632e6cca9e465e2da9058028",
      "url": "https://gate.dataloop.ai/api/v1/annotations/6331eb2aab9d91ed97ed808d",
      "item": "https://gate.dataloop.ai/api/v1/items/632e6cca9e465e2da9058028",
      "dataset": "https://gate.dataloop.ai/api/v1/datasets/632e6c9aff5edd8643bb923f",
      "type": "point",
      "label": "model_found_building",
      "attributes": [],
      "coordinates": {
        "x": 345.36556525342326,
        "y": 416.35251464014965,
        "z": 0
      },
      "metadata": {
        "system": {
          "startTime": 0,
          "endTime": 0,
          "frame": 0,
          "endFrame": 0,
          "snapshots_": [],
          "clientId": "3a262208-3e1c-4a36-ab1d-9f68073200b2",
          "automated": false,
          "objectId": "18",
          "isOpen": false,
          "isOnlyLocal": false,
          "attributes": {},
          "system": false,
          "itemLinks": [],
          "openAnnotationVersion": "1.47.1-prod.3",
          "recipeId": "632e6c9b433d0b508cde9dbc",
          "taskId": "632e91ec7eb1331d49af333f",
          "assignmentId": "632e91ed7eb1334452af3341",
          "coordinateVersion": "v1"
        },
        "user": {}
      },
      "creator": "lewis.kalata@es.cloudfactory.com",
      "createdAt": "2022-09-26T18:10:50.668Z",
      "updatedBy": "lewis.kalata@es.cloudfactory.com",
      "updatedAt": "2022-09-26T18:10:50.668Z",
      "hash": "29f1d44ae805f335aca973f4db0e11ffedd4b359",
      "source": "ui"
    },
    {
      "id": "6331eb505c8ddceaeac9589a",
      "datasetId": "632e6c9aff5edd8643bb923f",
      "itemId": "632e6cca9e465e2da9058028",
      "url": "https://gate.dataloop.ai/api/v1/annotations/6331eb505c8ddceaeac9589a",
      "item": "https://gate.dataloop.ai/api/v1/items/632e6cca9e465e2da9058028",
      "dataset": "https://gate.dataloop.ai/api/v1/datasets/632e6c9aff5edd8643bb923f",
      "type": "point",
      "label": "building_missed_by_model",
      "attributes": [],
      "coordinates": {
        "x": 99.34717827290771,
        "y": 694.6974340018287,
        "z": 0
      },
      "metadata": {
        "system": {
          "startTime": 0,
          "endTime": 0,
          "frame": 0,
          "endFrame": 0,
          "snapshots_": [],
          "clientId": "638eb4fd-93a3-42a3-b309-54b8f30c3793",
          "automated": false,
          "objectId": "31",
          "isOpen": false,
          "isOnlyLocal": false,
          "attributes": {},
          "system": false,
          "itemLinks": [],
          "openAnnotationVersion": "1.47.1-prod.3",
          "recipeId": "632e6c9b433d0b508cde9dbc",
          "taskId": "632e91ec7eb1331d49af333f",
          "assignmentId": "632e91ed7eb1334452af3341",
          "coordinateVersion": "v1"
        },
        "user": {}
      },
      "creator": "lewis.kalata@es.cloudfactory.com",
      "createdAt": "2022-09-26T18:11:28.800Z",
      "updatedBy": "lewis.kalata@es.cloudfactory.com",
      "updatedAt": "2022-09-26T18:11:28.800Z",
      "hash": "6449e1aa22ddba77663df0fdb342218350b11ee2",
      "source": "ui"
    },
    {
      "id": "6331eb505c8ddc4992c9589c",
      "datasetId": "632e6c9aff5edd8643bb923f",
      "itemId": "632e6cca9e465e2da9058028",
      "url": "https://gate.dataloop.ai/api/v1/annotations/6331eb505c8ddc4992c9589c",
      "item": "https://gate.dataloop.ai/api/v1/items/632e6cca9e465e2da9058028",
      "dataset": "https://gate.dataloop.ai/api/v1/datasets/632e6c9aff5edd8643bb923f",
      "type": "point",
      "label": "model_found_building",
      "attributes": [],
      "coordinates": {
        "x": 57.21565240848088,
        "y": 306.4933582743921,
        "z": 0
      },
      "metadata": {
        "system": {
          "startTime": 0,
          "endTime": 0,
          "frame": 0,
          "endFrame": 0,
          "snapshots_": [],
          "clientId": "b57da95d-f43b-48c4-811a-b0c2da7da2dd",
          "automated": false,
          "objectId": "33",
          "isOpen": false,
          "isOnlyLocal": false,
          "attributes": {},
          "system": false,
          "itemLinks": [],
          "openAnnotationVersion": "1.47.1-prod.3",
          "recipeId": "632e6c9b433d0b508cde9dbc",
          "taskId": "632e91ec7eb1331d49af333f",
          "assignmentId": "632e91ed7eb1334452af3341",
          "coordinateVersion": "v1"
        },
        "user": {}
      },
      "creator": "lewis.kalata@es.cloudfactory.com",
      "createdAt": "2022-09-26T18:11:28.805Z",
      "updatedBy": "lewis.kalata@es.cloudfactory.com",
      "updatedAt": "2022-09-26T18:11:28.805Z",
      "hash": "ad074c6f37fbc850ee889a6729951a0e2156fc6b",
      "source": "ui"
    },
    {
      "id": "6331eb505c8ddc0f5fc9589b",
      "datasetId": "632e6c9aff5edd8643bb923f",
      "itemId": "632e6cca9e465e2da9058028",
      "url": "https://gate.dataloop.ai/api/v1/annotations/6331eb505c8ddc0f5fc9589b",
      "item": "https://gate.dataloop.ai/api/v1/items/632e6cca9e465e2da9058028",
      "dataset": "https://gate.dataloop.ai/api/v1/datasets/632e6c9aff5edd8643bb923f",
      "type": "point",
      "label": "model_found_building",
      "attributes": [],
      "coordinates": {
        "x": 18.725122606411926,
        "y": 400.5838961492698,
        "z": 0
      },
      "metadata": {
        "system": {
          "startTime": 0,
          "endTime": 0,
          "frame": 0,
          "endFrame": 0,
          "snapshots_": [],
          "clientId": "e1dc3299-3318-45a7-b991-69126a198e89",
          "automated": false,
          "objectId": "32",
          "isOpen": false,
          "isOnlyLocal": false,
          "attributes": {},
          "system": false,
          "itemLinks": [],
          "openAnnotationVersion": "1.47.1-prod.3",
          "recipeId": "632e6c9b433d0b508cde9dbc",
          "taskId": "632e91ec7eb1331d49af333f",
          "assignmentId": "632e91ed7eb1334452af3341",
          "coordinateVersion": "v1"
        },
        "user": {}
      },
      "creator": "lewis.kalata@es.cloudfactory.com",
      "createdAt": "2022-09-26T18:11:28.802Z",
      "updatedBy": "lewis.kalata@es.cloudfactory.com",
      "updatedAt": "2022-09-26T18:11:28.802Z",
      "hash": "a403ccf32a3f5b5957e07f045e6b6b575abec8e0",
      "source": "ui"
    },
    {
      "id": "6331eb505c8ddc4293c95899",
      "datasetId": "632e6c9aff5edd8643bb923f",
      "itemId": "632e6cca9e465e2da9058028",
      "url": "https://gate.dataloop.ai/api/v1/annotations/6331eb505c8ddc4293c95899",
      "item": "https://gate.dataloop.ai/api/v1/items/632e6cca9e465e2da9058028",
      "dataset": "https://gate.dataloop.ai/api/v1/datasets/632e6c9aff5edd8643bb923f",
      "type": "point",
      "label": "model_found_building",
      "attributes": [],
      "coordinates": {
        "x": 48.893375694520024,
        "y": 732.1257142614485,
        "z": 0
      },
      "metadata": {
        "system": {
          "startTime": 0,
          "endTime": 0,
          "frame": 0,
          "endFrame": 0,
          "snapshots_": [],
          "clientId": "0fa3f3bd-de47-40fb-8653-22d70eb500b3",
          "automated": false,
          "objectId": "30",
          "isOpen": false,
          "isOnlyLocal": false,
          "attributes": {},
          "system": false,
          "itemLinks": [],
          "openAnnotationVersion": "1.47.1-prod.3",
          "recipeId": "632e6c9b433d0b508cde9dbc",
          "taskId": "632e91ec7eb1331d49af333f",
          "assignmentId": "632e91ed7eb1334452af3341",
          "coordinateVersion": "v1"
        },
        "user": {}
      },
      "creator": "lewis.kalata@es.cloudfactory.com",
      "createdAt": "2022-09-26T18:11:28.797Z",
      "updatedBy": "lewis.kalata@es.cloudfactory.com",
      "updatedAt": "2022-09-26T18:11:28.797Z",
      "hash": "41779c2a6b252a0117ce9dfe847bcea36b36691e",
      "source": "ui"
    },
    {
      "id": "6331eb505c8ddc21b5c95898",
      "datasetId": "632e6c9aff5edd8643bb923f",
      "itemId": "632e6cca9e465e2da9058028",
      "url": "https://gate.dataloop.ai/api/v1/annotations/6331eb505c8ddc21b5c95898",
      "item": "https://gate.dataloop.ai/api/v1/items/632e6cca9e465e2da9058028",
      "dataset": "https://gate.dataloop.ai/api/v1/datasets/632e6c9aff5edd8643bb923f",
      "type": "point",
      "label": "model_found_building",
      "attributes": [],
      "coordinates": {
        "x": 230.94317881241375,
        "y": 536.4355817287162,
        "z": 0
      },
      "metadata": {
        "system": {
          "startTime": 0,
          "endTime": 0,
          "frame": 0,
          "endFrame": 0,
          "snapshots_": [],
          "clientId": "4ccf082a-79c2-44ab-be07-7bacc55adc99",
          "automated": false,
          "objectId": "29",
          "isOpen": false,
          "isOnlyLocal": false,
          "attributes": {},
          "system": false,
          "itemLinks": [],
          "openAnnotationVersion": "1.47.1-prod.3",
          "recipeId": "632e6c9b433d0b508cde9dbc",
          "taskId": "632e91ec7eb1331d49af333f",
          "assignmentId": "632e91ed7eb1334452af3341",
          "coordinateVersion": "v1"
        },
        "user": {}
      },
      "creator": "lewis.kalata@es.cloudfactory.com",
      "createdAt": "2022-09-26T18:11:28.793Z",
      "updatedBy": "lewis.kalata@es.cloudfactory.com",
      "updatedAt": "2022-09-26T18:11:28.793Z",
      "hash": "d7e2e3447b7df1850750f866bc17e6bdd100155a",
      "source": "ui"
    },
    {
      "id": "6331eba5526e5c35ffd27a6b",
      "datasetId": "632e6c9aff5edd8643bb923f",
      "itemId": "632e6cca9e465e2da9058028",
      "url": "https://gate.dataloop.ai/api/v1/annotations/6331eba5526e5c35ffd27a6b",
      "item": "https://gate.dataloop.ai/api/v1/items/632e6cca9e465e2da9058028",
      "dataset": "https://gate.dataloop.ai/api/v1/datasets/632e6c9aff5edd8643bb923f",
      "type": "point",
      "label": "model_found_building",
      "attributes": [],
      "coordinates": {
        "x": 84.26305172885365,
        "y": 250.87077511079042,
        "z": 0
      },
      "metadata": {
        "system": {
          "startTime": 0,
          "endTime": 0,
          "frame": 0,
          "endFrame": 0,
          "snapshots_": [],
          "clientId": "3d4a5b04-c182-4cc7-a52c-5b8b4e93c688",
          "automated": false,
          "objectId": "35",
          "isOpen": false,
          "isOnlyLocal": false,
          "attributes": {},
          "system": false,
          "itemLinks": [],
          "openAnnotationVersion": "1.47.1-prod.3",
          "recipeId": "632e6c9b433d0b508cde9dbc",
          "taskId": "632e91ec7eb1331d49af333f",
          "assignmentId": "632e91ed7eb1334452af3341",
          "coordinateVersion": "v1"
        },
        "user": {}
      },
      "creator": "lewis.kalata@es.cloudfactory.com",
      "createdAt": "2022-09-26T18:12:53.973Z",
      "updatedBy": "lewis.kalata@es.cloudfactory.com",
      "updatedAt": "2022-09-26T18:12:53.973Z",
      "hash": "19f816c0258d03b6013e8a0d343d8f0fed06a0b7",
      "source": "ui"
    },
    {
      "id": "6331eba5526e5c14f4d27a6e",
      "datasetId": "632e6c9aff5edd8643bb923f",
      "itemId": "632e6cca9e465e2da9058028",
      "url": "https://gate.dataloop.ai/api/v1/annotations/6331eba5526e5c14f4d27a6e",
      "item": "https://gate.dataloop.ai/api/v1/items/632e6cca9e465e2da9058028",
      "dataset": "https://gate.dataloop.ai/api/v1/datasets/632e6c9aff5edd8643bb923f",
      "type": "point",
      "label": "model_found_building",
      "attributes": [],
      "coordinates": {
        "x": 92.06518614819196,
        "y": 181.32691881595068,
        "z": 0
      },
      "metadata": {
        "system": {
          "startTime": 0,
          "endTime": 0,
          "frame": 0,
          "endFrame": 0,
          "snapshots_": [],
          "clientId": "c804828b-577d-4ca7-b960-5c1e702beb1b",
          "automated": false,
          "objectId": "38",
          "isOpen": false,
          "isOnlyLocal": false,
          "attributes": {},
          "system": false,
          "itemLinks": [],
          "openAnnotationVersion": "1.47.1-prod.3",
          "recipeId": "632e6c9b433d0b508cde9dbc",
          "taskId": "632e91ec7eb1331d49af333f",
          "assignmentId": "632e91ed7eb1334452af3341",
          "coordinateVersion": "v1"
        },
        "user": {}
      },
      "creator": "lewis.kalata@es.cloudfactory.com",
      "createdAt": "2022-09-26T18:12:53.979Z",
      "updatedBy": "lewis.kalata@es.cloudfactory.com",
      "updatedAt": "2022-09-26T18:12:53.979Z",
      "hash": "1111ab9bcef036ce65e6459420c9f4fabfa230d3",
      "source": "ui"
    },
    {
      "id": "6331eba5526e5cc942d27a6c",
      "datasetId": "632e6c9aff5edd8643bb923f",
      "itemId": "632e6cca9e465e2da9058028",
      "url": "https://gate.dataloop.ai/api/v1/annotations/6331eba5526e5cc942d27a6c",
      "item": "https://gate.dataloop.ai/api/v1/items/632e6cca9e465e2da9058028",
      "dataset": "https://gate.dataloop.ai/api/v1/datasets/632e6c9aff5edd8643bb923f",
      "type": "point",
      "label": "model_found_building",
      "attributes": [],
      "coordinates": {
        "x": 19.245264901034478,
        "y": 229.67178081795967,
        "z": 0
      },
      "metadata": {
        "system": {
          "startTime": 0,
          "endTime": 0,
          "frame": 0,
          "endFrame": 0,
          "snapshots_": [],
          "clientId": "7f3e0b92-73b5-4656-96f0-9153ba6bb47d",
          "automated": false,
          "objectId": "36",
          "isOpen": false,
          "isOnlyLocal": false,
          "attributes": {},
          "system": false,
          "itemLinks": [],
          "openAnnotationVersion": "1.47.1-prod.3",
          "recipeId": "632e6c9b433d0b508cde9dbc",
          "taskId": "632e91ec7eb1331d49af333f",
          "assignmentId": "632e91ed7eb1334452af3341",
          "coordinateVersion": "v1"
        },
        "user": {}
      },
      "creator": "lewis.kalata@es.cloudfactory.com",
      "createdAt": "2022-09-26T18:12:53.975Z",
      "updatedBy": "lewis.kalata@es.cloudfactory.com",
      "updatedAt": "2022-09-26T18:12:53.975Z",
      "hash": "1e95720bbe91935db22fa1e99430f135ee799cfb",
      "source": "ui"
    },
    {
      "id": "6331eba5526e5c0a70d27a6a",
      "datasetId": "632e6c9aff5edd8643bb923f",
      "itemId": "632e6cca9e465e2da9058028",
      "url": "https://gate.dataloop.ai/api/v1/annotations/6331eba5526e5c0a70d27a6a",
      "item": "https://gate.dataloop.ai/api/v1/items/632e6cca9e465e2da9058028",
      "dataset": "https://gate.dataloop.ai/api/v1/datasets/632e6c9aff5edd8643bb923f",
      "type": "point",
      "label": "building_missed_by_model",
      "attributes": [],
      "coordinates": {
        "x": 30.168253088108102,
        "y": 285.18003201544195,
        "z": 0
      },
      "metadata": {
        "system": {
          "startTime": 0,
          "endTime": 0,
          "frame": 0,
          "endFrame": 0,
          "snapshots_": [],
          "clientId": "105dc6bd-b1a5-4b40-9fb6-76a1688e4b80",
          "automated": false,
          "objectId": "34",
          "isOpen": false,
          "isOnlyLocal": false,
          "attributes": {},
          "system": false,
          "itemLinks": [],
          "openAnnotationVersion": "1.47.1-prod.3",
          "recipeId": "632e6c9b433d0b508cde9dbc",
          "taskId": "632e91ec7eb1331d49af333f",
          "assignmentId": "632e91ed7eb1334452af3341",
          "coordinateVersion": "v1"
        },
        "user": {}
      },
      "creator": "lewis.kalata@es.cloudfactory.com",
      "createdAt": "2022-09-26T18:12:53.971Z",
      "updatedBy": "lewis.kalata@es.cloudfactory.com",
      "updatedAt": "2022-09-26T18:12:53.971Z",
      "hash": "290feb9107c9eaf8cc2ad7cc21307ede3d5f73cd",
      "source": "ui"
    },
    {
      "id": "6331eba5526e5c6393d27a6d",
      "datasetId": "632e6c9aff5edd8643bb923f",
      "itemId": "632e6cca9e465e2da9058028",
      "url": "https://gate.dataloop.ai/api/v1/annotations/6331eba5526e5c6393d27a6d",
      "item": "https://gate.dataloop.ai/api/v1/items/632e6cca9e465e2da9058028",
      "dataset": "https://gate.dataloop.ai/api/v1/datasets/632e6c9aff5edd8643bb923f",
      "type": "point",
      "label": "model_found_building",
      "attributes": [],
      "coordinates": {
        "x": 59.816363881593645,
        "y": 185.4856166225751,
        "z": 0
      },
      "metadata": {
        "system": {
          "startTime": 0,
          "endTime": 0,
          "frame": 0,
          "endFrame": 0,
          "snapshots_": [],
          "clientId": "fc080e1b-f676-4852-a4f1-9774b1ef1000",
          "automated": false,
          "objectId": "37",
          "isOpen": false,
          "isOnlyLocal": false,
          "attributes": {},
          "system": false,
          "itemLinks": [],
          "openAnnotationVersion": "1.47.1-prod.3",
          "recipeId": "632e6c9b433d0b508cde9dbc",
          "taskId": "632e91ec7eb1331d49af333f",
          "assignmentId": "632e91ed7eb1334452af3341",
          "coordinateVersion": "v1"
        },
        "user": {}
      },
      "creator": "lewis.kalata@es.cloudfactory.com",
      "createdAt": "2022-09-26T18:12:53.977Z",
      "updatedBy": "lewis.kalata@es.cloudfactory.com",
      "updatedAt": "2022-09-26T18:12:53.977Z",
      "hash": "457fc9610935a51954766fd25bf2efe6e53b21af",
      "source": "ui"
    },
    {
      "id": "6331eba5526e5c6072d27a70",
      "datasetId": "632e6c9aff5edd8643bb923f",
      "itemId": "632e6cca9e465e2da9058028",
      "url": "https://gate.dataloop.ai/api/v1/annotations/6331eba5526e5c6072d27a70",
      "item": "https://gate.dataloop.ai/api/v1/items/632e6cca9e465e2da9058028",
      "dataset": "https://gate.dataloop.ai/api/v1/datasets/632e6c9aff5edd8643bb923f",
      "type": "point",
      "label": "model_found_building",
      "attributes": [],
      "coordinates": {
        "x": 281.917123685424,
        "y": 63.8437057788106,
        "z": 0
      },
      "metadata": {
        "system": {
          "startTime": 0,
          "endTime": 0,
          "frame": 0,
          "endFrame": 0,
          "snapshots_": [],
          "clientId": "ebdaa9ea-e9e6-4add-aba5-7e4ecc04bfcb",
          "automated": false,
          "objectId": "42",
          "isOpen": false,
          "isOnlyLocal": false,
          "attributes": {},
          "system": false,
          "itemLinks": [],
          "openAnnotationVersion": "1.47.1-prod.3",
          "recipeId": "632e6c9b433d0b508cde9dbc",
          "taskId": "632e91ec7eb1331d49af333f",
          "assignmentId": "632e91ed7eb1334452af3341",
          "coordinateVersion": "v1"
        },
        "user": {}
      },
      "creator": "lewis.kalata@es.cloudfactory.com",
      "createdAt": "2022-09-26T18:12:53.985Z",
      "updatedBy": "lewis.kalata@es.cloudfactory.com",
      "updatedAt": "2022-09-26T18:12:53.985Z",
      "hash": "488aa1a5a0dee735f6a0a20f85ed21ae17ed205d",
      "source": "ui"
    },
    {
      "id": "6331eba5526e5c95ffd27a6f",
      "datasetId": "632e6c9aff5edd8643bb923f",
      "itemId": "632e6cca9e465e2da9058028",
      "url": "https://gate.dataloop.ai/api/v1/annotations/6331eba5526e5c95ffd27a6f",
      "item": "https://gate.dataloop.ai/api/v1/items/632e6cca9e465e2da9058028",
      "dataset": "https://gate.dataloop.ai/api/v1/datasets/632e6c9aff5edd8643bb923f",
      "type": "point",
      "label": "model_found_building",
      "attributes": [],
      "coordinates": {
        "x": 259.0308627220316,
        "y": 109.06954442585126,
        "z": 0
      },
      "metadata": {
        "system": {
          "startTime": 0,
          "endTime": 0,
          "frame": 0,
          "endFrame": 0,
          "snapshots_": [],
          "clientId": "03972f09-e0df-4c49-8239-bc61870fc996",
          "automated": false,
          "objectId": "41",
          "isOpen": false,
          "isOnlyLocal": false,
          "attributes": {},
          "system": false,
          "itemLinks": [],
          "openAnnotationVersion": "1.47.1-prod.3",
          "recipeId": "632e6c9b433d0b508cde9dbc",
          "taskId": "632e91ec7eb1331d49af333f",
          "assignmentId": "632e91ed7eb1334452af3341",
          "coordinateVersion": "v1"
        },
        "user": {}
      },
      "creator": "lewis.kalata@es.cloudfactory.com",
      "createdAt": "2022-09-26T18:12:53.981Z",
      "updatedBy": "lewis.kalata@es.cloudfactory.com",
      "updatedAt": "2022-09-26T18:12:53.981Z",
      "hash": "525f94db6f773bb12bcf85df1840d221932e1ba9",
      "source": "ui"
    },
    {
      "id": "6331eba5526e5c0600d27a72",
      "datasetId": "632e6c9aff5edd8643bb923f",
      "itemId": "632e6cca9e465e2da9058028",
      "url": "https://gate.dataloop.ai/api/v1/annotations/6331eba5526e5c0600d27a72",
      "item": "https://gate.dataloop.ai/api/v1/items/632e6cca9e465e2da9058028",
      "dataset": "https://gate.dataloop.ai/api/v1/datasets/632e6c9aff5edd8643bb923f",
      "type": "point",
      "label": "model_found_building",
      "attributes": [],
      "coordinates": {
        "x": 183.09008770713882,
        "y": 70.6015897145753,
        "z": 0
      },
      "metadata": {
        "system": {
          "startTime": 0,
          "endTime": 0,
          "frame": 0,
          "endFrame": 0,
          "snapshots_": [],
          "clientId": "581b9044-25cb-4253-817a-732365918fb1",
          "automated": false,
          "objectId": "40",
          "isOpen": false,
          "isOnlyLocal": false,
          "attributes": {},
          "system": false,
          "itemLinks": [],
          "openAnnotationVersion": "1.47.1-prod.3",
          "recipeId": "632e6c9b433d0b508cde9dbc",
          "taskId": "632e91ec7eb1331d49af333f",
          "assignmentId": "632e91ed7eb1334452af3341",
          "coordinateVersion": "v1"
        },
        "user": {}
      },
      "creator": "lewis.kalata@es.cloudfactory.com",
      "createdAt": "2022-09-26T18:12:53.988Z",
      "updatedBy": "lewis.kalata@es.cloudfactory.com",
      "updatedAt": "2022-09-26T18:12:53.988Z",
      "hash": "c1d5edc5b50d8ffd2e4ff08ab53d83acb4cb70b8",
      "source": "ui"
    },
    {
      "id": "6331eba5526e5c1932d27a76",
      "datasetId": "632e6c9aff5edd8643bb923f",
      "itemId": "632e6cca9e465e2da9058028",
      "url": "https://gate.dataloop.ai/api/v1/annotations/6331eba5526e5c1932d27a76",
      "item": "https://gate.dataloop.ai/api/v1/items/632e6cca9e465e2da9058028",
      "dataset": "https://gate.dataloop.ai/api/v1/datasets/632e6c9aff5edd8643bb923f",
      "type": "point",
      "label": "model_found_building",
      "attributes": [],
      "coordinates": {
        "x": 18.725122606411926,
        "y": 722.3457478910416,
        "z": 0
      },
      "metadata": {
        "system": {
          "startTime": 0,
          "endTime": 0,
          "frame": 0,
          "endFrame": 0,
          "snapshots_": [],
          "clientId": "1d8a3559-65d4-4959-bd22-2ebb980c0746",
          "automated": false,
          "objectId": "45",
          "isOpen": false,
          "isOnlyLocal": false,
          "attributes": {},
          "system": false,
          "itemLinks": [],
          "openAnnotationVersion": "1.47.1-prod.3",
          "recipeId": "632e6c9b433d0b508cde9dbc",
          "taskId": "632e91ec7eb1331d49af333f",
          "assignmentId": "632e91ed7eb1334452af3341",
          "coordinateVersion": "v1"
        },
        "user": {}
      },
      "creator": "lewis.kalata@es.cloudfactory.com",
      "createdAt": "2022-09-26T18:12:53.995Z",
      "updatedBy": "lewis.kalata@es.cloudfactory.com",
      "updatedAt": "2022-09-26T18:12:53.995Z",
      "hash": "cf46c3600ae724f60c5e7919a7bfb6156405a885",
      "source": "ui"
    },
    {
      "id": "6331eba5526e5c868fd27a75",
      "datasetId": "632e6c9aff5edd8643bb923f",
      "itemId": "632e6cca9e465e2da9058028",
      "url": "https://gate.dataloop.ai/api/v1/annotations/6331eba5526e5c868fd27a75",
      "item": "https://gate.dataloop.ai/api/v1/items/632e6cca9e465e2da9058028",
      "dataset": "https://gate.dataloop.ai/api/v1/datasets/632e6c9aff5edd8643bb923f",
      "type": "point",
      "label": "model_found_building",
      "attributes": [],
      "coordinates": {
        "x": 279.83655450693374,
        "y": 933.8058347592262,
        "z": 0
      },
      "metadata": {
        "system": {
          "startTime": 0,
          "endTime": 0,
          "frame": 0,
          "endFrame": 0,
          "snapshots_": [],
          "clientId": "a071c4fa-c7dc-4ef1-a687-665c51944c0c",
          "automated": false,
          "objectId": "46",
          "isOpen": false,
          "isOnlyLocal": false,
          "attributes": {},
          "system": false,
          "itemLinks": [],
          "openAnnotationVersion": "1.47.1-prod.3",
          "recipeId": "632e6c9b433d0b508cde9dbc",
          "taskId": "632e91ec7eb1331d49af333f",
          "assignmentId": "632e91ed7eb1334452af3341",
          "coordinateVersion": "v1"
        },
        "user": {}
      },
      "creator": "lewis.kalata@es.cloudfactory.com",
      "createdAt": "2022-09-26T18:12:53.993Z",
      "updatedBy": "lewis.kalata@es.cloudfactory.com",
      "updatedAt": "2022-09-26T18:12:53.993Z",
      "hash": "279ecc11954df670e30525ea4c5408f5608b6c80",
      "source": "ui"
    },
    {
      "id": "6331eba5526e5cbf1dd27a71",
      "datasetId": "632e6c9aff5edd8643bb923f",
      "itemId": "632e6cca9e465e2da9058028",
      "url": "https://gate.dataloop.ai/api/v1/annotations/6331eba5526e5cbf1dd27a71",
      "item": "https://gate.dataloop.ai/api/v1/items/632e6cca9e465e2da9058028",
      "dataset": "https://gate.dataloop.ai/api/v1/datasets/632e6c9aff5edd8643bb923f",
      "type": "point",
      "label": "model_found_building",
      "attributes": [],
      "coordinates": {
        "x": 128.4751467717707,
        "y": 217.19568739808633,
        "z": 0
      },
      "metadata": {
        "system": {
          "startTime": 0,
          "endTime": 0,
          "frame": 0,
          "endFrame": 0,
          "snapshots_": [],
          "clientId": "8d437771-5721-4502-b78e-8ee9568141aa",
          "automated": false,
          "objectId": "39",
          "isOpen": false,
          "isOnlyLocal": false,
          "attributes": {},
          "system": false,
          "itemLinks": [],
          "openAnnotationVersion": "1.47.1-prod.3",
          "recipeId": "632e6c9b433d0b508cde9dbc",
          "taskId": "632e91ec7eb1331d49af333f",
          "assignmentId": "632e91ed7eb1334452af3341",
          "coordinateVersion": "v1"
        },
        "user": {}
      },
      "creator": "lewis.kalata@es.cloudfactory.com",
      "createdAt": "2022-09-26T18:12:53.987Z",
      "updatedBy": "lewis.kalata@es.cloudfactory.com",
      "updatedAt": "2022-09-26T18:12:53.987Z",
      "hash": "091a01be8633e30fe6b5d4c109e09c3ff00b2ea8",
      "source": "ui"
    },
    {
      "id": "6331eba5526e5c89f0d27a73",
      "datasetId": "632e6c9aff5edd8643bb923f",
      "itemId": "632e6cca9e465e2da9058028",
      "url": "https://gate.dataloop.ai/api/v1/annotations/6331eba5526e5c89f0d27a73",
      "item": "https://gate.dataloop.ai/api/v1/items/632e6cca9e465e2da9058028",
      "dataset": "https://gate.dataloop.ai/api/v1/datasets/632e6c9aff5edd8643bb923f",
      "type": "point",
      "label": "model_found_building",
      "attributes": [],
      "coordinates": {
        "x": 250.70858600807077,
        "y": 18.714140129809923,
        "z": 0
      },
      "metadata": {
        "system": {
          "startTime": 0,
          "endTime": 0,
          "frame": 0,
          "endFrame": 0,
          "snapshots_": [],
          "clientId": "4eac6b3e-08a3-4904-b0ef-ef0de8e0a47e",
          "automated": false,
          "objectId": "43",
          "isOpen": false,
          "isOnlyLocal": false,
          "attributes": {},
          "system": false,
          "itemLinks": [],
          "openAnnotationVersion": "1.47.1-prod.3",
          "recipeId": "632e6c9b433d0b508cde9dbc",
          "taskId": "632e91ec7eb1331d49af333f",
          "assignmentId": "632e91ed7eb1334452af3341",
          "coordinateVersion": "v1"
        },
        "user": {}
      },
      "creator": "lewis.kalata@es.cloudfactory.com",
      "createdAt": "2022-09-26T18:12:53.990Z",
      "updatedBy": "lewis.kalata@es.cloudfactory.com",
      "updatedAt": "2022-09-26T18:12:53.990Z",
      "hash": "4e9cb7bf854ced29cfb70985e3ca6c6c43e822f6",
      "source": "ui"
    },
    {
      "id": "6331eba5526e5c06dad27a74",
      "datasetId": "632e6c9aff5edd8643bb923f",
      "itemId": "632e6cca9e465e2da9058028",
      "url": "https://gate.dataloop.ai/api/v1/annotations/6331eba5526e5c06dad27a74",
      "item": "https://gate.dataloop.ai/api/v1/items/632e6cca9e465e2da9058028",
      "dataset": "https://gate.dataloop.ai/api/v1/datasets/632e6c9aff5edd8643bb923f",
      "type": "point",
      "label": "model_found_building",
      "attributes": [],
      "coordinates": {
        "x": 20.285549490279585,
        "y": 770.6906098930506,
        "z": 0
      },
      "metadata": {
        "system": {
          "startTime": 0,
          "endTime": 0,
          "frame": 0,
          "endFrame": 0,
          "snapshots_": [],
          "clientId": "17f118e8-c7fa-452f-8e90-d76be5d6d5c8",
          "automated": false,
          "objectId": "44",
          "isOpen": false,
          "isOnlyLocal": false,
          "attributes": {},
          "system": false,
          "itemLinks": [],
          "openAnnotationVersion": "1.47.1-prod.3",
          "recipeId": "632e6c9b433d0b508cde9dbc",
          "taskId": "632e91ec7eb1331d49af333f",
          "assignmentId": "632e91ed7eb1334452af3341",
          "coordinateVersion": "v1"
        },
        "user": {}
      },
      "creator": "lewis.kalata@es.cloudfactory.com",
      "createdAt": "2022-09-26T18:12:53.992Z",
      "updatedBy": "lewis.kalata@es.cloudfactory.com",
      "updatedAt": "2022-09-26T18:12:53.992Z",
      "hash": "edd3ce41acd9726971b53fbc2956928c208552aa",
      "source": "ui"
    }
  ],
  "annotationsCount": 46,
  "annotated": true
}